Workbook
Name Abos_1: #REF!
Name Abos_1: #REF!
Name Abos_1: #REF!
Name Abos_10: #REF!
Name Abos_10: #REF!
Name Abos_10: #REF!
Name Abos_2: #REF!
Name Abos_2: #REF!
Name Abos_2: #REF!
Name Abos_3: #REF!
Name Abos_3: #REF!
Name Abos_3: #REF!
Name Abos_4: #REF!
Name Abos_4: #REF!
Name Abos_4: #REF!
Name Abos_5: #REF!
Name Abos_5: #REF!
Name Abos_5: #REF!
Name Abos_6: #REF!
Name Abos_6: #REF!
Name Abos_6: #REF!
Name Abos_7: #REF!
Name Abos_7: #REF!
Name Abos_7: #REF!
Name Abos_8: #REF!
Name Abos_8: #REF!
Name Abos_8: #REF!
Name Abos_9: #REF!
Name Abos_9: #REF!
Name Abos_9: #REF!
Name Aufwand: '[1]Drop Downs - Do not delete!'!$E$4:$E$7
Name Aufwand: '[1]Drop Downs - Do not delete!'!$E$4:$E$7
Name Aufwand: '[2]Drop Downs - Do not delete!'!$E$4:$E$7
Name Beratung_1: #REF!
Name Beratung_1: #REF!
Name Beratung_1: #REF!
Name Beratung_10: #REF!
Name Beratung_10: #REF!
Name Beratung_10: #REF!
Name Beratung_2: #REF!
Name Beratung_2: #REF!
Name Beratung_2: #REF!
Name Beratung_3: #REF!
Name Beratung_3: #REF!
Name Beratung_3: #REF!
Name Beratung_4: #REF!
Name Beratung_4: #REF!
Name Beratung_4: #REF!
Name Beratung_5: #REF!
Name Beratung_5: #REF!
Name Beratung_5: #REF!
Name Beratung_6: #REF!
Name Beratung_6: #REF!
Name Beratung_6: #REF!
Name Beratung_7: #REF!
Name Beratung_7: #REF!
Name Beratung_7: #REF!
Name Beratung_8: #REF!
Name Beratung_8: #REF!
Name Beratung_8: #REF!

Sheet Maturity assessment
G2: Rapid.AI - Indirect Procurement Assessment Tool - Questionnaire
C7: Category Levels | F7: Question Theme | G7: Assessment questionnaire | H7: Maturity Range | O7: Lever
B8: Q No. | C8: L1 | D8: L2 | E8: L3 | F8: Question Theme | G8: Questions | H8: Low (1) | I8: Little (2) | J8: Middle (3) | K8: High (4) | L8: Savings% (low) | M8: Savings% (high) | N8: Savings Opportunity | O8: Lever Description | P8: 4 Strategies | Q8: 16 Levers | R8: 64 Methods
A9: =_xlfn.CONCAT(C9,D9,O9) -> Office SuppliesNAConsolidate to max 3 suppliers for all office material spending | B9: 1 | C9: Office Supplies | D9: NA | G9: % Spend with the top 3 suppliers | H9: >60% | I9: >70% | J9: >80% | K9: >90% | L9: 0.01 | M9: 0.02 | N9: =_xlfn.CONCAT(TEXT(L9,"0.0%"),"-",TEXT(M9,"0.0%")) -> 1.0%-2.0% | O9: Consolidate to max 3 suppliers for all office material spending | P9: Leverage Competition Among Suppliers | Q9: Rationalize Supply Base | R9: Consolidate volume/reduce number of suppliers
A10: =_xlfn.CONCAT(C10,D10,O10) -> TravelAirIncluding budget airlines offers cost-effective options and leverages competition to reduce prices. | B10: 2 | C10: Travel | D10: Air | G10: Are budget airlines included in the portal? | H10: No or we do not have a travel portal | I10: No, but can be booked and expensed privately | J10: Yes, without its highlighting | K10: Yes, are displayed as preferred | L10: 0.005 | M10: 0.01 | N10: =_xlfn.CONCAT(TEXT(L10,"0.0%"),"-",TEXT(M10,"0.0%")) -> 0.5%-1.0% | O10: Including budget airlines offers cost-effective options and leverages competition to reduce prices. | P10: Leverage Competition Among Suppliers | Q10: Standardize Specifications | R10: Leverage competition (general)
A11: =_xlfn.CONCAT(C11,D11,O11) -> TravelRailOffering loyalty cards for rail travel reduces costs and enhances travel benefits through rewards. | B11: 3 | C11: Travel | D11: Rail | G11: Are employees able to apply for a loyalty card for the ground transport (rails)? | H11: Yes, anyone can submit a request | I11: After coordination with supervisors, an application can be submitted and approved | J11: Standard business case must be completed | K11: Anyone who regularly rides a train can submit an application | L11: 0.01 | M11: 0.02 | N11: =_xlfn.CONCAT(TEXT(L11,"0.0%"),"-",TEXT(M11,"0.0%")) -> 1.0%-2.0% | O11: Offering loyalty cards for rail travel reduces costs and enhances travel benefits through rewards. | P11: Seek Joint Advantage with Suppliers | Q11: Joint Process Improvement | R11: Improve loyalty programs/discounts
A12: =_xlfn.CONCAT(C12,D12,O12) -> FleetFuelDrive efficiently to save on fuel, reduce maintenance costs, and potentially earn insurance discounts. | B12: 4 | C12: Fleet | D12: Fuel | G12: Are employees incentivized to drive more efficient? | H12: No | I12: Employees are informed about the general policy of efficient driving | J12: Once employees receive a car they can conduct voluntary trainings | K12: Yes - training on efficienct driving is mandatory to take. Telemetic supports transparency | L12: 0.01 | M12: 0.02 | N12: =_xlfn.CONCAT(TEXT(L12,"0.0%"),"-",TEXT(M12,"0.0%")) -> 1.0%-2.0% | O12: Drive efficiently to save on fuel, reduce maintenance costs, and potentially earn insurance discounts. | P12: Change the Nature of Demand | Q12: Reduce Complexity | R12: Improve operational efficiency (e.g., fuel efficiency)
A13: =_xlfn.CONCAT(C13,D13,O13) -> FleetFuelImplement incentives for employees to reduce kilometers traveled, such as rewards for carpooling, using public transport, or biking to work. | B13: 5 | C13: Fleet | D13: Fuel | G13: Are employees incentivized to reduce km travelled? | H13: No | I13: Employees are informed about the general policy of not driving too many kms | J13: For business purposes employees are requested to reduce km allowance of travel | K13: Yes - avoid paying for privatly driven fuel (e.g. through telemetric solution), reduce km allowance of travel | L13: 0.01 | M13: 0.02 | N13: =_xlfn.CONCAT(TEXT(L13,"0.0%"),"-",TEXT(M13,"0.0%")) -> 1.0%-2.0% | O13: Implement incentives for employees to reduce kilometers traveled, such as rewards for carpooling, using public transport, or biking to work. | P13: Change the Nature of Demand | Q13: Reduce Consumption | R13: Incentivize reduced travel
A14: =_xlfn.CONCAT(C14,D14,O14) -> FleetFuelImplementing financial incentives, such as bonuses or matching contributions, encourages employees to save money by directly rewarding their savings efforts. | B14: 6 | C14: Fleet | D14: Fuel | G14: Are employees incentivized to tank at the cheapest station? | H14: No | I14: Employees are informed about fuel grade to purchase and card is limited to the relevant one | J14: In addition to the fuel grade, employees receive app in the beginning | K14: Yes, app for cheapest fuel station nearby is loaded on the phones and positive news coverage on the internal newsletter / incentivation for employees exist/ name & shame list | L14: 0.01 | M14: 0.02 | N14: =_xlfn.CONCAT(TEXT(L14,"0.0%"),"-",TEXT(M14,"0.0%")) -> 1.0%-2.0% | O14: Implementing financial incentives, such as bonuses or matching contributions, encourages employees to save money by directly rewarding their savings efforts. | P14: Change the Nature of Demand | Q14: Reduce Consumption | R14: Incentivize consumption reduction
A15: =_xlfn.CONCAT(C15,D15,O15) -> LegalNAIndicative hourly rates and experience levels allow performance-based project control and provide grounds for complaints if hours significantly exceed estimates. | B15: 7 | C15: Legal | D15: NA | G15: Are hourly rates and experience levels set and controlled for each contract? | H15: No | I15: Only for selected contracts | J15: For the majority of contracts | K15: Yes, completely | L15: 0.01 | M15: 0.02 | N15: =_xlfn.CONCAT(TEXT(L15,"0.0%"),"-",TEXT(M15,"0.0%")) -> 1.0%-2.0% | O15: Indicative hourly rates and experience levels allow performance-based project control and provide grounds for complaints if hours significantly exceed estimates. | P15: Manage Spend | Q15: Control Compliance | R15: Implement performance-based contracts/SLAs
A16: =_xlfn.CONCAT(C16,D16,O16) -> AuditNAIndicative hourly rates and experience levels allow performance-based project control and provide grounds for complaints if hours significantly exceed estimates. | B16: 8 | C16: Audit | D16: NA | G16: Are hourly rates and experience levels set and controlled for each contract? | H16: No | I16: Only for selected contracts | J16: For the majority of contracts | K16: Yes, completely | L16: 0.01 | M16: 0.02 | N16: =_xlfn.CONCAT(TEXT(L16,"0.0%"),"-",TEXT(M16,"0.0%")) -> 1.0%-2.0% | O16: Indicative hourly rates and experience levels allow performance-based project control and provide grounds for complaints if hours significantly exceed estimates. | P16: Manage Spend | Q16: Control Compliance | R16: Implement performance-based contracts/SLAs
A17: =_xlfn.CONCAT(C17,D17,O17) -> HRTrainingConsider training to be conducted internaly, enables to realize savings & build a training 100% to the need of the specific company & culture. | B17: 9 | C17: HR | D17: Training | G17: Are internal resources leverage to conduct trainings? | H17: No, external trainers are used | I17: There are few examples conducted, but they mainly did not work out. | J17: Yes, we have continuously been working on this strategy and overcome the initial downsides. | K17: Yes, around 60-70% of the trainings are conducted with internal experts | L17: 0.01 | M17: 0.02 | N17: =_xlfn.CONCAT(TEXT(L17,"0.0%"),"-",TEXT(M17,"0.0%")) -> 1.0%-2.0% | O17: Consider training to be conducted internaly, enables to realize savings & build a training 100% to the need of the specific company & culture. | P17: Change the Nature of Demand | Q17: Reduce Consumption | R17: Insourcing (for services)
A18: =_xlfn.CONCAT(C18,D18,O18) -> FleetWay of purchasingWithin a RFP ideally fix 1-2 OEMs, to ensure the received discounts are significant. | B18: 10 | C18: Fleet | D18: Way of purchasing | G18: Are preferential OEMs defined (car manufacturer) and pre-negotiated agreements exist? If yes, what is the % share of the top 3 OEMs? | H18: <50% | I18: 50-70% | J18: 70-90% | K18: >90% | L18: 0.01 | M18: 0.02 | N18: =_xlfn.CONCAT(TEXT(L18,"0.0%"),"-",TEXT(M18,"0.0%")) -> 1.0%-2.0% | O18: Within a RFP ideally fix 1-2 OEMs, to ensure the received discounts are significant. | P18: Leverage Competition Among Suppliers | Q18: Target Pricing & Cost modles | R18: Strategic supplier selection (focused)
A19: =_xlfn.CONCAT(C19,D19,O19) -> FleetPolicyImplementing programs to manage underutilized and oversized assets throughout their lifecycle ensures optimal usage and cost distribution. This approach helps in disposing of unnecessary assets, expanding their influence, and efficiently managing workloads with the use of third parties for peak times, resulting in significant cost savings | B19: 11 | C19: Fleet | D19: Policy | G19: Are there programs to reduce underutilized assets (e.g. pool cars) or oversized assets e.g. dispose, expand areas of influence, manage base workload and use 3rd parties for peak? | H19: No - we trust the people driving this topic take care of it | I19: Yes - there are policies existing but controlling is low | J19: Policies existing, controlling in certain countries not overarching | K19: Policies & tracking are regularly conducted, utilization is managed properly | L19: 0.01 | M19: 0.02 | N19: =_xlfn.CONCAT(TEXT(L19,"0.0%"),"-",TEXT(M19,"0.0%")) -> 1.0%-2.0% | O19: Implementing programs to manage underutilized and oversized assets throughout their lifecycle ensures optimal usage and cost distribution. This approach helps in disposing of unnecessary assets, expanding their influence, and efficiently managing workloads with the use of third parties for peak times, resulting in significant cost savings | P19: Change the Nature of Demand | Q19: Optimize Asset Utilization | R19: Optimize asset utilization/dispose of unused assets
A20: =_xlfn.CONCAT(C20,D20,O20) -> Office SuppliesNAUse white label where possible, typically this needs to be > 90% for office suppliers | B20: 12 | C20: Office Supplies | D20: NA | G20: Are white label (no-name brands) products focused? | H20: No | I20: They are offered | J20: They are preferred | K20: Only white lable products can be ordered | L20: 0.02 | M20: 0.04 | N20: =_xlfn.CONCAT(TEXT(L20,"0.0%"),"-",TEXT(M20,"0.0%")) -> 2.0%-4.0% | O20: Use white label where possible, typically this needs to be > 90% for office suppliers | P20: Leverage Competition Among Suppliers | Q20: Standardize Specifications | R20: Use white-label/private label products
... A39: =_xlfn.CONCAT(C39,D39,O39) -> ConsultingNASet-up framework contracts for different types of consulting work, allows to commercially tender and have the right rates in place. | B39: 31 | C39: Consulting | D39: NA | G39: Do you have a pre-qualification process for identifying and selecting qualified consulting providers with relevant experience and expertise in specific areas like compliance or risk management? | H39: No pre-qualification process | I39: Basic pre-qualification exists, but may not be consistently applied | J39: Standardized pre-qualification process ensures qualified consulting providers with relevant experience | K39: Rigorous pre-qualification process evaluates potential providers based on specific criteria aligned with project requirements and industry best practices | L39: 0.005 | M39: 0.01 | N39: =_xlfn.CONCAT(TEXT(L39,"0.0%"),"-",TEXT(M39,"0.0%")) -> 0.5%-1.0% | O39: Set-up framework contracts for different types of consulting work, allows to commercially tender and have the right rates in place. | P39: Leverage Competition Among Suppliers | Q39: Competitive Bidding | R39: Framework agreements
A40: =_xlfn.CONCAT(C40,D40,O40) -> TravelUber/ TaxiEstablishing agreements with taxi/Uber services ensures standardized rates and cost savings. | B40: 32 | C40: Travel | D40: Uber/ Taxi | G40: Do you have company agreements for taxis/ uber? | H40: No - employees can freely chose when they want to use what | K40: Yes- there are agreements with uber as well as taxi companies in place. The policy defines, that employees should primerily use Uber. | L40: 0.02 | M40: 0.04 | N40: =_xlfn.CONCAT(TEXT(L40,"0.0%"),"-",TEXT(M40,"0.0%")) -> 2.0%-4.0% | O40: Establishing agreements with taxi/Uber services ensures standardized rates and cost savings. | P40: Leverage Competition Among Suppliers | Q40: Competitive Bidding | R40: Negotiate framework agreements (travel)
A41: =_xlfn.CONCAT(C41,D41,O41) -> TravelHotelMaintaining an LRA rate card ensures standardized rates, fostering relationships and cost efficiencies. | B41: 33 | C41: Travel | D41: Hotel | G41: Do you have LRA rate card with Tier 1/Tier 2 hotel chains across top cities of travel? | H41: No LRA rate card | I41: LRA rate card with Tier 1 hotels only | J41: LRA rate card with Tier 2 hotels only | K41: LRA rate card with both Tier 1 and Tier 2 hotels | L41: 0.005 | M41: 0.01 | N41: =_xlfn.CONCAT(TEXT(L41,"0.0%"),"-",TEXT(M41,"0.0%")) -> 0.5%-1.0% | O41: Maintaining an LRA rate card ensures standardized rates, fostering relationships and cost efficiencies. | P41: Manage Spend | Q41: Control Compliance | R41: Standardize rate cards
A42: =_xlfn.CONCAT(C42,D42,O42) -> TravelCar RentalPartnering with preferred car rental providers ensures cost-effective rental options. | B42: 34 | C42: Travel | D42: Car Rental | G42: Do you have preferred partners with negotiated rates for Car rentals? | H42: No preferred partners | I42: Some preferred partners with minimal negotiations | J42: Preferred partners with standard negotiated rates | K42: Extensive preferred partners with comprehensive negotiated rates | L42: 0.01 | M42: 0.02 | N42: =_xlfn.CONCAT(TEXT(L42,"0.0%"),"-",TEXT(M42,"0.0%")) -> 1.0%-2.0% | O42: Partnering with preferred car rental providers ensures cost-effective rental options. | P42: Seek Joint Advantage with Suppliers | Q42: Joint Process Improvement | R42: Develop preferred supplier relationships (travel)
A43: =_xlfn.CONCAT(C43,D43,O43) -> ITSoftware development and maintenanceConsolidate contracts by developing small suppliers and establishing a preferred supplier pool for major development. Transition to fixed pricing with risk-sharing mechanisms and establish SLA guidelines to track compliance and shortcomings. | B43: 35 | C43: IT | D43: Software development and maintenance | G43: Do you have strategic supplier pools serving different needs? | H43: No | I43: - | J43: Only partially | K43: Yes | L43: 0.01 | M43: 0.02 | N43: =_xlfn.CONCAT(TEXT(L43,"0.0%"),"-",TEXT(M43,"0.0%")) -> 1.0%-2.0% | O43: Consolidate contracts by developing small suppliers and establishing a preferred supplier pool for major development. Transition to fixed pricing with risk-sharing mechanisms and establish SLA guidelines to track compliance and shortcomings. | P43: Leverage Competition Among Suppliers | Q43: Rationalize Supply Base | R43: Consolidate contracts & suppliers
A44: =_xlfn.CONCAT(C44,D44,O44) -> ITSoftware development and maintenanceLeveraging AI-based models can automate some parts of development and testing; thus reducing time and resource needs. This innovative approach minimizes manual tasks, cuts operational costs and boosts efficiency. | B44: 36 | C44: IT | D44: Software development and maintenance | G44: Do you leverage AI for development/ testing activities? | H44: Not at all | I44: Rarely | J44: Partially | K44: Fully | L44: 0.005 | M44: 0.01 | N44: =_xlfn.CONCAT(TEXT(L44,"0.0%"),"-",TEXT(M44,"0.0%")) -> 0.5%-1.0% | O44: Leveraging AI-based models can automate some parts of development and testing; thus reducing time and resource needs. This innovative approach minimizes manual tasks, cuts operational costs and boosts efficiency. | P44: Change the Nature of Demand | Q44: Reduce Complexity | R44: Automate processes (development/testing)
A45: =_xlfn.CONCAT(C45,D45,O45) -> ITIT helpdeskAutomating help desk inquiries with AI cuts support costs and frees up resources for complex issues. | B45: 37 | C45: IT | D45: IT helpdesk | G45: Do you leverage the full potential of AI to process help desk inquiries automatically? | H45: Not at all | I45: Rarely | J45: Partially | K45: Fully | L45: 0.015 | M45: 0.03 | N45: =_xlfn.CONCAT(TEXT(L45,"0.0%"),"-",TEXT(M45,"0.0%")) -> 1.5%-3.0% | O45: Automating help desk inquiries with AI cuts support costs and frees up resources for complex issues. | P45: Change the Nature of Demand | Q45: Reduce Complexity | R45: Automate processes (help desk)
A46: =_xlfn.CONCAT(C46,D46,O46) -> TravelPolicyPartnering with a travel agency streamlines bookings and leverages discounts, reducing travel costs. | B46: 38 | C46: Travel | D46: Policy | G46: Do you use Travel Agency for all your bookings? If not, what percentage of your bookings go through Client’s Travel Agency ? | H46: No travel agency used | I46: Less than 50% of bookings through the agency | J46: 50-70% of bookings through the agency | K46: More than 70% of bookings through the agency | L46: 0.01 | M46: 0.02 | N46: =_xlfn.CONCAT(TEXT(L46,"0.0%"),"-",TEXT(M46,"0.0%")) -> 1.0%-2.0% | O46: Partnering with a travel agency streamlines bookings and leverages discounts, reducing travel costs. | P46: Leverage Competition Among Suppliers | Q46: Consolidate Volume | R46: Consolidate travel agencies
A47: =_xlfn.CONCAT(C47,D47,O47) -> LogisticsLOG OceanUnbundled rates with categorized services for flexible cost management. | B47: 39 | C47: Logistics | D47: LOG Ocean | G47: Do you work with all-in rates or are these unbundled, e.g., comparing door-door with forwarder vs. port-port with self-managed pre-/on-carriage? | H47: All-in rates | I47: Mixed with more all-in rates | J47: Mixed with more unbundled rates | K47: Unbundled rates | L47: 0.01 | M47: 0.02 | N47: =_xlfn.CONCAT(TEXT(L47,"0.0%"),"-",TEXT(M47,"0.0%")) -> 1.0%-2.0% | O47: Unbundled rates with categorized services for flexible cost management. | P47: Manage Spend | Q47: Control Compliance | R47: Unbundle rates/services
A48: =_xlfn.CONCAT(C48,D48,O48) -> LogisticsRoad LogisticsStandard tenders focus on quotes and supplier margins, while expressive bidding also addresses systemic costs through volume discounts, bundle discounts, and alternative bids, leading to lower rates. | B48: 40 | C48: Logistics | D48: Road Logistics | G48: Do you work with all-in rates or are these unbundled, e.g., with separate fuel floater and surcharges? | H48: All-in rates | I48: Mixed with more all-in rates | J48: Mixed with more unbundled rates | K48: Unbundled rates | L48: 0.0025 | M48: 0.005 | N48: =_xlfn.CONCAT(TEXT(L48,"0.0%"),"-",TEXT(M48,"0.0%")) -> 0.3%-0.5% | O48: Standard tenders focus on quotes and supplier margins, while expressive bidding also addresses systemic costs through volume discounts, bundle discounts, and alternative bids, leading to lower rates. | P48: Leverage Competition Among Suppliers | Q48: Competitive Bidding | R48: Expressive bidding
A49: =_xlfn.CONCAT(C49,D49,O49) -> PackagingNACost-based price modeling is a process-oriented method for determining target prices. The basis for target prices are the individual process steps, to which reference values are applied. | B49: 41 | C49: Packaging | D49: NA | G49: Do your contracts include any sort of price adjustment mechanisms based on raw material indexes? | H49: No price adjustment clauses - fixed contract pricing only | I49: No automatic price adjustment clause, but regular (e.g. half-yearly) price negotiations | J49: Price adjustment clauses for the main categories in terms of spend | K49: Price adjustements for all contracts | L49: 0.025 | M49: 0.05 | N49: =_xlfn.CONCAT(TEXT(L49,"0.0%"),"-",TEXT(M49,"0.0%")) -> 2.5%-5.0% | O49: Cost-based price modeling is a process-oriented method for determining target prices. The basis for target prices are the individual process steps, to which reference values are applied. | P49: Leverage Competition Among Suppliers | Q49: Target Pricing & Cost Models | R49: Implement cost-based price modeling
A50: =_xlfn.CONCAT(C50,D50,O50) -> TravelAirDefining and enforcing flight class policies ensures cost-effective travel options. | B50: 42 | C50: Travel | D50: Air | G50: Flight: What classes can be booked? | H50: Not specified | I50: Business Class > 3 hours | J50: Business Class > 5 hours | K50: Only Economy Class | L50: 0.015 | M50: 0.03 | N50: =_xlfn.CONCAT(TEXT(L50,"0.0%"),"-",TEXT(M50,"0.0%")) -> 1.5%-3.0% | O50: Defining and enforcing flight class policies ensures cost-effective travel options. | P50: Manage Spend | Q50: Control Compliance | R50: Enforce travel policies (flight class)
A51: =_xlfn.CONCAT(C51,D51,O51) -> FleetPolicyLeasing duration can vary, offering flexibility in lease terms to suit different needs. | B51: 43 | C51: Fleet | D51: Policy | G51: For leasing cars with defined return date (closed-end lease cars): What is the typical leasing duration? | H51: Very diverse, depending who orders them | I51: Around 2 years as a standard | J51: Around 3 years as a standard | K51: 4-5 years, depending on the country (road conditions) | L51: 0.0025 | M51: 0.005 | N51: =_xlfn.CONCAT(TEXT(L51,"0.0%"),"-",TEXT(M51,"0.0%")) -> 0.3%-0.5% | O51: Leasing duration can vary, offering flexibility in lease terms to suit different needs. | P51: Change the Nature of Demand | Q51: Optimize Asset Utilization | R51: Flexible leasing terms
A52: =_xlfn.CONCAT(C52,D52,O52) -> MarketingPOS MaterialMove POS material to digital screens | B52: 44 | C52: Marketing | D52: POS Material | G52: For that % of current POS material that could be replaced with digital - what is the business case? | H52: Significant | I52: Good | J52: Low | K52: No business case | L52: 0.015 | M52: 0.03 | N52: =_xlfn.CONCAT(TEXT(L52,"0.0%"),"-",TEXT(M52,"0.0%")) -> 1.5%-3.0% | O52: Move POS material to digital screens | P52: Change the Nature of Demand | Q52: Reduce Consumption | R52: Substitute materials/processes (digital)
... A78: =_xlfn.CONCAT(C78,D78,O78) -> Temp LabourNAGlobal RFPs are conducted every 2-3 years, requesting additional savings ideas (e.g., reducing equal pay in Germany). | B78: 70 | C78: Temp Labour | D78: NA | G78: How is temp labour sourcing conducted? | H78: Every site/ BU sources their temp labour agencies individually | I78: BU bundle their volumes so that truly global volumes are put on the market | J78: Next to hourly rate and multiplier also other benefits are requested, e.g. free trainings, additional ideas to circumvent high payment | K78: Global RFPs are conducted and additional ideas for savings are requested (e.g. reduction of equal pay in Germany) | L78: 0.005 | M78: 0.01 | N78: =_xlfn.CONCAT(TEXT(L78,"0.0%"),"-",TEXT(M78,"0.0%")) -> 0.5%-1.0% | O78: Global RFPs are conducted every 2-3 years, requesting additional savings ideas (e.g., reducing equal pay in Germany). | P78: Leverage Competition Among Suppliers | Q78: Competitive Bidding | R78: Conduct global RFPs (regularly)
A79: =_xlfn.CONCAT(C79,D79,O79) -> HRTrainingStreamlining the training approval process and ensuring adherence to guidelines results in efficient procurement and cost savings | B79: 71 | C79: HR | D79: Training | G79: How is the approval process for training set-up? | H79: The employees does the training he wishes for | I79: The employee needs to discuss the trainings with his boss | K79: There is a rigorous approval process for trainings outside of prescribed catalogue and preferred partner network | L79: 0.015 | M79: 0.03 | N79: =_xlfn.CONCAT(TEXT(L79,"0.0%"),"-",TEXT(M79,"0.0%")) -> 1.5%-3.0% | O79: Streamlining the training approval process and ensuring adherence to guidelines results in efficient procurement and cost savings | P79: Manage Spend | Q79: Improve Process Efficiency | R79: Streamline approval processes
A80: =_xlfn.CONCAT(C80,D80,O80) -> ITEnd user/ Workplace HardwareStandardized hardware specifications / product variants. This enables more efficient sourcing & buying, along with better consistency and more streamlined support processes. | B80: 72 | C80: IT | D80: End user/ Workplace Hardware | G80: How is the specification of the HW defined? | H80: The specification is defined according to what the employees ask for. | I80: - | J80: Employee's needs are assessed and based on the relevant user group the specification is assigned to. | K80: Within a collaborative optimization the features are evaluated in monetary terms and decisions are based on them. | L80: 0.01 | M80: 0.02 | N80: =_xlfn.CONCAT(TEXT(L80,"0.0%"),"-",TEXT(M80,"0.0%")) -> 1.0%-2.0% | O80: Standardized hardware specifications / product variants. This enables more efficient sourcing & buying, along with better consistency and more streamlined support processes. | P80: Change the Nature of Demand | Q80: Optimize Specifications | R80: Standardize hardware specifications
A81: =_xlfn.CONCAT(C81,D81,O81) -> Facility ManagementNAEstablish a central Facility Management organization for easier service provider monitoring, increased transparency, and better control over categories and services. | B81: 73 | C81: Facility Management | D81: NA | G81: How is your facility management organized? | H81: Not organized | I81: Local | J81: Regional | K81: Central | L81: 0.005 | M81: 0.01 | N81: =_xlfn.CONCAT(TEXT(L81,"0.0%"),"-",TEXT(M81,"0.0%")) -> 0.5%-1.0% | O81: Establish a central Facility Management organization for easier service provider monitoring, increased transparency, and better control over categories and services. | P81: Manage Spend | Q81: Improve Process Efficiency | R81: Centralize FM organization
A82: =_xlfn.CONCAT(C82,D82,O82) -> TravelTravel Management AgencyConsolidating travel agencies leverages volume bundling, reducing costs through economies of scale. | B82: 74 | C82: Travel | D82: Travel Management Agency | G82: How many active travel agencies are you working with? | H82: Every country has its own | I82: 30% spend bundled to one agency | J82: 60% spend bundled to one agency | K82: Close to 100% bundled to one agency | L82: 0.02 | M82: 0.04 | N82: =_xlfn.CONCAT(TEXT(L82,"0.0%"),"-",TEXT(M82,"0.0%")) -> 2.0%-4.0% | O82: Consolidating travel agencies leverages volume bundling, reducing costs through economies of scale. | P82: Leverage Competition Among Suppliers | Q82: Consolidate Volume | R82: Consolidate travel agencies
A83: =_xlfn.CONCAT(C83,D83,O83) -> LogisticsRoad LogisticsIn the current market, carriers can cherry-pick customers and loads, so it's crucial to become a shipper of choice by enhancing warehouse infrastructure and improving communication with carriers. | B83: 75 | C83: Logistics | D83: Road Logistics | G83: How many carriers did participate in the last tender? | H83: <5 | I83: 5-10 | J83: 10-25 | K83: >25 | L83: 0.0025 | M83: 0.005 | N83: =_xlfn.CONCAT(TEXT(L83,"0.0%"),"-",TEXT(M83,"0.0%")) -> 0.3%-0.5% | O83: In the current market, carriers can cherry-pick customers and loads, so it's crucial to become a shipper of choice by enhancing warehouse infrastructure and improving communication with carriers. | P83: Seek Joint Advantage with Suppliers | Q83: Joint Capacity & Planning | R83: Become shipper of choice
A84: =_xlfn.CONCAT(C84,D84,O84) -> LogisticsLOG OceanLeveraging carrier participation for competitive ocean freight rates. | B84: 76 | C84: Logistics | D84: LOG Ocean | G84: How many carriers did participate in the last tender? | H84: <5 | I84: 5-10 | J84: 10-15 | K84: >15 | L84: 0.005 | M84: 0.01 | N84: =_xlfn.CONCAT(TEXT(L84,"0.0%"),"-",TEXT(M84,"0.0%")) -> 0.5%-1.0% | O84: Leveraging carrier participation for competitive ocean freight rates. | P84: Leverage Competition Among Suppliers | Q84: Competitive Bidding | R84: Leverage carrier participation
A85: =_xlfn.CONCAT(C85,D85,O85) -> LogisticsRoad LogisticsTransportation is often managed by a long-term partner with premium rates, but regularly seeking multiple quotes for large volumes helps identify alternatives and true market rates. | B85: 77 | C85: Logistics | D85: Road Logistics | G85: How many carriers do you have on your contact longlist? | H85: >50 | I85: 25-50 | J85: 25-10 | K85: <10 | L85: 0.0025 | M85: 0.005 | N85: =_xlfn.CONCAT(TEXT(L85,"0.0%"),"-",TEXT(M85,"0.0%")) -> 0.3%-0.5% | O85: Transportation is often managed by a long-term partner with premium rates, but regularly seeking multiple quotes for large volumes helps identify alternatives and true market rates. | P85: Leverage Competition Among Suppliers | Q85: Competitive Bidding | R85: Benchmark and seek multiple quotes
A86: =_xlfn.CONCAT(C86,D86,O86) -> LogisticsLOG OceanOptimize carrier network by consolidating suppliers into specific categories. | B86: 78 | C86: Logistics | D86: LOG Ocean | G86: How many carriers do you have on your contact longlist? | H86: <10 | I86: 10-20 | J86: 20-30 | K86: >30 | L86: 0.005 | M86: 0.01 | N86: =_xlfn.CONCAT(TEXT(L86,"0.0%"),"-",TEXT(M86,"0.0%")) -> 0.5%-1.0% | O86: Optimize carrier network by consolidating suppliers into specific categories. | P86: Leverage Competition Among Suppliers | Q86: Rationalize Supply Base | R86: Optimize carrier network/consolidate suppliers
A87: =_xlfn.CONCAT(C87,D87,O87) -> Facility ManagementNATrack and monitor a critical number of KPIs for effective governance; avoid too few or too many (over 15) KPIs to manage monitoring efforts efficiently. | B87: 79 | C87: Facility Management | D87: NA | G87: How many KPIs do you have in place to monitor the performance of the facility management providers? | H87: No KPIs defined | I87: >15 | J87: 10-15 | K87: 5-10 | L87: 0.01 | M87: 0.02 | N87: =_xlfn.CONCAT(TEXT(L87,"0.0%"),"-",TEXT(M87,"0.0%")) -> 1.0%-2.0% | O87: Track and monitor a critical number of KPIs for effective governance; avoid too few or too many (over 15) KPIs to manage monitoring efforts efficiently. | P87: Manage Spend | Q87: Control Compliance | R87: Implement effective KPI monitoring
A88: =_xlfn.CONCAT(C88,D88,O88) -> TravelPolicyEvaluating travel flexibility balances cost control with business needs, optimizing travel spend. | B88: 80 | C88: Travel | D88: Policy | G88: How much flexibility does your department require when travelling? | H88: Complete flexibility | I88: Limited flexibility within predefined policies | J88: Strict adherence to policies | K88: Case-by-case flexibility based on approval | L88: 0.01 | M88: 0.02 | N88: =_xlfn.CONCAT(TEXT(L88,"0.0%"),"-",TEXT(M88,"0.0%")) -> 1.0%-2.0% | O88: Evaluating travel flexibility balances cost control with business needs, optimizing travel spend. | P88: Change the Nature of Demand | Q88: Optimize Service Levels | R88: Evaluate travel flexibility
A89: =_xlfn.CONCAT(C89,D89,O89) -> ITSoftware licensesReduce the number of software license providers to enhance bargaining power. | B89: 81 | C89: IT | D89: Software licenses | G89: How much of your license spend is with preferred suppliers? | H89: <20% | I89: 20-60% | J89: 60-80% | K89: 80-100% | L89: 0.015 | M89: 0.03 | N89: =_xlfn.CONCAT(TEXT(L89,"0.0%"),"-",TEXT(M89,"0.0%")) -> 1.5%-3.0% | O89: Reduce the number of software license providers to enhance bargaining power. | P89: Leverage Competition Among Suppliers | Q89: Rationalize Supply Base | R89: Reduce number of software license providers
A90: =_xlfn.CONCAT(C90,D90,O90) -> PackagingNAThis organization is characterized by the permanent concentration of decision makers in one place plus a dynamic planning process. Via improved information flow, disruption costs are avoided. | B90: 82 | C90: Packaging | D90: NA | G90: How much of your packaging spend is purchased from distributors? | H90: >75% | I90: 75-50% | J90: 50-25% | K90: <25% | L90: 0.035 | M90: 0.07 | N90: =_xlfn.CONCAT(TEXT(L90,"0.0%"),"-",TEXT(M90,"0.0%")) -> 3.5%-7.0% | O90: This organization is characterized by the permanent concentration of decision makers in one place plus a dynamic planning process. Via improved information flow, disruption costs are avoided. | P90: Manage Spend | Q90: Improve Process Efficiency | R90: Improve information flow/centralize planning
A91: =_xlfn.CONCAT(C91,D91,O91) -> ConsultingNASetting up budgets for consultancy is a base step in establising a forecast and ensure Procurement can create meaningful framework contracts. | B91: 83 | C91: Consulting | D91: NA | G91: How much spend is reviewed every year for budgeting? | H91: <40% | I91: 40-60% | J91: 60-80% | K91: 80-100% | L91: 0.015 | M91: 0.03 | N91: =_xlfn.CONCAT(TEXT(L91,"0.0%"),"-",TEXT(M91,"0.0%")) -> 1.5%-3.0% | O91: Setting up budgets for consultancy is a base step in establising a forecast and ensure Procurement can create meaningful framework contracts. | P91: Manage Spend | Q91: Improve Process Efficiency | R91: Set up budgets/forecasts (consultancy)
... A103: =_xlfn.CONCAT(C103,D103,O103) -> MarketingTraditional MediaFor TV/radio, secure agency commitments based on the total campaign cost rather than just the price per unit. Secure agency commitments for TV/radio based on total campaign cost, not just unit price. | B103: 95 | C103: Marketing | D103: Traditional Media | G103: Is agency using the TCOC targets established during pitch for campaign planning? | H103: Never | I103: For some campaigns | J103: For most campaigns | K103: Always | L103: 0.015 | M103: 0.03 | N103: =_xlfn.CONCAT(TEXT(L103,"0.0%"),"-",TEXT(M103,"0.0%")) -> 1.5%-3.0% | O103: For TV/radio, secure agency commitments based on the total campaign cost rather than just the price per unit. Secure agency commitments for TV/radio based on total campaign cost, not just unit price. | P103: Manage Spend | Q103: Control Compliance | R103: Secure total campaign cost commitments
A104: =_xlfn.CONCAT(C104,D104,O104) -> MarketingPOS MaterialDefine one integrator, who takes care of the whole SC and demand management of POS material | B104: 96 | C104: Marketing | D104: POS Material | G104: Is an POS Material& Print supplier in place | H104: No | I104: Partially, some other agencies exists | K104: Yes | L104: 0.015 | M104: 0.03 | N104: =_xlfn.CONCAT(TEXT(L104,"0.0%"),"-",TEXT(M104,"0.0%")) -> 1.5%-3.0% | O104: Define one integrator, who takes care of the whole SC and demand management of POS material | P104: Seek Joint Advantage with Suppliers | Q104: Joint Process Improvement | R104: Appoint single integrator (POS)
A105: =_xlfn.CONCAT(C105,D105,O105) -> Facility ManagementNACentralize service standards for better SLA control and harmonization across locations, simplifying service provider management. | B105: 97 | C105: Facility Management | D105: NA | G105: Is the standard of these Soft services determined centrally or decentrally? | H105: Determined by demand owners individually | I105: Local | J105: Regional | K105: Central | L105: 0.01 | M105: 0.02 | N105: =_xlfn.CONCAT(TEXT(L105,"0.0%"),"-",TEXT(M105,"0.0%")) -> 1.0%-2.0% | O105: Centralize service standards for better SLA control and harmonization across locations, simplifying service provider management. | P105: Manage Spend | Q105: Improve Process Efficiency | R105: Centralize service standards/SLAs
A106: =_xlfn.CONCAT(C106,D106,O106) -> FleetWay of purchasingExpand fixed elements in framework agreements for better structure and clarity. | B106: 98 | C106: Fleet | D106: Way of purchasing | G106: Is there a group-wide framework agreement existing within the company, including all Business entities? If yes, what is included in the framework agreement? | H106: No framework agreements/ Lose agreement of collaboration | I106: In the framework agreement there is loosly described how the charges are calculated | J106: Regional & national bonus/ Signing bonus | K106: Regional & national bonus/ Signing bonus, Interest rate, for shorter duration: OEM discount, service cost, fuel card bonus (if included over leasing company) | L106: 0.005 | M106: 0.01 | N106: =_xlfn.CONCAT(TEXT(L106,"0.0%"),"-",TEXT(M106,"0.0%")) -> 0.5%-1.0% | O106: Expand fixed elements in framework agreements for better structure and clarity. | P106: Leverage Competition Among Suppliers | Q106: Competitive Bidding | R106: Expand fixed elements in framework agreements
A107: =_xlfn.CONCAT(C107,D107,O107) -> TravelCar RentalDefining car size policies and ensuring compliance controls rental costs and optimizes resource use. | B107: 99 | C107: Travel | D107: Car Rental | G107: Is there a policy in place defining the size of the car. If yes, how compliant is the proces? | H107: There is no policy in place, the employee takes what he considers suitable. | I107: There is a vague policy in place, adherence is not tracked. | J107: Policy is in place - but the adherence is not tracked. | K107: There is a clear definition in place which car to take in which situation. The policy is quite strict & adherence is monitored quite strictly. | L107: 0.02 | M107: 0.04 | N107: =_xlfn.CONCAT(TEXT(L107,"0.0%"),"-",TEXT(M107,"0.0%")) -> 2.0%-4.0% | O107: Defining car size policies and ensuring compliance controls rental costs and optimizes resource use. | P107: Manage Spend | Q107: Control Compliance | R107: Define and enforce car size policies
A108: =_xlfn.CONCAT(C108,D108,O108) -> MRONAThe approach critically evaluates current specifications and asking whether they are in fact useful or merely increase cost and complexity. Specifications that are not necessary are discarded. | B108: 100 | C108: MRO | D108: NA | G108: Is there a process for approving alternative products? | H108: No | I108: No, but discussions ongoing | J108: Yes, but rarely implemented | K108: Yes | L108: 0.015 | M108: 0.03 | N108: =_xlfn.CONCAT(TEXT(L108,"0.0%"),"-",TEXT(M108,"0.0%")) -> 1.5%-3.0% | O108: The approach critically evaluates current specifications and asking whether they are in fact useful or merely increase cost and complexity. Specifications that are not necessary are discarded. | P108: Change the Nature of Demand | Q108: Optimize Specifications | R108: Challenge and optimize specifications
A109: =_xlfn.CONCAT(C109,D109,O109) -> TravelPolicyStrict travel guidelines ensure necessary travel only, reducing unnecessary trips and costs. | B109: 101 | C109: Travel | D109: Policy | G109: Is there a strict & rigorious definition when to travel? | H109: No restriction - people travel when they feel the need to | I109: Definition of critical and non critical | J109: Amount of people restricted by travel activity | K109: Number 2 & 3 - and definition thoroughly checked | L109: 0.01 | M109: 0.02 | N109: =_xlfn.CONCAT(TEXT(L109,"0.0%"),"-",TEXT(M109,"0.0%")) -> 1.0%-2.0% | O109: Strict travel guidelines ensure necessary travel only, reducing unnecessary trips and costs. | P109: Manage Spend | Q109: Control Compliance | R109: Implement strict travel guidelines
A110: =_xlfn.CONCAT(C110,D110,O110) -> TravelPolicyImplement a travel cost guideline to ensure cost-conscious booking within company restrictions. | B110: 102 | C110: Travel | D110: Policy | G110: Is there an existing travel cost policy? | H110: Yes, anyone can submit a request | I110: Yes, but not communicated | J110: Yes, but only as a document | K110: Yes and implemented systemically | L110: 0.015 | M110: 0.03 | N110: =_xlfn.CONCAT(TEXT(L110,"0.0%"),"-",TEXT(M110,"0.0%")) -> 1.5%-3.0% | O110: Implement a travel cost guideline to ensure cost-conscious booking within company restrictions. | P110: Manage Spend | Q110: Control Compliance | R110: Implement travel cost guidelines
A111: =_xlfn.CONCAT(C111,D111,O111) -> MarketingAd ProductionEnhance process efficiency by streamlining and optimizing existing workflows and procedures. | B111: 103 | C111: Marketing | D111: Ad Production | G111: Is tripple bidding in place? | H111: Never | I111: Sometimes | J111: Almost always | K111: Always | L111: 0.005 | M111: 0.01 | N111: =_xlfn.CONCAT(TEXT(L111,"0.0%"),"-",TEXT(M111,"0.0%")) -> 0.5%-1.0% | O111: Enhance process efficiency by streamlining and optimizing existing workflows and procedures. | P111: Manage Spend | Q111: Improve Process Efficiency | R111: Streamline/optimize workflows
A112: =_xlfn.CONCAT(C112,D112,O112) -> Temp LabourNAFor larger spend in several locations:consider a master vendor. A master vendor is a supplier who guarantees a fixed multiplier, subcontracts other agencies when needed, and may take over HR and operations tasks; they often offer reduced multipliers for large temp labor demands, balancing cost reduction with the risk of single-supplier dependence. | B112: 104 | C112: Temp Labour | D112: NA | G112: Master Vendor: if spend on specific sites is larger, are master vendor programs tested? (a master vendor is a supplier who guarantees a multiplier and subcontracts other agencies when he does not have sufficient staff) | H112: No - at sites with large spend, several suppliers are engaged | I112: It is tested but decided against due to different reasons | J112: There is a master vendor program in place, where the MV is requesting staff from other agencies from time-to-time | K112: There is a MV in place where the MV is also taking over the HR role and manage staff with additional targets to reduce costs | L112: 0.01 | M112: 0.02 | N112: =_xlfn.CONCAT(TEXT(L112,"0.0%"),"-",TEXT(M112,"0.0%")) -> 1.0%-2.0% | O112: For larger spend in several locations:consider a master vendor. A master vendor is a supplier who guarantees a fixed multiplier, subcontracts other agencies when needed, and may take over HR and operations tasks; they often offer reduced multipliers for large temp labor demands, balancing cost reduction with the risk of single-supplier dependence. | P112: Leverage Competition Among Suppliers | Q112: Rationalize Supply Base | R112: Utilize master vendors (temp labor)
A113: =_xlfn.CONCAT(C113,D113,O113) -> Real estateNAContinuously monitoring potential areas of value loss, such as unutilized payment terms, ensures that real estate demand is accurately assessed. This proactive approach helps optimize space usage and reduce unnecessary costs | B113: 105 | C113: Real estate | D113: NA | G113: Need for real estate: how is demand for real estate derived? | H113: Real estate demand is currently existing locations. | I113: Real estate demand is defined through the future target picture of how many people the company might have + a certain assumption about home office. No tracking of people in the office is possible. | J113: Real estate demand is derived from future expecations + future analysis | K113: Real estate demand is optimzed, in accordance to the analyzed need: how many employees really come to the office, home office policy, co-sharing of desks, decrease of common rooms, | L113: 0.01 | M113: 0.02 | N113: =_xlfn.CONCAT(TEXT(L113,"0.0%"),"-",TEXT(M113,"0.0%")) -> 1.0%-2.0% | O113: Continuously monitoring potential areas of value loss, such as unutilized payment terms, ensures that real estate demand is accurately assessed. This proactive approach helps optimize space usage and reduce unnecessary costs | P113: Change the Nature of Demand | Q113: Optimize Asset Utilization | R113: Monitor value loss/optimize space usage
A114: =_xlfn.CONCAT(C114,D114,O114) -> Office SuppliesNAThe approach critically evaluates current specifications and asking whether they are in fact useful or merely increase cost and complexity. Specifications that are not necessary are discarded. | B114: 106 | C114: Office Supplies | D114: NA | G114: Office material: What is the % of white label products to the total spend? | H114: 20% | I114: 40% | J114: 60% | K114: >80% | L114: 0.01 | M114: 0.02 | N114: =_xlfn.CONCAT(TEXT(L114,"0.0%"),"-",TEXT(M114,"0.0%")) -> 1.0%-2.0% | O114: The approach critically evaluates current specifications and asking whether they are in fact useful or merely increase cost and complexity. Specifications that are not necessary are discarded. | P114: Change the Nature of Demand | Q114: Optimize Specifications | R114: Challenge and optimize specifications
A115: =_xlfn.CONCAT(C115,D115,O115) -> ITSoftware development and maintenanceAlign internal processes with industry standards to leverage out-of-the-box solutions. | B115: 107 | C115: IT | D115: Software development and maintenance | G115: Past three years, regarding introduction of new software: What is the degree of commercial off-the-shelf software compared to total software (counted in SW products)? | H115: <20% | I115: 20-60% | J115: 60-80% | K115: 80-100% | L115: 0.015 | M115: 0.03 | N115: =_xlfn.CONCAT(TEXT(L115,"0.0%"),"-",TEXT(M115,"0.0%")) -> 1.5%-3.0% | O115: Align internal processes with industry standards to leverage out-of-the-box solutions. | P115: Change the Nature of Demand | Q115: Reduce Complexity | R115: Align processes with industry standards
A116: =_xlfn.CONCAT(C116,D116,O116) -> ITSoftware licensesUsing bundled license providers consolidates suppliers, achieving economies of scale, reducing costs. | B116: 108 | C116: IT | D116: Software licenses | G116: To what degree do you use bundled license providers, e.g., SoftwareOne, to utilise economies of scale? | H116: 0 | I116: <5% | J116: <20% | K116: >20% | L116: 0.005 | M116: 0.01 | N116: =_xlfn.CONCAT(TEXT(L116,"0.0%"),"-",TEXT(M116,"0.0%")) -> 0.5%-1.0% | O116: Using bundled license providers consolidates suppliers, achieving economies of scale, reducing costs. | P116: Leverage Competition Among Suppliers | Q116: Consolidate Volume | R116: Bundle license providers
A117: =_xlfn.CONCAT(C117,D117,O117) -> LegalNASpecialist departments lead in commissioning legal and auditing services, while involving the purchasing department in critical processes like price negotiation can yield additional savings. | B117: 109 | C117: Legal | D117: NA | G117: To what degree is the purchasing department integrated in the procurement of legal advice? | H117: Sourcing is conducted by legal department | I117: Partially integrated (e.g. market screening of law/audit firms) | J117: Extended integrated (e.g. price negotiations) | K117: Procurement conducts the RFP, creates a panel of legal companies and negotiates the lawyers | L117: 0.005 | M117: 0.01 | N117: =_xlfn.CONCAT(TEXT(L117,"0.0%"),"-",TEXT(M117,"0.0%")) -> 0.5%-1.0% | O117: Specialist departments lead in commissioning legal and auditing services, while involving the purchasing department in critical processes like price negotiation can yield additional savings. | P117: Manage Spend | Q117: Improve Process Efficiency | R117: Involve purchasing in critical processes
A118: =_xlfn.CONCAT(C118,D118,O118) -> LogisticsRoad LogisticsMost shipments are prioritized for fast delivery, but many could be slower and cheaper without impacting needs. A data-driven discussion with the business side is essential to highlight this opportunity. | B118: 110 | C118: Logistics | D118: Road Logistics | G118: To what extent are SLAs and requirements standardized across sites / BUs? | H118: Not at all | I118: Somewhat | J118: To a large extent | K118: Fully standardized | L118: 0.0025 | M118: 0.005 | N118: =_xlfn.CONCAT(TEXT(L118,"0.0%"),"-",TEXT(M118,"0.0%")) -> 0.3%-0.5% | O118: Most shipments are prioritized for fast delivery, but many could be slower and cheaper without impacting needs. A data-driven discussion with the business side is essential to highlight this opportunity. | P118: Change the Nature of Demand | Q118: Optimize Service Levels | R118: Optimize delivery speed vs. cost
A119: =_xlfn.CONCAT(C119,D119,O119) -> LogisticsLOG OceanStrategic SRM program enhances shipper status via collaborative capacity management. | B119: 111 | C119: Logistics | D119: LOG Ocean | G119: To what extent are you investing resources and efforts in becoming a shipper of choice, e.g., through a strategic SRM program? | H119: None | I119: As little as needed to keep operations running | J119: We selectively invest in partner to increase competition | K119: All the time - competition is key for optimal rates | L119: 0.005 | M119: 0.01 | N119: =_xlfn.CONCAT(TEXT(L119,"0.0%"),"-",TEXT(M119,"0.0%")) -> 0.5%-1.0% | O119: Strategic SRM program enhances shipper status via collaborative capacity management. | P119: Seek Joint Advantage with Suppliers | Q119: Joint Capacity & Planning | R119: Implement Strategic SRM
A120: =_xlfn.CONCAT(C120,D120,O120) -> LogisticsRoad LogisticsTransportation is often managed by a long-term partner with premium rates, but regularly seeking multiple quotes for large volumes helps identify alternatives and true market rates. | B120: 112 | C120: Logistics | D120: Road Logistics | G120: To what extent are you investing time and money to build new carriers to challenge existing partners? | H120: None | I120: As little as needed to keep operations running | J120: We selectively invest in partner to increase competition | K120: All the time - competition is key for optimal rates | L120: 0.0025 | M120: 0.005 | N120: =_xlfn.CONCAT(TEXT(L120,"0.0%"),"-",TEXT(M120,"0.0%")) -> 0.3%-0.5% | O120: Transportation is often managed by a long-term partner with premium rates, but regularly seeking multiple quotes for large volumes helps identify alternatives and true market rates. | P120: Leverage Competition Among Suppliers | Q120: Competitive Bidding | R120: Benchmark and seek multiple quotes
A121: =_xlfn.CONCAT(C121,D121,O121) -> LogisticsCEP LogisticsInvesting in new suppliers to challenge and diversify existing partnerships. | B121: 113 | C121: Logistics | D121: CEP Logistics | G121: To what extent are you investing time and money to build new suppliers to challenge existing partners | H121: None | I121: As little as needed to keep operations running | J121: We selectively invest in partner to increase competition | K121: All the time - competition is key for optimal rates | L121: 0.005 | M121: 0.01 | N121: =_xlfn.CONCAT(TEXT(L121,"0.0%"),"-",TEXT(M121,"0.0%")) -> 0.5%-1.0% | O121: Investing in new suppliers to challenge and diversify existing partnerships. | P121: Leverage Competition Among Suppliers | Q121: Rationalize Supply Base | R121: Introduce new suppliers
A122: =_xlfn.CONCAT(C122,D122,O122) -> LogisticsRoad LogisticsCentralizing transportation spend increases leverage and reduces fragmented local solutions. | B122: 114 | C122: Logistics | D122: Road Logistics | G122: To what extent do you use expressive bidding elements (alternative bids, bundle / volume discounts, etc.) during RFPs? | H122: Not at all | I122: Tried in past but didn't work | J122: Ocassionally | K122: Everytime | L122: 0.0025 | M122: 0.005 | N122: =_xlfn.CONCAT(TEXT(L122,"0.0%"),"-",TEXT(M122,"0.0%")) -> 0.3%-0.5% | O122: Centralizing transportation spend increases leverage and reduces fragmented local solutions. | P122: Leverage Competition Among Suppliers | Q122: Consolidate Volume | R122: Centralize transportation spend
A123: =_xlfn.CONCAT(C123,D123,O123) -> LogisticsCEP LogisticsExpressive bidding with categories enhances flexibility and competitive supplier proposals. | B123: 115 | C123: Logistics | D123: CEP Logistics | G123: To what extent do you use expressive bidding elements (alternative bids, bundle / volume discounts, etc.) during RFPs? | H123: Not at all | I123: Tried in past but didn't work | J123: Ocassionally | K123: Everytime | L123: 0.015 | M123: 0.03 | N123: =_xlfn.CONCAT(TEXT(L123,"0.0%"),"-",TEXT(M123,"0.0%")) -> 1.5%-3.0% | O123: Expressive bidding with categories enhances flexibility and competitive supplier proposals. | P123: Leverage Competition Among Suppliers | Q123: Competitive Bidding | R123: Expressive bidding (categorized)
A124: =_xlfn.CONCAT(C124,D124,O124) -> LogisticsLOG OceanMost firms' spend isn't large enough to attract CEP providers, but a purchasing consortium like CoreTrust bundles volumes from multiple participants to negotiate significant savings, with no major prerequisites besides joining the pool. | B124: 116 | C124: Logistics | D124: LOG Ocean | G124: To what extent do you use expressive bidding elements (alternative contract lenghts / sailing time, bundle / volume discounts, etc.)? | H124: Not at all | I124: Somewhat | J124: To a large extent | K124: Exclusively | L124: 0.005 | M124: 0.01 | N124: =_xlfn.CONCAT(TEXT(L124,"0.0%"),"-",TEXT(M124,"0.0%")) -> 0.5%-1.0% | O124: Most firms' spend isn't large enough to attract CEP providers, but a purchasing consortium like CoreTrust bundles volumes from multiple participants to negotiate significant savings, with no major prerequisites besides joining the pool. | P124: Leverage Competition Among Suppliers | Q124: Consolidate Volume | R124: Utilize purchasing consortia
A125: =_xlfn.CONCAT(C125,D125,O125) -> LogisticsCEP LogisticsIncorporate strategic bidding to optimize supplier selection and pricing. | B125: 117 | C125: Logistics | D125: CEP Logistics | G125: To what extent do you use game-theoretical elements during RFPs? | H125: Not at all | I125: Somewhat | J125: To a large extent | K125: Exclusively | L125: 0.005 | M125: 0.01 | N125: =_xlfn.CONCAT(TEXT(L125,"0.0%"),"-",TEXT(M125,"0.0%")) -> 0.5%-1.0% | O125: Incorporate strategic bidding to optimize supplier selection and pricing. | P125: Leverage Competition Among Suppliers | Q125: Competitive Bidding | R125: Strategic bidding
A126: =_xlfn.CONCAT(C126,D126,O126) -> Office SuppliesNAReducing demand by changing the setup and perception of office material use is a powerful way to save money. This can include reducing office printers, eliminating paper waste baskets, implementing a policy requiring signatures, and training employees to use laptops instead of pen and paper. | B126: 118 | C126: Office Supplies | D126: NA | G126: To which degree are demand measures implemented? | H126: No definition of demand measures, employees can take all items they wish | I126: Request only through assistants for various matters | J126: People are advised to write notes on laptops rather to print on papers | K126: Strict demand management - per year ZBB levers are applied and target of reducing spend/ material is further given | L126: 0.02 | M126: 0.04 | N126: =_xlfn.CONCAT(TEXT(L126,"0.0%"),"-",TEXT(M126,"0.0%")) -> 2.0%-4.0% | O126: Reducing demand by changing the setup and perception of office material use is a powerful way to save money. This can include reducing office printers, eliminating paper waste baskets, implementing a policy requiring signatures, and training employees to use laptops instead of pen and paper. | P126: Change the Nature of Demand | Q126: Reduce Consumption | R126: Implement demand reduction policies
A127: =_xlfn.CONCAT(C127,D127,O127) -> TravelTravel Management AgencyTender travel agencies every 2-3 years for competitiveness or benchmark after 5 years and negotiate. | B127: 119 | C127: Travel | D127: Travel Management Agency | G127: Travel agency: When was the last time travel agency was tendered? | H127: Never | I127: > 5 years ago | J127: >2 years ago | K127: Last year | L127: 0.025 | M127: 0.05 | N127: =_xlfn.CONCAT(TEXT(L127,"0.0%"),"-",TEXT(M127,"0.0%")) -> 2.5%-5.0% | O127: Tender travel agencies every 2-3 years for competitiveness or benchmark after 5 years and negotiate. | P127: Leverage Competition Among Suppliers | Q127: Competitive Bidding | R127: Regular tendering/benchmarking (travel agencies)
A128: =_xlfn.CONCAT(C128,D128,O128) -> TravelTravel Management AgencyChoosing the right pricing agreements aligns costs with usage, optimizing travel expenses. | B128: 120 | C128: Travel | D128: Travel Management Agency | G128: Travel agency: Which of the following pricing agreements are included in the contract? | H128: Online & offline rates | I128: No. 1 & Volume discount and signing fee | J128: No. 2 & Guaranteed online bookings (ca. 80%) | K128: all of before + free negotiation of the modes | L128: 0.025 | M128: 0.05 | N128: =_xlfn.CONCAT(TEXT(L128,"0.0%"),"-",TEXT(M128,"0.0%")) -> 2.5%-5.0% | O128: Choosing the right pricing agreements aligns costs with usage, optimizing travel expenses. | P128: Leverage Competition Among Suppliers | Q128: Target Pricing & Cost Models | R128: Optimize pricing agreements (travel)
... A137: =_xlfn.CONCAT(C137,D137,O137) -> MarketingTraditional MediaImplement a P4P scheme that rewards employees for exceeding delivery standards. | B137: 129 | C137: Marketing | D137: Traditional Media | G137: What % of total agency fee is linked to agency performance? | H137: <10% | I137: 10-20% | J137: 20-40% | K137: >40% | L137: 0.005 | M137: 0.01 | N137: =_xlfn.CONCAT(TEXT(L137,"0.0%"),"-",TEXT(M137,"0.0%")) -> 0.5%-1.0% | O137: Implement a P4P scheme that rewards employees for exceeding delivery standards. | P137: Change the Nature of Demand | Q137: Optimize Labor Mix | R137: Implement Pay-for-Performance (P4P)
A138: =_xlfn.CONCAT(C138,D138,O138) -> MarketingTraditional MediaImplement an effective pay-for-performance (P4P) scheme that rewards employees for good performance. Introduce a P4P scheme that effectively rewards good performance. | B138: 130 | C138: Marketing | D138: Traditional Media | G138: What % of total agency fee is linked to agency performance? | H138: <10% | I138: 10-20% | J138: 20-40% | K138: >40% | L138: 0.015 | M138: 0.03 | N138: =_xlfn.CONCAT(TEXT(L138,"0.0%"),"-",TEXT(M138,"0.0%")) -> 1.5%-3.0% | O138: Implement an effective pay-for-performance (P4P) scheme that rewards employees for good performance. Introduce a P4P scheme that effectively rewards good performance. | P138: #N/A | Q138: #N/A | R138: #N/A
A139: =_xlfn.CONCAT(C139,D139,O139) -> ITSoftware development and maintenanceLeverage SaaS/IaaS based solutions to the fullest, especially for standard functionalities that can be catered-to by third party SaaS/Iaas providers. This helps reduce costs associated with software maintenance, upgrades etc. | B139: 131 | C139: IT | D139: Software development and maintenance | G139: What % of used software are SaaS or IaaS-based? | H139: <20% | I139: 20-60% | J139: 60-80% | K139: 80-100% | L139: 0.015 | M139: 0.03 | N139: =_xlfn.CONCAT(TEXT(L139,"0.0%"),"-",TEXT(M139,"0.0%")) -> 1.5%-3.0% | O139: Leverage SaaS/IaaS based solutions to the fullest, especially for standard functionalities that can be catered-to by third party SaaS/Iaas providers. This helps reduce costs associated with software maintenance, upgrades etc. | P139: Change the Nature of Demand | Q139: Reduce Complexity | R139: Leverage SaaS/IaaS solutions
A140: =_xlfn.CONCAT(C140,D140,O140) -> FleetWay of purchasingAs a standard use Game-theory based methods e.g. auctions or supplier-days. Ensure that the teams are regularly trained in these methods. | B140: 132 | C140: Fleet | D140: Way of purchasing | G140: What approach do you use to decide the contractual agreement to be used? | H140: We tender via asking the supplier for their best price via email | I140: We challenge the supplier with at least one other provider | J140: We separately negotiate the suppliers in various rounds | K140: Highly competitive either via a supplier-days or an auctions | L140: 0.0025 | M140: 0.005 | N140: =_xlfn.CONCAT(TEXT(L140,"0.0%"),"-",TEXT(M140,"0.0%")) -> 0.3%-0.5% | O140: As a standard use Game-theory based methods e.g. auctions or supplier-days. Ensure that the teams are regularly trained in these methods. | P140: Leverage Competition Among Suppliers | Q140: Competitive Bidding | R140: Use game-theory based methods (auctions/supplier days)
A141: =_xlfn.CONCAT(C141,D141,O141) -> MarketingTraditional MediaEnhance WOW by leveraging 'first-to-book media' efficiencies for optimal results. | B141: 133 | C141: Marketing | D141: Traditional Media | G141: What could be the extra efficiency gained by earlier inventory booking? | H141: Significant | I141: Good | J141: Moderate | K141: Small | L141: 0.01 | M141: 0.02 | N141: =_xlfn.CONCAT(TEXT(L141,"0.0%"),"-",TEXT(M141,"0.0%")) -> 1.0%-2.0% | O141: Enhance WOW by leveraging 'first-to-book media' efficiencies for optimal results. | P141: Manage Spend | Q141: Improve Process Efficiency | R141: Enhance efficiency through early booking (media)
A142: =_xlfn.CONCAT(C142,D142,O142) -> MarketingTraditional MediaGet AVB transparency by vendor | B142: 134 | C142: Marketing | D142: Traditional Media | G142: What granularity of AVBs is in place? | H142: No AVBs provided | I142: Aggregated AVB number for all media provided | J142: Average AVBs per media type provided | K142: By vendor by spend range for all vendors | L142: 0.01 | M142: 0.02 | N142: =_xlfn.CONCAT(TEXT(L142,"0.0%"),"-",TEXT(M142,"0.0%")) -> 1.0%-2.0% | O142: Get AVB transparency by vendor | P142: Manage Spend | Q142: Control Compliance | R142: Ensure vendor transparency (AVB)
A143: =_xlfn.CONCAT(C143,D143,O143) -> MarketingTraditional MediaObtain AVB transparency specific to each vendor. | B143: 135 | C143: Marketing | D143: Traditional Media | G143: What granularity of AVBs is in place? | H143: No AVBs provided | I143: Aggregated AVB number for all media provided | J143: Average AVBs per media type provided | K143: By vendor by spend range for all vendors | L143: 0.015 | M143: 0.03 | N143: =_xlfn.CONCAT(TEXT(L143,"0.0%"),"-",TEXT(M143,"0.0%")) -> 1.5%-3.0% | O143: Obtain AVB transparency specific to each vendor. | P143: Manage Spend | Q143: Control Compliance | R143: Ensure vendor transparency (AVB)
A144: =_xlfn.CONCAT(C144,D144,O144) -> MarketingCreative AgenciesOutsource non-strategic services like DTP, BTL adaptation, and translation to more cost-effective agencies. | B144: 136 | C144: Marketing | D144: Creative Agencies | G144: What is current level of agency services provided by strategic creative agencies that can be transferred out to cheaper agencies? | H144: 50-40% | I144: 40-30% | J144: 30-20% | K144: <20% | L144: 0.015 | M144: 0.03 | N144: =_xlfn.CONCAT(TEXT(L144,"0.0%"),"-",TEXT(M144,"0.0%")) -> 1.5%-3.0% | O144: Outsource non-strategic services like DTP, BTL adaptation, and translation to more cost-effective agencies. | P144: Seek Joint Advantage with Suppliers | Q144: Outsourcing | R144: Outsource non-strategic services
A145: =_xlfn.CONCAT(C145,D145,O145) -> MarketingCreative AgenciesThe selected agency oversees in-source activities, including project management, resource allocation, and performance evaluation. | B145: 137 | C145: Marketing | D145: Creative Agencies | G145: What is current level of agency services that can be insourced (for every Euro of activities that can be transferred savings could be 40% on average)? | H145: 25-20% | I145: 20-15% | J145: 15-10% | K145: <10% | L145: 0.01 | M145: 0.02 | N145: =_xlfn.CONCAT(TEXT(L145,"0.0%"),"-",TEXT(M145,"0.0%")) -> 1.0%-2.0% | O145: The selected agency oversees in-source activities, including project management, resource allocation, and performance evaluation. | P145: Seek Joint Advantage with Suppliers | Q145: Joint Process Improvement | R145: Agency-managed insourcing
A146: =_xlfn.CONCAT(C146,D146,O146) -> MarketingDigital AgenciesThe Lever Description outlines activities managed by the selected agency for in-sourcing | B146: 138 | C146: Marketing | D146: Digital Agencies | G146: What is current level of agency services that can be insourced (for every Euro of actvivities that can be transferred savings could be 40% on average)? | H146: 25-20% | I146: 20-15% | J146: 15-10% | K146: <10% | L146: 0.01 | M146: 0.02 | N146: =_xlfn.CONCAT(TEXT(L146,"0.0%"),"-",TEXT(M146,"0.0%")) -> 1.0%-2.0% | O146: The Lever Description outlines activities managed by the selected agency for in-sourcing | P146: Seek Joint Advantage with Suppliers | Q146: Joint Process Improvement | R146: Agency-managed insourcing
A147: =_xlfn.CONCAT(C147,D147,O147) -> MarketingOnline MediaStreamline digital banner expenditures and unify media agency efforts. | B147: 139 | C147: Marketing | D147: Online Media | G147: What is current share of digital display spend that goes via the biggest agency? | H147: <40% | I147: 40-60% | J147: 60-80% | K147: >80% | L147: 0.04 | M147: 0.08 | N147: =_xlfn.CONCAT(TEXT(L147,"0.0%"),"-",TEXT(M147,"0.0%")) -> 4.0%-8.0% | O147: Streamline digital banner expenditures and unify media agency efforts. | P147: Leverage Competition Among Suppliers | Q147: Consolidate Volume | R147: Streamline digital media spend
A148: =_xlfn.CONCAT(C148,D148,O148) -> MarketingTraditional MediaStreamline media expenditures and agency partnerships. | B148: 140 | C148: Marketing | D148: Traditional Media | G148: What is current share of spend that goes via the biggest spend agency? | H148: <40% | I148: 40-60% | J148: 60-80% | K148: >80% | L148: 0.01 | M148: 0.02 | N148: =_xlfn.CONCAT(TEXT(L148,"0.0%"),"-",TEXT(M148,"0.0%")) -> 1.0%-2.0% | O148: Streamline media expenditures and agency partnerships. | P148: Leverage Competition Among Suppliers | Q148: Consolidate Volume | R148: Streamline media spend/partnerships
A149: =_xlfn.CONCAT(C149,D149,O149) -> MarketingTraditional MediaEnsure clear visibility and accountability throughout the digital value chain. | B149: 141 | C149: Marketing | D149: Traditional Media | G149: What is current share of spend that goes via the biggest spend agency? | H149: <40% | I149: 40-60% | J149: 60-80% | K149: >80% | L149: 0.04 | M149: 0.08 | N149: =_xlfn.CONCAT(TEXT(L149,"0.0%"),"-",TEXT(M149,"0.0%")) -> 4.0%-8.0% | O149: Ensure clear visibility and accountability throughout the digital value chain. | P149: Manage Spend | Q149: Improve Process Efficiency | R149: Ensure digital value chain transparency
A150: =_xlfn.CONCAT(C150,D150,O150) -> MarketingCreative AgenciesMerge multiple agencies into one streamlined, efficient organization. | B150: 142 | C150: Marketing | D150: Creative Agencies | G150: What is current share of total agency spend of the biggest agency? | H150: <40% | I150: 40-60% | J150: 60-80% | K150: >80% | L150: 0.01 | M150: 0.02 | N150: =_xlfn.CONCAT(TEXT(L150,"0.0%"),"-",TEXT(M150,"0.0%")) -> 1.0%-2.0% | O150: Merge multiple agencies into one streamlined, efficient organization. | P150: Leverage Competition Among Suppliers | Q150: Rationalize Supply Base | R150: Merge agencies
... A214: =_xlfn.CONCAT(C214,D214,O214) -> TravelCar RentalRegularly tendering car rental services ensures competitive pricing and terms, reducing costs. | B214: 207 | C214: Travel | D214: Car Rental | G214: When was the last time Car rental category was tendered? | H214: Never | I214: More than 5 years ago | J214: 2-5 years ago | K214: Less than 2 years ago | L214: 0.015 | M214: 0.03 | N214: =_xlfn.CONCAT(TEXT(L214,"0.0%"),"-",TEXT(M214,"0.0%")) -> 1.5%-3.0% | O214: Regularly tendering car rental services ensures competitive pricing and terms, reducing costs. | P214: Leverage Competition Among Suppliers | Q214: Competitive Bidding | R214: Regular tendering (car rental)
A215: =_xlfn.CONCAT(C215,D215,O215) -> FleetFuelFuel negotiations use strategic timing, market insights, and relationships to optimize outcomes and secure favorable terms. | C215: Fleet | D215: Fuel | G215: When was the last time the fuel was negotiated? | H215: Fuel cards do not exist, the employee invoices back what he payed at the station | I215: >3 years ago | J215: 3-1 years ago | K215: Fuel cards have been negotiated last year/ together with leasing car tender | L215: 0.01 | M215: 0.02 | N215: =_xlfn.CONCAT(TEXT(L215,"0.0%"),"-",TEXT(M215,"0.0%")) -> 1.0%-2.0% | O215: Fuel negotiations use strategic timing, market insights, and relationships to optimize outcomes and secure favorable terms. | P215: Leverage Competition Among Suppliers | Q215: Competitive Bidding | R215: Strategic negotiation (fuel)
A216: =_xlfn.CONCAT(C216,D216,O216) -> TravelTravel Management AgencyRegularly tendering travel agency services ensures competitive pricing and better terms. | C216: Travel | D216: Travel Management Agency | G216: When was the last time travel agency was tendered? | H216: Never | I216: > 5 years ago | J216: >2 years ago | K216: Last year | L216: 0.01 | M216: 0.02 | N216: =_xlfn.CONCAT(TEXT(L216,"0.0%"),"-",TEXT(M216,"0.0%")) -> 1.0%-2.0% | O216: Regularly tendering travel agency services ensures competitive pricing and better terms. | P216: Leverage Competition Among Suppliers | Q216: Competitive Bidding | R216: Regular tendering (travel agencies)
A217: =_xlfn.CONCAT(C217,D217,O217) -> MRONAExisting data on a sourcing group is analyzed in depth to identify any savings potential. For instance, this may include comparing the discount rates within a corporate group. | C217: MRO | D217: NA | G217: When was the last time you competitively awarded the total category volume? | H217: Never | I217: >5 years ago | J217: 2 years ago | K217: last year | L217: 0.01 | M217: 0.02 | N217: =_xlfn.CONCAT(TEXT(L217,"0.0%"),"-",TEXT(M217,"0.0%")) -> 1.0%-2.0% | O217: Existing data on a sourcing group is analyzed in depth to identify any savings potential. For instance, this may include comparing the discount rates within a corporate group. | P217: Leverage Competition Among Suppliers | Q217: Target Pricing & Cost Models | R217: Data analysis for savings potential
A218: =_xlfn.CONCAT(C218,D218,O218) -> PackagingNAThe primary aim of the RFI/RFP process is to benchmark current suppliers and pinpoint the most competitive ones in the market. This evaluation should encompass both global players and local champions situated near the plant. | C218: Packaging | D218: NA | G218: When was the last time you competitively benchmarked the total category volume? | H218: Never | I218: >5 years ago | J218: 2-5 years | K218: last year | L218: 0.06 | M218: 0.12 | N218: =_xlfn.CONCAT(TEXT(L218,"0.0%"),"-",TEXT(M218,"0.0%")) -> 6.0%-12.0% | O218: The primary aim of the RFI/RFP process is to benchmark current suppliers and pinpoint the most competitive ones in the market. This evaluation should encompass both global players and local champions situated near the plant. | P218: Leverage Competition Among Suppliers | Q218: Competitive Bidding | R218: Benchmark and identify competitive suppliers
A219: =_xlfn.CONCAT(C219,D219,O219) -> AuditNABy means of competitive tendering, existing audit firms can be benchmarked, and potential new providers can be identified. By adding game-theoretical negotiation elements, the competitive pressure can be further increased. | C219: Audit | D219: NA | G219: When was the last time you conducted a competitive tender in the field of auditing using game-theoretical negotiation models? | H219: Never | I219: >5 years ago | J219: 2 years ago | K219: Last year | L219: 0.025 | M219: 0.05 | N219: =_xlfn.CONCAT(TEXT(L219,"0.0%"),"-",TEXT(M219,"0.0%")) -> 2.5%-5.0% | O219: By means of competitive tendering, existing audit firms can be benchmarked, and potential new providers can be identified. By adding game-theoretical negotiation elements, the competitive pressure can be further increased. | P219: Leverage Competition Among Suppliers | Q219: Competitive Bidding | R219: Competitive tendering with game theory (audit firms)
A220: =_xlfn.CONCAT(C220,D220,O220) -> LegalNACompetitive tendering allows benchmarking of current law/audit firms and identification of new providers, with game-theoretical negotiation elements enhancing competitive pressure. | C220: Legal | D220: NA | G220: When was the last time you conducted a competitive tender in the field of legal advice using game-theoretical negotiation models? | H220: Never | I220: >5 years ago | J220: 2 years ago | K220: Last year | L220: 0.01 | M220: 0.02 | N220: =_xlfn.CONCAT(TEXT(L220,"0.0%"),"-",TEXT(M220,"0.0%")) -> 1.0%-2.0% | O220: Competitive tendering allows benchmarking of current law/audit firms and identification of new providers, with game-theoretical negotiation elements enhancing competitive pressure. | P220: Leverage Competition Among Suppliers | Q220: Competitive Bidding | R220: Competitive tendering with game theory (law/audit firms)
A221: =_xlfn.CONCAT(C221,D221,O221) -> ITEnd user/ Workplace HardwareBenchmark prices with the latest market rates, and potentially with the prices that peers / competitors are paying | C221: IT | D221: End user/ Workplace Hardware | G221: When was the last time you conducted an RFP to benchmark prices? | H221: Never | I221: > 5 years ago | J221: 2 years ago | K221: last year | L221: 0.01 | M221: 0.02 | N221: =_xlfn.CONCAT(TEXT(L221,"0.0%"),"-",TEXT(M221,"0.0%")) -> 1.0%-2.0% | O221: Benchmark prices with the latest market rates, and potentially with the prices that peers / competitors are paying | P221: Leverage Competition Among Suppliers | Q221: Target Pricing & Cost Models | R221: Benchmark prices with market/peers
A222: =_xlfn.CONCAT(C222,D222,O222) -> ITDatacenter & NetworkAssess market prices, re-negotiate terms, and/or initiate an RFP. | C222: IT | D222: Datacenter & Network | G222: When was the last time you conducted an RFP to benchmark prices? | H222: Never | I222: > 5 years ago | J222: 2 years ago | K222: last year | L222: 0.01 | M222: 0.02 | N222: =_xlfn.CONCAT(TEXT(L222,"0.0%"),"-",TEXT(M222,"0.0%")) -> 1.0%-2.0% | O222: Assess market prices, re-negotiate terms, and/or initiate an RFP. | P222: Leverage Competition Among Suppliers | Q222: Competitive Bidding | R222: Assess market prices/renegotiate/RFP
A223: =_xlfn.CONCAT(C223,D223,O223) -> ITSoftware licensesBenchmark prices, renegotiate, and/or conduct RFP, ensuring separation of SW & HW costs. | C223: IT | D223: Software licenses | G223: When was the last time you conducted an RFP to reach benchmark prices? | H223: Never | I223: > 5 years ago | J223: 2 years ago | K223: last year | L223: 0.015 | M223: 0.03 | N223: =_xlfn.CONCAT(TEXT(L223,"0.0%"),"-",TEXT(M223,"0.0%")) -> 1.5%-3.0% | O223: Benchmark prices, renegotiate, and/or conduct RFP, ensuring separation of SW & HW costs. | P223: Leverage Competition Among Suppliers | Q223: Competitive Bidding | R223: Benchmark/renegotiate/RFP (SW/HW split)
A224: =_xlfn.CONCAT(C224,D224,O224) -> LogisticsCEP LogisticsRegularly tender CEP spend to optimize costs and service levels. | C224: Logistics | D224: CEP Logistics | G224: When was the last time you tendered >50% of your CEP spend at the market? | H224: Never | I224: >5 years ago | J224: 2 years ago | K224: last year | L224: 0.005 | M224: 0.01 | N224: =_xlfn.CONCAT(TEXT(L224,"0.0%"),"-",TEXT(M224,"0.0%")) -> 0.5%-1.0% | O224: Regularly tender CEP spend to optimize costs and service levels. | P224: Leverage Competition Among Suppliers | Q224: Competitive Bidding | R224: Regular tendering (CEP)
A225: =_xlfn.CONCAT(C225,D225,O225) -> LogisticsRoad LogisticsIncumbent rates often include transportation and various surcharges with added margins and security buffers. Unbundling these rates ensures payment only for actual costs. | C225: Logistics | D225: Road Logistics | G225: When was the last time you tendered the majority of your transportation spend at the market? | H225: Never | I225: >5 years ago | J225: 2 years ago | K225: last year | L225: 0.005 | M225: 0.01 | N225: =_xlfn.CONCAT(TEXT(L225,"0.0%"),"-",TEXT(M225,"0.0%")) -> 0.5%-1.0% | O225: Incumbent rates often include transportation and various surcharges with added margins and security buffers. Unbundling these rates ensures payment only for actual costs. | P225: Manage Spend | Q225: Control Compliance | R225: Unbundle incumbent rates
A226: =_xlfn.CONCAT(C226,D226,O226) -> LogisticsLOG OceanMarket-based tendering for competitive pricing and cost optimization. | C226: Logistics | D226: LOG Ocean | G226: When was the last time you tendered the majority of your transportation spend at the market? | H226: Never | I226: >5 years ago | J226: 2 years ago | K226: last year | L226: 0.005 | M226: 0.01 | N226: =_xlfn.CONCAT(TEXT(L226,"0.0%"),"-",TEXT(M226,"0.0%")) -> 0.5%-1.0% | O226: Market-based tendering for competitive pricing and cost optimization. | P226: Leverage Competition Among Suppliers | Q226: Competitive Bidding | R226: Market-based tendering
... A235: =_xlfn.CONCAT(C235,D235,O235) -> LogisticsCEP LogisticsExploit market imbalances by engaging with multiple global CEP players. | C235: Logistics | D235: CEP Logistics | G235: With how many of the global CEP players are you regularly engaging? | H235: 1 | I235: 1-2 | J235: 2-3 | K235: >3 | L235: 0.0025 | M235: 0.005 | N235: =_xlfn.CONCAT(TEXT(L235,"0.0%"),"-",TEXT(M235,"0.0%")) -> 0.3%-0.5% | O235: Exploit market imbalances by engaging with multiple global CEP players. | P235: Leverage Competition Among Suppliers | Q235: Competitive Bidding | R235: Exploit market imbalances (CEP)

Sheet V1
J1: Hypotheses - Proof points
A2: L1 | B2: L2 | C2: Region | D2: Hypotheses (Value drivers) / Questions | E2: Standard initiative description | F2: 64 methods | G2: 16 Levers | H2: 4 Strategies | J2: Avg. spend / supplier | K2: Category spend vs. revenue | L2: Supplier fragmentation for botton 20% spend | M2: Price variations | N2: Regional fragmentation | O2: Single source / monopolistic traits | P2: Supplier concentration for top 80% spend | Q2: Low cost country options | R2: Supplier intel | S2: Market price trends
A3: Plant-based | B3: Grains | D3: Are you leveraging by-product opportunities, such as combo buying (e.g., bran and wheat flour), to reduce costs? | E3: Maximize resource utilization by ensuring all parts of the product (e.g., fish) are used effectively, often through combo buying strategies. | G3: Volume bundling | H3: Leverage competition among suppliers | J3: 1. Calculate 'category spend / # of unique suppliers' 2. If value < benchmark, then this category is relatively fragmented compare to peers i.e., this proof point confirms that there is value in reducing supplier fragmentation | L3: In case this proof-point shows high fragmentation in bottom 20% spend, then augment the initiative by describing the extent of fragmentation e.g., >90% supplier make up the bottom 20% spend
A4: Plant-based | B4: Grains | D4: Have you reviewed pack sizes or explored bulk purchasing options to optimize costs and streamline the supply chain? | E4: Improve material flow management to reduce waste, enhance efficiency, and lower costs across the supply chain. | G4: Volume bundling | H4: Leverage competition among suppliers
A5: Plant-based | B5: Grains | D5: How often do you conduct footprint optimization studies to enhance efficiency in grains sourcing and distribution? | E5: Improve material flow management to reduce waste, enhance efficiency, and lower costs across the supply chain. | G5: Volume bundling | H5: Leverage competition among suppliers | N5: If a large number of countries/regions contribute to a high percentage of total spend (e.g., >80%), then there can be potential to optimize the supply base. Callout such examples of locations that can be consolidated, while describing initiatives | Q5: Augment the initiative by mentioning incumbent low cost countries. If available, add country-specific differences in RM and freight costs - this shuld be directional and not numeric. Using market data, also highlight the risk associated with these countries
A6: Plant-based | B6: Grains | D6: Have you considered or implemented swapping specialty products for more cost-effective alternatives in your grains procurement? | E6: Substitute premium materials with lower-grade alternatives that meet functional requirements while reducing costs. | G6: Re-specification | H6: Seek joint advantage with supplier
A7: Plant-based | B7: Grains | D7: How often do you evaluate and adjust the inclusion levels of specialty products to incorporate standard products without compromising product quality? | E7: Optimize recipes by lowering expensive ingredient levels and replacing them with cost-effective substitutes. | G7: Re-specification | H7: Change nature of demand
A8: All | B8: All | D8: Geographic Sourcing Optimization for Cost Reduction - If significant spend for common goods/services occurs with suppliers located in high-cost regions, when similar quality suppliers exist in lower-cost regions (requires external data on regional cost indices), then a sourcing shift could yield savings due to reduced transportation and tarriffs | E8: Move spend to lower cost countries, starting with incumbents with a presence in low cost countries | G8: Global Sourcing | H8: Manage spend | Q8: Contextualize the initiative by mentioning high cost and low cost countries - ensure to callout most relevant regions/countries; along with market-data based suggestions on alternatives
A9: Plant-based | B9: Grains | D9: How often do you engage in open book costing with your suppliers to enhance transparency in pricing? | E9: Explore open book costing with top suppliers (top 80% spend) within the grains category | G9: Supplier pricing review | H9: Change nature of demand | P9: In case supplier concentration (top 80% spend) is high, then callout the top suppliers who could be targeted for this initiative.
A10: Plant-based | B10: Grains | D10: Are you actively considering suppliers located outside a specific geographic range (e.g., 500 km) to enhance competition and reduce costs? | E10: Foster supplier competition to secure competitive pricing and supply flexibility through strategies like supplier rotation and e-auctions. | G10: Supplier pricing review | H10: Change nature of demand
A11: Plant-based | B11: Grains | D11: Do you currently bundle purchases of related grains or ingredients (e.g., coarse and fine grains) to achieve volume discounts? | E11: Leverage bulk purchasing agreements and combo buying strategies to achieve economies of scale and cost efficiency. | G11: Volume bundling | H11: Change nature of demand | J11: 1. Calculate 'category spend / # of unique suppliers' 2. If value < benchmark, then this category is relatively fragmented compare to peers i.e., this proof point confirms that there is value in reducing supplier fragmentation
A12: Plant-based | B12: Grains | D12: Do you allow suppliers to make financial hedges on your behalf to manage cost volatility? If yes, how is this monitored? | E12: For imported grain supplies, empower suppliers to hedge financial risks e.g., taking a position in the futures or options market, informed by market forecasts | G12: Risk management | H12: Leverage competition among suppliers
A13: All | B13: All | D13: Is contract compliance tracked? If a high percentage of spend within a category is not linked to any discernible contract ID or occurs with suppliers outside a recognized 'preferred' list, then there's a risk of non-compliance and uncontrolled spend | E13: Track contract compliance e.g., are you buying from the right suppliers and at the right / negotiated prices? | G13: Compliance Management | H13: Manage spend
A14: All | B14: All | D14: Payment Term Optimization Potential - Working Capital Opportunity -- If the average payment cycle (from invoice date to payment date) for a significant portion of invoices is consistently very short (e.g., <20 days when 30-60 days is common), and there is no evidence of early payment discounts being captured, then there's an opportunity to optimize working capital | E14: Evaluate typical industry trends and negotiate higher payment days to unlock working capital. Focus on top suppliers (top 80% spend). | G14: Intelligent Deal Structure | H14: Leverage competition among suppliers

Sheet Sheet2
A1: L2 | B1: (All)
A3: Row Labels
A4: Risk
A5: Re-specification
A6: To what degree is the spend across suppliers concentrated within this category?
A7: To what degree is there a risk to prices for the major supply gerographies for this category?
A8: What is the average (weight avg) financial risk profile of top suppliers? (suppliers covering top 80% spend)
A9: What is the average (weighted avg) regional / geopoltical risk score across top suppliers?
A10: Value
A11: Cost Partnership
A12: How does your supplier strategy guide decisions on where to focus R&D for improving cost efficiency or innovation in vegetable oils?
A13: Globalization
A14: Have you considered shifting sourcing origins to take advantage of cost or availability benefits? If so, what challenges have you faced?
... A35: Grand Total

Sheet 1_Value & risk levers
H2: Rapid.AI - Indirect Procurement Assessment Tool - Questionnaire - CIRP directs
D7: Category Levels | G7: Question Theme | H7: Assessment questionnaire | I7: Maturity Range | P7: Lever
B8: Q No. | C8: Lever / initiative type | D8: L1 | E8: L2 | F8: L3 | G8: Question Theme | H8: Questions | I8: Low (1) | J8: Little (2) | K8: Middle (3) | L8: High (4) | M8: Savings% (low) | N8: Savings% (high) | O8: Addressability | P8: Lever Description | Q8: 4 Strategies | R8: 16 Levers | S8: 64 Methods | T8: Score (1-4) | U8: t
C9: Value | D9: Plant-based | E9: Vegetable Oils | G9: Value | H9: Are financial instruments, such as hedging or long-term contracts, used to manage risks in vegetable oil procurement? | I9: Not utilized | J9: Basic usage for high-risk categories | K9: Regularly employed for risk management | L9: Strategically implemented with advanced forecasting | M9: 0.02 | N9: 0.05 | O9: 0.8 | P9: Broader supplier strategy to determine where to focus R&D. Lock part of the price (mark-up) and follow market-based pricing. Use financial instruments to hedge risks. Lock volumes early in the season. | R9: Risk management | T9: 2 | U9: =VLOOKUP(H9,'2_Methodology (Value)'!$H$3:$H$1048576,1,FALSE) -> Are financial instruments, such as hedging or long-term contracts, used to manage risks in vegetable oil procurement?
C10: Value | D10: Plant-based | E10: Vegetable Oils | G10: Value | H10: Do you approve / qualify multiple suppliers for specialty products to hedge against significant risks in the supply chain? | I10: Single sourced / reliance on a single supplier forspecialty products | J10: Largely monopolistic for most specialty products e.g., a pool of 2-3 qualified / approved suppliers to choose from | K10: Multiple qualified suppliers / preferred supplier list for majoe specialty products | L10: Diversified sourcing options maintained for all specialties | M10: 0.02 | N10: 0.05 | O10: 0.8 | P10: Qualify and approve multiple suppliers for specialty products to hedge against supply risks. Activate these suppliers in case of regional supply chain issues. | R10: Risk management | T10: 2 | U10: =VLOOKUP(H10,'2_Methodology (Value)'!$H$3:$H$1048576,1,FALSE) -> Do you approve / qualify multiple suppliers for specialty products to hedge against significant risks in the supply chain?
C11: Value | D11: Plant-based | E11: Vegetable Oils | G11: Value | H11: To what extent do you use should cost models to challenge and negotiate supplier pricing? | I11: Rarely used | J11: Occasionally applied in negotiations, not a structured / defined approach for category managers to follow | K11: Regular practice for most vegetable oils, but requires manual calculations / manual updates | L11: Advanced/ automated modeling integrated into procurement tools | M11: 0.02 | N11: 0.05 | O11: 0.8 | P11: Challenge suppliers with should-cost models to ensure cost-effectiveness. Incoporate data automation to auto calculate should-cost based prices | R11: Target pricing | T11: 1 | U11: =VLOOKUP(H11,'2_Methodology (Value)'!$H$3:$H$1048576,1,FALSE) -> To what extent do you use should cost models to challenge and negotiate supplier pricing?
C12: Value | D12: Plant-based | E12: Vegetable Oils | G12: Value | H12: To what extent have you explored bundling of volumes across different types of vegetable oils to maximize economies of scale? | I12: Not practiced / not explored so far | J12: Ad-hoc initiatives to bundle volume across suppliers | K12: Suppliers are evaluated for their product coverage at the time of sourcing | L12: Comprehensive bundling strategy across all vegetable oils - following an optimization approach to identify the right volume mix across suppliers and SKUs | M12: 0.02 | N12: 0.05 | O12: 0.8 | P12: Bundle volumes across SKUs to achieve savings derived from better economies of scale. Focus on high-spend SKUs that are purchased from multiple suppliers. Potentially consolidate SKUs within the tail. | R12: Volume bundling | T12: 3 | U12: =VLOOKUP(H12,'2_Methodology (Value)'!$H$3:$H$1048576,1,FALSE) -> To what extent have you explored bundling of volumes across different types of vegetable oils to maximize economies of scale?
C13: Value | D13: Plant-based | E13: Vegetable Oils | G13: Value | H13: Have you undertaken specification rationalization to enable volume bundling and reduce sourcing complexity? | I13: Not undertaken | J13: Initial stages of exploration, requires more work | K13: Ad-hoc but frequent rationalization initiatives | L13: Fully optimized methodology to review cost and simplicity periodically | M13: 0.02 | N13: 0.03 | O13: 0.8 | P13: Rationalize specifications to allow for volume bundling and simplification. | R13: Re-specification | T13: 4 | U13: =VLOOKUP(H13,'2_Methodology (Value)'!$H$3:$H$1048576,1,FALSE) -> Have you undertaken specification rationalization to enable volume bundling and reduce sourcing complexity?
C14: Value | D14: Plant-based | E14: Vegetable Oils | G14: Value | H14: Have you considered shifting sourcing origins to take advantage of cost or availability benefits? If so, what challenges have you faced? | I14: Not considered | J14: Limited exploration of alternative origins | K14: Regularly sourcing from diverse origins | L14: Fully optimized global sourcing with risk mitigation plans | M14: 0.02 | N14: 0.03 | O14: 0.8 | P14: Switch origins to adjust to market dynamics and cost advantages. | R14: Globalization | T14: 1 | U14: =VLOOKUP(H14,'2_Methodology (Value)'!$H$3:$H$1048576,1,FALSE) -> Have you considered shifting sourcing origins to take advantage of cost or availability benefits? If so, what challenges have you faced?
C15: Value | D15: Plant-based | E15: Vegetable Oils | G15: Value | H15: Do you review pack sizes and explore delivery options in bulk or flexi tanks to streamline supply chain operations and reduce costs? | I15: No review conducted | J15: Limited trials for bulk options | K15: Regular assessments to optimize packaging | L15: Fully optimized with advanced logistics planning | M15: 0.02 | N15: 0.03 | O15: 0.8 | P15: Review pack sizes and set up delivery in bulk/flexi-tanks for efficiency. | R15: Re-specification | T15: 1 | U15: =VLOOKUP(H15,'2_Methodology (Value)'!$H$3:$H$1048576,1,FALSE) -> Do you review pack sizes and explore delivery options in bulk or flexi tanks to streamline supply chain operations and reduce costs?
C16: Risk | D16: Plant-based | E16: Vegetable Oils | G16: Risk | H16: To what degree is the spend across suppliers concentrated within this category? | I16: >80% of spend is with a single supplier | J16: Top 2 suppliers cover >80% of spend | K16: Top 3-4 suppliers cover >80% of spend | L16: 5 or more suppliers contribute to the top 80% spend | R16: Re-specification | T16: 4
C17: Risk | D17: Plant-based | E17: Vegetable Oils | G17: Risk | H17: What is the average (weight avg) financial risk profile of top suppliers? (suppliers covering top 80% spend) | I17: >75% spend is linked to high risk suppliers (risk score <30) | J17: 50-75% spend is linked to high risk suppliers (risk score <30) | K17: 30-50% spend is linked to high risk suppliers (risk score <30) | L17: <30% spend is linked to high risk suppliers (risk score <30) | R17: Re-specification | T17: 2
C18: Risk | D18: Plant-based | E18: Vegetable Oils | G18: Risk | H18: What is the average (weighted avg) regional / geopoltical risk score across top suppliers? | I18: >75% spend is linked to high risk suppliers (risk score >=DB5) | J18: 50-75% spend is linked to high risk suppliers (risk score >=DB5) | K18: 30-50% spend is linked to high risk suppliers (risk score >=DB5) | L18: <30% spend is linked to high risk suppliers (risk score >=DB5) | R18: Re-specification | T18: 3
C19: Risk | D19: Plant-based | E19: Vegetable Oils | G19: Risk | H19: To what degree is there a risk to prices for the major supply gerographies for this category? | I19: >75% spend is linked to regions witnessing price inflation due to cost driver inflation, tariffs, demand / supply imbalance etc. | J19: 50-75% spend is linked to regions witnessing price inflation due to cost driver inflation, tariffs, demand / supply imbalance etc. | K19: 30-50% spend is linked to regions witnessing price inflation due to cost driver inflation, tariffs, demand / supply imbalance etc. | L19: <30% spend is linked to regions witnessing price inflation due to cost driver inflation, tariffs, demand / supply imbalance etc. | R19: Re-specification | T19: 2
B20: 1 | C20: Value | D20: Plant-based | E20: Vegetable Oils | G20: Value | H20: How does your supplier strategy guide decisions on where to focus R&D for improving cost efficiency or innovation in vegetable oils? | I20: No connection between supplier strategy and R&D | J20: Occasional collaboration for innovation | K20: Regular input from suppliers to guide R&D | L20: Integrated partnerships driving co-developed innovations | M20: 0.02 | N20: 0.05 | O20: 0.8 | P20: Broader supplier strategy to determine where to focus R&D. Lock part of the price (mark-up) and follow market-based pricing. Use financial instruments to hedge risks. Lock volumes early in the season. | R20: Cost Partnership | T20: 2 | U20: =VLOOKUP(H20,'2_Methodology (Value)'!$H$3:$H$1048576,1,FALSE) -> #N/A
B21: 2 | C21: Value | D21: Plant-based | E21: Vegetable Oils | G21: Value | H21: Do you lock part of the price (e.g., mark-up) and allow commodity pricing to follow market trends? If so, how do you monitor its effectiveness? | I21: Not practiced | J21: Commodity indices are linked to pricing, no defined methodology to track and review this | K21: Commodity indices are linked to prices, and category managers / buyers calculate the market impact manually as per defined review periods | L21: Automated index-based price calculations by SKU, plant, supplier etc. | M21: 0.02 | N21: 0.05 | O21: 0.8 | P21: Broader supplier strategy to determine where to focus R&D. Lock part of the price (mark-up) and follow market-based pricing. Use financial instruments to hedge risks. Lock volumes early in the season. | R21: Supplier pricing review | T21: 3 | U21: =VLOOKUP(H21,'2_Methodology (Value)'!$H$3:$H$1048576,1,FALSE) -> #N/A
B22: 4 | C22: Value | D22: Plant-based | E22: Vegetable Oils | G22: Value | H22: How early in the season do you lock in volumes to ensure supply stability and pricing predictability? | I22: Not practiced | L22: We typically aim to lock-in prices early in the season, based on crop reports, yield estimates etc | M22: 0.02 | N22: 0.05 | O22: 0.8 | P22: Broader supplier strategy to determine where to focus R&D. Lock part of the price (mark-up) and follow market-based pricing. Use financial instruments to hedge risks. Lock volumes early in the season. | R22: Risk management | U22: =VLOOKUP(H22,'2_Methodology (Value)'!$H$3:$H$1048576,1,FALSE) -> #N/A
B23: 8 | C23: Value | D23: Plant-based | E23: Vegetable Oils | G23: Value | H23: Have you explored switching to the cheapest alternatives for vegetable oils without compromising product quality or functionality? | I23: Not explored | J23: Limited trials conducted | K23: Regular evaluation and switching | L23: Embedded in procurement and formulation strategies | M23: 0.02 | N23: 0.03 | O23: 0.8 | P23: Switch to the cheapest alternative materials while maintaining functionality. | R23: Re-specification | T23: 1 | U23: =VLOOKUP(H23,'2_Methodology (Value)'!$H$3:$H$1048576,1,FALSE) -> #N/A
B24: 9 | C24: Value | D24: Plant-based | E24: Vegetable Oils | G24: Value | H24: To what extent have you explored implementing blending of specialty products with commodities to reduce costs or optimize product formulations? | I24: Not explored / implemented | J24: Initial stages of exploration, requires more work | K24: Ad-hoc examples of formulation adjustments for expensive specialty products | L24: We have a periodic governance / review mechanism to evaluate the inclusion of specialty products | M24: 0.02 | N24: 0.03 | O24: 0.8 | P24: Blend specialty products and focus on expensive specialty products for optimization. | R24: Re-specification | T24: 2 | U24: =VLOOKUP(H24,'2_Methodology (Value)'!$H$3:$H$1048576,1,FALSE) -> #N/A
B25: 10 | C25: Value | D25: Plant-based | E25: Vegetable Oils | G25: Value | H25: Are you leveraging specific strategies for managing expensive specialty products? If so, how effective have they been? | I25: No specific strategies | J25: Basic cost-saving measures | K25: Effective strategies for major specialties | L25: Advanced strategies with measurable cost reductions | M25: 0.02 | N25: 0.03 | O25: 0.8 | P25: Blend specialty products and focus on expensive specialty products for optimization. | T25: 3 | U25: =VLOOKUP(H25,'2_Methodology (Value)'!$H$3:$H$1048576,1,FALSE) -> #N/A
B26: 12 | C26: Value | D26: Plant-based | E26: Vegetable Oils | G26: Value | H26: How often do you identify opportunities to simplify your portfolio of vegetable oils to enhance procurement efficiency? | I26: Rarely addressed | J26: Occasional portfolio reviews | K26: Regular reviews to identify simplification | L26: Continuously optimized portfolio management | M26: 0.02 | N26: 0.03 | O26: 0.8 | P26: Simplify the portfolio where possible to reduce complexity and costs. | R26: Technical data mining | U26: =VLOOKUP(H26,'2_Methodology (Value)'!$H$3:$H$1048576,1,FALSE) -> #N/A
B27: 13 | C27: Value | D27: Plant-based | E27: Vegetable Oils | G27: Value | H27: To what extent do you maintain flexible formulations / recipe flexibility to accommodate alternative or varied specifications of vegetable oils? | I27: Not maintained | J27: Ad-hoc / one-off design and testing of new formulations, based on specific projects / initiatives | K27: We maintain a list of potential formulations, however the should-costs for these are not transparent / not maintained periodically | L27: We maintain a list of formulations, updated with market prices regularly to identify relative cost benefits | M27: 0.02 | N27: 0.03 | O27: 0.8 | P27: Enable recipe flexibility to expand sourcing options. | R27: Re-specification | T27: 3 | U27: =VLOOKUP(H27,'2_Methodology (Value)'!$H$3:$H$1048576,1,FALSE) -> #N/A

Sheet Sheet5

Sheet 2_Methodology (Value)
M1: Maturity Range | T1: Risk profile calc. | W1: Category-level savings / addressability | AK1: Directional initiative-level %es | BK1: Mapping for value initiative details view | BR1: Mapping for value initiative details view
A2: Initiative ID | B2: Industry group | C2: Industry segment | D2: L1 | E2: L2 | F2: Region | G2: Hypotheses type | H2: Hypotheses / Questions | I2: Risk metric Weightage (%) | J2: Standard initiative / value driver description | K2: 64 methods | L2: 16 Levers | M2: Low (1) | N2: Little (2) | O2: Middle (3) | P2: High (4) | Q2: Maturity score (1-4) | R2: Category health / maturity score (Value) | S2: Category health / maturity score (Risk) | T2: Weighted risk score calculation logic | U2: Weighted risk score (scale of 10) - higher score = higher risk | V2: Weighted category-level risk score | W2: Savings% (low) | X2: Savings% (high) | Y2: Addressability | Z2: Maturity adj savings % (low) | AA2: Maturity adj savings % (high) | AB2: Maturity adj savings $ (low) | AC2: Maturity adj savings $ (high) | AD2: # of value drivers / initiatives tested | AE2: Confidence score | AF2: Confidence bucket | AG2: Confidence adj savings % (low) | AH2: Confidence adj savings % (high) | AI2: Confidence adj savings $ (low) | AJ2: Confidence adj savings $ (high) | AK2: Savings BM% (low) | AL2: Savings BM% (high) | AM2: Intermediate calc. | AN2: Maturity adjusted savings weightage | AO2: savings % (low) | AP2: savings % (high) | AQ2: savings $ (low) | AR2: savings $ (high) | AS2: total proof points in methodology | AT2: Initiative impact score | AU2: Impact bucket | AV2: Proof points | AW2: Hypotheses brief | AX2: Qualifier type | AY2: Prompt to contextualize value driving Initiatives | AZ2: Proof point impact flag (GPT 5) | BA2: Prompt for overall initiative description | BB2: Risk levers linked to value levers/initiatives | BC2: Prompt to contextualize risk for value initiatives | BD2: Risk driver impact flag (GPT5) | BE2: Test 1 Proof point contextualization---- Perplexity (Claude Sonnet 4.0) | BF2: Test 2 Proof point contextualization---- ChatGPT (GPT 5) | BG2: Test 2 Proof point contextualization---- Perplexity (Claude Sonnet 4.0) | BH2: Test 2 Value contextualization ---- ChatGPT (GPT 5) applied on proof-point insights generated by Sonnet | BI2: Test 2 Risk contextualization for Value initiatives -- Perplexity (Sonnet 4.0) | BJ2: Test 2 - Final description of initiatives (Perplexity - Sonnrt 4.0) | BK2: Regional / country-specific cost differences | BL2: Fragmentation - by region | BM2: Fragmentation - by Supplier | BN2: Unit Price / index / cost driver trends | BO2: Internal price arbitrage | BP2: Category size vs peers | BQ2: Supplier concentration | BR2: Price volatility risk | BS2: Supplier conc risk | BT2: Supplier financial risk | BU2: Supplier geopolitical risk | BV2: Flag (active logics)
A3: 1 | B3: Consumer goods / products | C3: Food & beverages | D3: Plant-based | E3: Vegetable oils | G3: Value | H3: To what extent have you explored bundling of volumes across different types of vegetable oils to maximize economies of scale? | J3: Bundle volumes across SKUs to achieve savings derived from better economies of scale. Focus on high-spend SKUs that are purchased from multiple suppliers. Potentially consolidate SKUs within the tail. | L3: Volume bundling | M3: =VLOOKUP(H3,'1_Value & risk levers'!$H$9:$O$1048576,2,FALSE) -> Not practiced / not explored so far | N3: =VLOOKUP(H3,'1_Value & risk levers'!$H$9:$O$1048576,3,FALSE) -> Ad-hoc initiatives to bundle volume across suppliers | O3: =VLOOKUP(H3,'1_Value & risk levers'!$H$9:$O$1048576,4,FALSE) -> Suppliers are evaluated for their product coverage at the time of sourcing | P3: =VLOOKUP(H3,'1_Value & risk levers'!$H$9:$O$1048576,5,FALSE) -> Comprehensive bundling strategy across all vegetable oils - following an optimization approach to identify the right volume mix across suppliers and SKUs | Q3: =IF(VLOOKUP(H3,'1_Value & risk levers'!$H$9:$T$1048576,13,FALSE)=0,"",VLOOKUP(H3,'1_Value & risk levers'!$H$9:$T$1048576,13,FALSE)) -> 3 | R3: =AVERAGEIFS($Q$3:$Q$1048576,$G$3:$G$1048576,"Value") -> 2 | S3: =AVERAGEIFS($Q$3:$Q$1048576,$G$3:$G$1048576,"Risk") -> #DIV/0! | W3: 0.04 | X3: 0.1 | Y3: =VLOOKUP(H3,'1_Value & risk levers'!$H$9:$O$1048576,8,FALSE) -> 0.8 | Z3: =(4-AVERAGEIFS($Q$3:$Q$1048576,$AV$3:$AV$1048576,"Inflation"))*(X3-W3)/4+W3 -> 0.07 | AA3: =Z3+(X3-W3)/4 -> 0.085 | AB3: =Y3*Z3*50000000 -> 2800000 | AC3: =Y3*AA3*50000000 -> 3400000 | AD3: =(COUNTA($Q$3:$Q$1048576)-COUNTIFS($Q$3:$Q$1048576,"",$A$3:$A$1048576,"<>"))/41 -> 7 | AE3: =AVERAGE($AT$3:$AT$1048576)/10 -> 0.48864541 | AF3: =IF(AE3<0.5,"Low",IF(AE3<0.75,"Medium","High")) -> Low | AG3: =Z3-(1-AE3)*2/100 -> 0.059772908 | AH3: =AA3+(1-AE3)*2/100 -> 0.095227092 | AI3: =Y3*AG3*50000000 -> 2390916.3 | AJ3: =Y3*AH3*50000000 -> 3809083.7 | AK3: =VLOOKUP(H3,'1_Value & risk levers'!$H$9:$O$1048576,6,FALSE) -> 0.02 | AL3: =VLOOKUP(H3,'1_Value & risk levers'!$H$9:$O$1048576,7,FALSE) -> 0.05 | AM3: =IF(ISERROR((AK3+((AL3-AK3)*(4-Q3))/4)),"",(AK3+((AL3-AK3)*(4-Q3))/4)) -> 0.0275 | AN3: =IF(AM3="","",AM3/SUMIFS($AM$3:$AM$1048576,$AV$3:$AV$1048576,"Regional Spend Addressability")) -> 0.12790698 | AO3: =IF(AN3="","",AN3*AG3) -> 0.007645372 | AP3: =IF(AN3="","",AN3*AH3) -> 0.012180209 | AQ3: =IF(AN3="","",AN3*AB3) -> 358139.53 | AR3: =IF(AN3="","",AN3*AC3) -> 434883.72 | AS3: =COUNTIFS($A$3:$A$1048576,A3,$BG$3:$BG$1048576,"<>") -> 41 | AT3: =10*(COUNTIFS($A$3:$A$1048576,A3,$AZ$3:$AZ$1048576,"Medium",$BG$3:$BG$1048576,"<>")*0.625+COUNTIFS($A$3:$A$1048576,A3,$AZ$3:$AZ$1048576,"Low",$BG$3:$BG$1048576,"<>")*0.25+COUNTIFS($A$3:$A$1048576,A3,$AZ$3:$AZ$1048576,"High",$BG$3:$BG$1048576,"<>")*0.874)/COUNTIFS($A$3:$A$1048576,A3,$AY$3:$AY$1048576,"<>") -> 7.18375 | AU3: =IF(AT3<5,"Low",IF(AT3<7.5,"Medium","High")) -> Medium | AV3: Regional Spend Addressability | AW3: If a small number of countries/regions (e.g., 3 countries) contribute to a very high percentage of total spend (e.g., >80%), then these are the primary regions for initial procurement focus, indicating high addressability there. Conversely, highly fragmented global spend suggests lower immediate global addressability | AX3: Client data insights | AY3: If a large number of countries/regions (>3-4) contribute to the top >80% spend, then call out these countries/examples with potential for consolidation. If SKU/item level data is available, share examples of top SKUs/items that have a one-to-many mapping between plants/countries/regions-to-suppliers | AZ3: =IF(ISERROR(_xlfn.XLOOKUP(CONCATENATE(A3,"_",AV3),'Reference-Proof pt impact flag'!$I$3:$I$1048576,'Reference-Proof pt impact flag'!$G$3:$G$1048576)),"",_xlfn.XLOOKUP(CONCATENATE(A3,"_",AV3),'Reference-Proof pt impact flag'!$I$3:$I$1048576,'Reference-Proof pt impact flag'!$G$3:$G$1048576)) -> High | BA3: Contextualize and enrich the insights to make it 100-120 words summary explaining what you should do, with examples of reasons why. Structure this as bullet points, dont provide specific targets, and also talk about how future trends will impact this | BE3: Analysis reveals 100% vegetable oil spend concentrated in Malaysia across 3 plants (PH06, PH1A, potentially SHJ2), indicating extremely high regional addressability. Raw ricebran oil (Material 102038) represents the entire category spend with ~50+ unique suppliers serving these Malaysian operations. This concentration presents significant volume bundling opportunities across plants: PH06 and PH1A both source from overlapping suppliers including UNIVERSAL AGRO FOOD INDUSTRIES, ANSUL OVERSEAS, and SAI TEJA SOLVENT AND FOOD. Recommend implementing regional bundling strategy leveraging collective $40M+ annual spend to negotiate better economies of scale with key suppliers like SAWARIA FOOD & FATS, GOEL INTERNATIONAL, and SHAKTI FOOD OIL across all Malaysian plants. | BF3: =_xlfn.XLOOKUP(CONCATENATE(H3,"_",AV3),'Test 2 - Proof points - GPT5'!$T:$T,'Test 2 - Proof points - GPT5'!$S:$S) -> Insights: Spend is concentrated across plants — Malaysia 81.4%, India 7.1%, Australia 7.1%, Indonesia 4.5%. Actions: Bundle cross-plant demand windows and align delivery INCOTERMS to exploit backhauls and supplier MOQ breaks. | BG3: =_xlfn.XLOOKUP(CONCATENATE(H3,"_",AV3),'Test 2 -Proof points - Sonnet'!$AB:$AB,'Test 2 -Proof points - Sonnet'!$AA:$AA) -> â€¢ **Prioritize Malaysia-centric consolidation strategy**: With >95% spend concentrated in Malaysian plants (PH06, SHJ2), focus volume bundling efforts on consolidating multiple suppliers like SHIVAGANGA FOOD OIL EXTRACTIONS, SIDDAGANGA OIL & BIO INDUSTRIES, and SAKLECHA SOLVENTEX across both ricebran and sunflower oil categories. â€¢ **Leverage multi-supplier SKU opportunities**: Raw ricebran oil (Material 102038) shows procurement from 8+ different suppliers with similar specifications, creating immediate bundling potential to negotiate better pricing through volume concentration. â€¢ **Future market dynamics favor consolidation**: Rising commodity price volatility and supply chain disruptions are driving suppliers to prefer larger, committed volume relationships, making bundling strategies more effective in securing preferential pricing and supply continuity. | BH3: Why (Strategic Need): Rising price volatility, ESG demands, and digital procurement transformation are driving the need for supplier consolidation, cost efficiency, and risk mitigation. What (Insights Identified): 95% of spend is India/Malaysia-centric; ricebran oil alone is sourced from 10+ suppliers with identical specs. >75% of suppliers contribute to <20% of spend, and average spend per supplier trails industry benchmarks. How (Recommended Actions): Consolidate suppliers like SHIVAGANGA, SIDDAGANGA, and SAKLECHA across ricebran and sunflower oils. Eliminate tail suppliers with sporadic volumes (e.g., RAICHUR SOLVENTS). Leverage cross-category bundling with multi-oil suppliers. Prioritize strategic partnerships with financially stable, ESG-compliant vendors. Align sourcing strategy with market consolidation trends and future digitization shifts. | BJ3: What insights did I find? 95% of spend is concentrated in the India/Malaysia region with ricebran oil sourced from 10+ suppliers despite identical specifications. Over 75% of suppliers contribute to less than 20% of total spend, with average spend per supplier falling below industry benchmarks. This fragmentation limits economies of scale and negotiating power. Why is there a savings opportunity? Rising price volatility, ESG demands, and digital transformation are driving the need for supplier consolidation. The current fragmented supplier base prevents optimal volume leverage and increases administrative overhead. Consolidating volumes across similar SKUs can unlock better pricing through enhanced economies of scale. What should you do next? Consolidate suppliers like SHIVAGANGA, SIDDAGANGA, and SAKLECHA across ricebran and sunflower oils. Eliminate tail suppliers with sporadic volumes such as RAICHUR SOLVENTS. Leverage cross-category bundling opportunities with multi-oil suppliers and prioritize strategic partnerships with financially stable, ESG-compliant vendors. Potential risks involved Geographic concentration risk from consolidating with Indian suppliers could create vulnerability to regional disruptions. Heavy reliance on established suppliers may reduce negotiating leverage over time, while India's medium geopolitical risk rating could impact supply continuity and eliminate projected cost savings. | BL3: Yes | BV3: Yes
A4: 1 | B4: Consumer goods / products | C4: Food & beverages | D4: Plant-based | E4: Vegetable oils | G4: Value | H4: To what extent have you explored bundling of volumes across different types of vegetable oils to maximize economies of scale? | J4: Bundle volumes across SKUs to achieve savings derived from better economies of scale. Focus on high-spend SKUs that are purchased from multiple suppliers. Potentially consolidate SKUs within the tail | L4: Volume bundling | M4: =VLOOKUP(H4,'1_Value & risk levers'!$H$9:$O$1048576,2,FALSE) -> Not practiced / not explored so far | N4: =VLOOKUP(H4,'1_Value & risk levers'!$H$9:$O$1048576,3,FALSE) -> Ad-hoc initiatives to bundle volume across suppliers | O4: =VLOOKUP(H4,'1_Value & risk levers'!$H$9:$O$1048576,4,FALSE) -> Suppliers are evaluated for their product coverage at the time of sourcing | P4: =VLOOKUP(H4,'1_Value & risk levers'!$H$9:$O$1048576,5,FALSE) -> Comprehensive bundling strategy across all vegetable oils - following an optimization approach to identify the right volume mix across suppliers and SKUs | Q4: =IF(VLOOKUP(H4,'1_Value & risk levers'!$H$9:$T$1048576,13,FALSE)=0,"",VLOOKUP(H4,'1_Value & risk levers'!$H$9:$T$1048576,13,FALSE)) -> 3 | R4: =AVERAGEIFS($Q$3:$Q$1048576,$G$3:$G$1048576,"Value") -> 2 | S4: =AVERAGEIFS($Q$3:$Q$1048576,$G$3:$G$1048576,"Risk") -> #DIV/0! | W4: 0.04 | X4: 0.1 | Y4: =VLOOKUP(H4,'1_Value & risk levers'!$H$9:$O$1048576,8,FALSE) -> 0.8 | Z4: =(4-AVERAGEIFS($Q$3:$Q$1048576,$AV$3:$AV$1048576,"Inflation"))*(X4-W4)/4+W4 -> 0.07 | AA4: =Z4+(X4-W4)/4 -> 0.085 | AB4: =Y4*Z4*50000000 -> 2800000 | AC4: =Y4*AA4*50000000 -> 3400000 | AD4: =(COUNTA($Q$3:$Q$1048576)-COUNTIFS($Q$3:$Q$1048576,"",$A$3:$A$1048576,"<>"))/41 -> 7 | AE4: =AVERAGE($AT$3:$AT$1048576)/10 -> 0.48864541 | AF4: =IF(AE4<0.5,"Low",IF(AE4<0.75,"Medium","High")) -> Low | AG4: =Z4-(1-AE4)*2/100 -> 0.059772908 | AH4: =AA4+(1-AE4)*2/100 -> 0.095227092 | AI4: =Y4*AG4*50000000 -> 2390916.3 | AJ4: =Y4*AH4*50000000 -> 3809083.7 | AK4: =VLOOKUP(H4,'1_Value & risk levers'!$H$9:$O$1048576,6,FALSE) -> 0.02 | AL4: =VLOOKUP(H4,'1_Value & risk levers'!$H$9:$O$1048576,7,FALSE) -> 0.05 | AM4: =IF(ISERROR((AK4+((AL4-AK4)*(4-Q4))/4)),"",(AK4+((AL4-AK4)*(4-Q4))/4)) -> 0.0275 | AN4: =IF(AM4="","",AM4/SUMIFS($AM$3:$AM$1048576,$AV$3:$AV$1048576,"Regional Spend Addressability")) -> 0.12790698 | AO4: =IF(AN4="","",AN4*AG4) -> 0.007645372 | AP4: =IF(AN4="","",AN4*AH4) -> 0.012180209 | AQ4: =IF(AN4="","",AN4*AB4) -> 358139.53 | AR4: =IF(AN4="","",AN4*AC4) -> 434883.72 | AS4: =COUNTIFS($A$3:$A$1048576,A4,$BG$3:$BG$1048576,"<>") -> 41 | AT4: =10*(COUNTIFS($A$3:$A$1048576,A4,$AZ$3:$AZ$1048576,"Medium",$BG$3:$BG$1048576,"<>")*0.625+COUNTIFS($A$3:$A$1048576,A4,$AZ$3:$AZ$1048576,"Low",$BG$3:$BG$1048576,"<>")*0.25+COUNTIFS($A$3:$A$1048576,A4,$AZ$3:$AZ$1048576,"High",$BG$3:$BG$1048576,"<>")*0.874)/COUNTIFS($A$3:$A$1048576,A4,$AY$3:$AY$1048576,"<>") -> 7.18375 | AU4: =IF(AT4<5,"Low",IF(AT4<7.5,"Medium","High")) -> Medium | AV4: Single Sourcing / Supplier Dependency Risk | AW4: If a high-spend category (e.g., top 10% of total spend categories) or a critical category is supplied by only one unique supplier, then the client faces elevated supply chain and operational risk due to dependency | AX4: Client data insights | AZ4: =IF(ISERROR(_xlfn.XLOOKUP(CONCATENATE(A4,"_",AV4),'Reference-Proof pt impact flag'!$I$3:$I$1048576,'Reference-Proof pt impact flag'!$G$3:$G$1048576)),"",_xlfn.XLOOKUP(CONCATENATE(A4,"_",AV4),'Reference-Proof pt impact flag'!$I$3:$I$1048576,'Reference-Proof pt impact flag'!$G$3:$G$1048576)) | BF4: =_xlfn.XLOOKUP(CONCATENATE(H4,"_",AV4),'Test 2 - Proof points - GPT5'!$T:$T,'Test 2 - Proof points - GPT5'!$S:$S) -> #N/A | BG4: =_xlfn.XLOOKUP(CONCATENATE(H4,"_",AV4),'Test 2 -Proof points - Sonnet'!$AB:$AB,'Test 2 -Proof points - Sonnet'!$AA:$AA) -> #N/A | BJ4: What insights did I find? 95% of spend is concentrated in the India/Malaysia region with ricebran oil sourced from 10+ suppliers despite identical specifications. Over 75% of suppliers contribute to less than 20% of total spend, with average spend per supplier falling below industry benchmarks. This fragmentation limits economies of scale and negotiating power. Why is there a savings opportunity? Rising price volatility, ESG demands, and digital transformation are driving the need for supplier consolidation. The current fragmented supplier base prevents optimal volume leverage and increases administrative overhead. Consolidating volumes across similar SKUs can unlock better pricing through enhanced economies of scale. What should you do next? Consolidate suppliers like SHIVAGANGA, SIDDAGANGA, and SAKLECHA across ricebran and sunflower oils. Eliminate tail suppliers with sporadic volumes such as RAICHUR SOLVENTS. Leverage cross-category bundling opportunities with multi-oil suppliers and prioritize strategic partnerships with financially stable, ESG-compliant vendors. Potential risks involved Geographic concentration risk from consolidating with Indian suppliers could create vulnerability to regional disruptions. Heavy reliance on established suppliers may reduce negotiating leverage over time, while India's medium geopolitical risk rating could impact supply continuity and eliminate projected cost savings.
A5: 1 | B5: Consumer goods / products | C5: Food & beverages | D5: Plant-based | E5: Vegetable oils | G5: Value | H5: To what extent have you explored bundling of volumes across different types of vegetable oils to maximize economies of scale? | J5: Bundle volumes across SKUs to achieve savings derived from better economies of scale. Focus on high-spend SKUs that are purchased from multiple suppliers. Potentially consolidate SKUs within the tail | L5: Volume bundling | M5: =VLOOKUP(H5,'1_Value & risk levers'!$H$9:$O$1048576,2,FALSE) -> Not practiced / not explored so far | N5: =VLOOKUP(H5,'1_Value & risk levers'!$H$9:$O$1048576,3,FALSE) -> Ad-hoc initiatives to bundle volume across suppliers | O5: =VLOOKUP(H5,'1_Value & risk levers'!$H$9:$O$1048576,4,FALSE) -> Suppliers are evaluated for their product coverage at the time of sourcing | P5: =VLOOKUP(H5,'1_Value & risk levers'!$H$9:$O$1048576,5,FALSE) -> Comprehensive bundling strategy across all vegetable oils - following an optimization approach to identify the right volume mix across suppliers and SKUs | Q5: =IF(VLOOKUP(H5,'1_Value & risk levers'!$H$9:$T$1048576,13,FALSE)=0,"",VLOOKUP(H5,'1_Value & risk levers'!$H$9:$T$1048576,13,FALSE)) -> 3 | R5: =AVERAGEIFS($Q$3:$Q$1048576,$G$3:$G$1048576,"Value") -> 2 | S5: =AVERAGEIFS($Q$3:$Q$1048576,$G$3:$G$1048576,"Risk") -> #DIV/0! | W5: 0.04 | X5: 0.1 | Y5: =VLOOKUP(H5,'1_Value & risk levers'!$H$9:$O$1048576,8,FALSE) -> 0.8 | Z5: =(4-AVERAGEIFS($Q$3:$Q$1048576,$AV$3:$AV$1048576,"Inflation"))*(X5-W5)/4+W5 -> 0.07 | AA5: =Z5+(X5-W5)/4 -> 0.085 | AB5: =Y5*Z5*50000000 -> 2800000 | AC5: =Y5*AA5*50000000 -> 3400000 | AD5: =(COUNTA($Q$3:$Q$1048576)-COUNTIFS($Q$3:$Q$1048576,"",$A$3:$A$1048576,"<>"))/41 -> 7 | AE5: =AVERAGE($AT$3:$AT$1048576)/10 -> 0.48864541 | AF5: =IF(AE5<0.5,"Low",IF(AE5<0.75,"Medium","High")) -> Low | AG5: =Z5-(1-AE5)*2/100 -> 0.059772908 | AH5: =AA5+(1-AE5)*2/100 -> 0.095227092 | AI5: =Y5*AG5*50000000 -> 2390916.3 | AJ5: =Y5*AH5*50000000 -> 3809083.7 | AK5: =VLOOKUP(H5,'1_Value & risk levers'!$H$9:$O$1048576,6,FALSE) -> 0.02 | AL5: =VLOOKUP(H5,'1_Value & risk levers'!$H$9:$O$1048576,7,FALSE) -> 0.05 | AM5: =IF(ISERROR((AK5+((AL5-AK5)*(4-Q5))/4)),"",(AK5+((AL5-AK5)*(4-Q5))/4)) -> 0.0275 | AN5: =IF(AM5="","",AM5/SUMIFS($AM$3:$AM$1048576,$AV$3:$AV$1048576,"Regional Spend Addressability")) -> 0.12790698 | AO5: =IF(AN5="","",AN5*AG5) -> 0.007645372 | AP5: =IF(AN5="","",AN5*AH5) -> 0.012180209 | AQ5: =IF(AN5="","",AN5*AB5) -> 358139.53 | AR5: =IF(AN5="","",AN5*AC5) -> 434883.72 | AS5: =COUNTIFS($A$3:$A$1048576,A5,$BG$3:$BG$1048576,"<>") -> 41 | AT5: =10*(COUNTIFS($A$3:$A$1048576,A5,$AZ$3:$AZ$1048576,"Medium",$BG$3:$BG$1048576,"<>")*0.625+COUNTIFS($A$3:$A$1048576,A5,$AZ$3:$AZ$1048576,"Low",$BG$3:$BG$1048576,"<>")*0.25+COUNTIFS($A$3:$A$1048576,A5,$AZ$3:$AZ$1048576,"High",$BG$3:$BG$1048576,"<>")*0.874)/COUNTIFS($A$3:$A$1048576,A5,$AY$3:$AY$1048576,"<>") -> 7.18375 | AU5: =IF(AT5<5,"Low",IF(AT5<7.5,"Medium","High")) -> Medium | AV5: Supplier Concentration Risk | AW5: If a small number of suppliers (e.g., top 5-7%) account for a disproportionately large percentage of total spend (e.g., >70-90%), then the overall organization has a high supplier concentration risk, potentially limiting leverage and increasing exposure to a few vendor's issues | AX5: Client data insights | AZ5: =IF(ISERROR(_xlfn.XLOOKUP(CONCATENATE(A5,"_",AV5),'Reference-Proof pt impact flag'!$I$3:$I$1048576,'Reference-Proof pt impact flag'!$G$3:$G$1048576)),"",_xlfn.XLOOKUP(CONCATENATE(A5,"_",AV5),'Reference-Proof pt impact flag'!$I$3:$I$1048576,'Reference-Proof pt impact flag'!$G$3:$G$1048576)) | BF5: =_xlfn.XLOOKUP(CONCATENATE(H5,"_",AV5),'Test 2 - Proof points - GPT5'!$T:$T,'Test 2 - Proof points - GPT5'!$S:$S) -> #N/A | BG5: =_xlfn.XLOOKUP(CONCATENATE(H5,"_",AV5),'Test 2 -Proof points - Sonnet'!$AB:$AB,'Test 2 -Proof points - Sonnet'!$AA:$AA) -> #N/A | BJ5: What insights did I find? 95% of spend is concentrated in the India/Malaysia region with ricebran oil sourced from 10+ suppliers despite identical specifications. Over 75% of suppliers contribute to less than 20% of total spend, with average spend per supplier falling below industry benchmarks. This fragmentation limits economies of scale and negotiating power. Why is there a savings opportunity? Rising price volatility, ESG demands, and digital transformation are driving the need for supplier consolidation. The current fragmented supplier base prevents optimal volume leverage and increases administrative overhead. Consolidating volumes across similar SKUs can unlock better pricing through enhanced economies of scale. What should you do next? Consolidate suppliers like SHIVAGANGA, SIDDAGANGA, and SAKLECHA across ricebran and sunflower oils. Eliminate tail suppliers with sporadic volumes such as RAICHUR SOLVENTS. Leverage cross-category bundling opportunities with multi-oil suppliers and prioritize strategic partnerships with financially stable, ESG-compliant vendors. Potential risks involved Geographic concentration risk from consolidating with Indian suppliers could create vulnerability to regional disruptions. Heavy reliance on established suppliers may reduce negotiating leverage over time, while India's medium geopolitical risk rating could impact supply continuity and eliminate projected cost savings.
A6: 1 | B6: Consumer goods / products | C6: Food & beverages | D6: Plant-based | E6: Vegetable oils | G6: Value | H6: To what extent have you explored bundling of volumes across different types of vegetable oils to maximize economies of scale? | J6: Bundle volumes across SKUs to achieve savings derived from better economies of scale. Focus on high-spend SKUs that are purchased from multiple suppliers. Potentially consolidate SKUs within the tail | L6: Volume bundling | M6: =VLOOKUP(H6,'1_Value & risk levers'!$H$9:$O$1048576,2,FALSE) -> Not practiced / not explored so far | N6: =VLOOKUP(H6,'1_Value & risk levers'!$H$9:$O$1048576,3,FALSE) -> Ad-hoc initiatives to bundle volume across suppliers | O6: =VLOOKUP(H6,'1_Value & risk levers'!$H$9:$O$1048576,4,FALSE) -> Suppliers are evaluated for their product coverage at the time of sourcing | P6: =VLOOKUP(H6,'1_Value & risk levers'!$H$9:$O$1048576,5,FALSE) -> Comprehensive bundling strategy across all vegetable oils - following an optimization approach to identify the right volume mix across suppliers and SKUs | Q6: =IF(VLOOKUP(H6,'1_Value & risk levers'!$H$9:$T$1048576,13,FALSE)=0,"",VLOOKUP(H6,'1_Value & risk levers'!$H$9:$T$1048576,13,FALSE)) -> 3 | R6: =AVERAGEIFS($Q$3:$Q$1048576,$G$3:$G$1048576,"Value") -> 2 | S6: =AVERAGEIFS($Q$3:$Q$1048576,$G$3:$G$1048576,"Risk") -> #DIV/0! | W6: 0.04 | X6: 0.1 | Y6: =VLOOKUP(H6,'1_Value & risk levers'!$H$9:$O$1048576,8,FALSE) -> 0.8 | Z6: =(4-AVERAGEIFS($Q$3:$Q$1048576,$AV$3:$AV$1048576,"Inflation"))*(X6-W6)/4+W6 -> 0.07 | AA6: =Z6+(X6-W6)/4 -> 0.085 | AB6: =Y6*Z6*50000000 -> 2800000 | AC6: =Y6*AA6*50000000 -> 3400000 | AD6: =(COUNTA($Q$3:$Q$1048576)-COUNTIFS($Q$3:$Q$1048576,"",$A$3:$A$1048576,"<>"))/41 -> 7 | AE6: =AVERAGE($AT$3:$AT$1048576)/10 -> 0.48864541 | AF6: =IF(AE6<0.5,"Low",IF(AE6<0.75,"Medium","High")) -> Low | AG6: =Z6-(1-AE6)*2/100 -> 0.059772908 | AH6: =AA6+(1-AE6)*2/100 -> 0.095227092 | AI6: =Y6*AG6*50000000 -> 2390916.3 | AJ6: =Y6*AH6*50000000 -> 3809083.7 | AK6: =VLOOKUP(H6,'1_Value & risk levers'!$H$9:$O$1048576,6,FALSE) -> 0.02 | AL6: =VLOOKUP(H6,'1_Value & risk levers'!$H$9:$O$1048576,7,FALSE) -> 0.05 | AM6: =IF(ISERROR((AK6+((AL6-AK6)*(4-Q6))/4)),"",(AK6+((AL6-AK6)*(4-Q6))/4)) -> 0.0275 | AN6: =IF(AM6="","",AM6/SUMIFS($AM$3:$AM$1048576,$AV$3:$AV$1048576,"Regional Spend Addressability")) -> 0.12790698 | AO6: =IF(AN6="","",AN6*AG6) -> 0.007645372 | AP6: =IF(AN6="","",AN6*AH6) -> 0.012180209 | AQ6: =IF(AN6="","",AN6*AB6) -> 358139.53 | AR6: =IF(AN6="","",AN6*AC6) -> 434883.72 | AS6: =COUNTIFS($A$3:$A$1048576,A6,$BG$3:$BG$1048576,"<>") -> 41 | AT6: =10*(COUNTIFS($A$3:$A$1048576,A6,$AZ$3:$AZ$1048576,"Medium",$BG$3:$BG$1048576,"<>")*0.625+COUNTIFS($A$3:$A$1048576,A6,$AZ$3:$AZ$1048576,"Low",$BG$3:$BG$1048576,"<>")*0.25+COUNTIFS($A$3:$A$1048576,A6,$AZ$3:$AZ$1048576,"High",$BG$3:$BG$1048576,"<>")*0.874)/COUNTIFS($A$3:$A$1048576,A6,$AY$3:$AY$1048576,"<>") -> 7.18375 | AU6: =IF(AT6<5,"Low",IF(AT6<7.5,"Medium","High")) -> Medium | AV6: Tail Spend Consolidation Opportunity - Volume & Administrative Savings | AW6: If the lowest 10-20% of total spend (by value) is distributed across more than 70-80% of the total unique suppliers, then significant opportunity exists for both administrative cost reduction (managing fewer vendors) and price savings through consolidation | AX6: Client data insights | AY6: In case this proof-point shows high fragmentation in bottom 20% spend, then augment the initiative by describing the extent of fragmentation e.g., >90% supplier make up the bottom 20% spend. | AZ6: =IF(ISERROR(_xlfn.XLOOKUP(CONCATENATE(A6,"_",AV6),'Reference-Proof pt impact flag'!$I$3:$I$1048576,'Reference-Proof pt impact flag'!$G$3:$G$1048576)),"",_xlfn.XLOOKUP(CONCATENATE(A6,"_",AV6),'Reference-Proof pt impact flag'!$I$3:$I$1048576,'Reference-Proof pt impact flag'!$G$3:$G$1048576)) -> High | BA6: Contextualize and enrich the insights to make it 100-120 words summary explaining what you should do, with examples of reasons why. Structure this as bullet points, dont provide specific targets, and also talk about how future trends will impact this | BE6: Significant tail spend consolidation opportunity identified. With 50+ unique suppliers serving raw ricebran oil requirements, substantial fragmentation exists in the supplier base. Many suppliers like BENI AGRO PRODUCTS PVT LTD, RAICHUR SOLVENTS LIMITED, and PRAKRUTHI SOLVEX PRIVATE LIMITED appear with smaller, less frequent transactions suggesting they represent tail spend. Analysis shows numerous suppliers with sporadic order patterns and smaller volumes, indicating high administrative burden with limited volume leverage. Recommend consolidating tail suppliers (bottom 20% spend) representing approximately 40+ vendors into preferred supplier agreements with top-performing vendors, potentially reducing supplier base by 60-70% while maintaining supply security and achieving both administrative cost savings and better pricing through volume consolidation. | BF6: =_xlfn.XLOOKUP(CONCATENATE(H6,"_",AV6),'Test 2 - Proof points - GPT5'!$T:$T,'Test 2 - Proof points - GPT5'!$S:$S) -> Insights: Supplier base: 87 vendors; Top-1 share 8.6%; HHI ≈ 344 → fragmented. Leverage via bundled bids and two-tiering is feasible. Top leverage candidates by spend: RAW RICEBRAN OIL, REFINED RICEBRAN OIL, REFINED SUNFLOWER OIL EDIBLE. Estimated admin + unit-price benefit from tail collapse (tail 20.6%): 1–3% admin and 2–5% price on rebid. | BG6: =_xlfn.XLOOKUP(CONCATENATE(H6,"_",AV6),'Test 2 -Proof points - Sonnet'!$AB:$AB,'Test 2 -Proof points - Sonnet'!$AA:$AA) -> â€¢ **Address tail supplier fragmentation**: Analysis shows >75% of unique suppliers (including RAICHUR SOLVENTS, smaller regional processors) contribute to bottom 20% of spend, creating administrative burden and limiting negotiation leverage. â€¢ **Consolidate smaller volume suppliers**: Multiple suppliers like UNIVERSAL AGRO FOOD INDUSTRIES, N.K.PROTEINS LIMITED show sporadic, small-volume transactions that can be consolidated into preferred supplier relationships or eliminated entirely. â€¢ **Future procurement digitization trends**: Industry shift toward supplier relationship management platforms and automated procurement processes will favor organizations with streamlined supplier portfolios, making tail spend consolidation essential for operational efficiency and cost competitiveness. | BH6: Why (Strategic Need): Rising price volatility, ESG demands, and digital procurement transformation are driving the need for supplier consolidation, cost efficiency, and risk mitigation. What (Insights Identified): 95% of spend is India/Malaysia-centric; ricebran oil alone is sourced from 10+ suppliers with identical specs. >75% of suppliers contribute to <20% of spend, and average spend per supplier trails industry benchmarks. How (Recommended Actions): Consolidate suppliers like SHIVAGANGA, SIDDAGANGA, and SAKLECHA across ricebran and sunflower oils. Eliminate tail suppliers with sporadic volumes (e.g., RAICHUR SOLVENTS). Leverage cross-category bundling with multi-oil suppliers. Prioritize strategic partnerships with financially stable, ESG-compliant vendors. Align sourcing strategy with market consolidation trends and future digitization shifts. | BJ6: What insights did I find? 95% of spend is concentrated in the India/Malaysia region with ricebran oil sourced from 10+ suppliers despite identical specifications. Over 75% of suppliers contribute to less than 20% of total spend, with average spend per supplier falling below industry benchmarks. This fragmentation limits economies of scale and negotiating power. Why is there a savings opportunity? Rising price volatility, ESG demands, and digital transformation are driving the need for supplier consolidation. The current fragmented supplier base prevents optimal volume leverage and increases administrative overhead. Consolidating volumes across similar SKUs can unlock better pricing through enhanced economies of scale. What should you do next? Consolidate suppliers like SHIVAGANGA, SIDDAGANGA, and SAKLECHA across ricebran and sunflower oils. Eliminate tail suppliers with sporadic volumes such as RAICHUR SOLVENTS. Leverage cross-category bundling opportunities with multi-oil suppliers and prioritize strategic partnerships with financially stable, ESG-compliant vendors. Potential risks involved Geographic concentration risk from consolidating with Indian suppliers could create vulnerability to regional disruptions. Heavy reliance on established suppliers may reduce negotiating leverage over time, while India's medium geopolitical risk rating could impact supply continuity and eliminate projected cost savings. | BM6: Yes | BV6: Yes
A7: 1 | B7: Consumer goods / products | C7: Food & beverages | D7: Plant-based | E7: Vegetable oils | G7: Value | H7: To what extent have you explored bundling of volumes across different types of vegetable oils to maximize economies of scale? | J7: Bundle volumes across SKUs to achieve savings derived from better economies of scale. Focus on high-spend SKUs that are purchased from multiple suppliers. Potentially consolidate SKUs within the tail | L7: Volume bundling | M7: =VLOOKUP(H7,'1_Value & risk levers'!$H$9:$O$1048576,2,FALSE) -> Not practiced / not explored so far | N7: =VLOOKUP(H7,'1_Value & risk levers'!$H$9:$O$1048576,3,FALSE) -> Ad-hoc initiatives to bundle volume across suppliers | O7: =VLOOKUP(H7,'1_Value & risk levers'!$H$9:$O$1048576,4,FALSE) -> Suppliers are evaluated for their product coverage at the time of sourcing | P7: =VLOOKUP(H7,'1_Value & risk levers'!$H$9:$O$1048576,5,FALSE) -> Comprehensive bundling strategy across all vegetable oils - following an optimization approach to identify the right volume mix across suppliers and SKUs | Q7: =IF(VLOOKUP(H7,'1_Value & risk levers'!$H$9:$T$1048576,13,FALSE)=0,"",VLOOKUP(H7,'1_Value & risk levers'!$H$9:$T$1048576,13,FALSE)) -> 3 | R7: =AVERAGEIFS($Q$3:$Q$1048576,$G$3:$G$1048576,"Value") -> 2 | S7: =AVERAGEIFS($Q$3:$Q$1048576,$G$3:$G$1048576,"Risk") -> #DIV/0! | W7: 0.04 | X7: 0.1 | Y7: =VLOOKUP(H7,'1_Value & risk levers'!$H$9:$O$1048576,8,FALSE) -> 0.8 | Z7: =(4-AVERAGEIFS($Q$3:$Q$1048576,$AV$3:$AV$1048576,"Inflation"))*(X7-W7)/4+W7 -> 0.07 | AA7: =Z7+(X7-W7)/4 -> 0.085 | AB7: =Y7*Z7*50000000 -> 2800000 | AC7: =Y7*AA7*50000000 -> 3400000 | AD7: =(COUNTA($Q$3:$Q$1048576)-COUNTIFS($Q$3:$Q$1048576,"",$A$3:$A$1048576,"<>"))/41 -> 7 | AE7: =AVERAGE($AT$3:$AT$1048576)/10 -> 0.48864541 | AF7: =IF(AE7<0.5,"Low",IF(AE7<0.75,"Medium","High")) -> Low | AG7: =Z7-(1-AE7)*2/100 -> 0.059772908 | AH7: =AA7+(1-AE7)*2/100 -> 0.095227092 | AI7: =Y7*AG7*50000000 -> 2390916.3 | AJ7: =Y7*AH7*50000000 -> 3809083.7 | AK7: =VLOOKUP(H7,'1_Value & risk levers'!$H$9:$O$1048576,6,FALSE) -> 0.02 | AL7: =VLOOKUP(H7,'1_Value & risk levers'!$H$9:$O$1048576,7,FALSE) -> 0.05 | AM7: =IF(ISERROR((AK7+((AL7-AK7)*(4-Q7))/4)),"",(AK7+((AL7-AK7)*(4-Q7))/4)) -> 0.0275 | AN7: =IF(AM7="","",AM7/SUMIFS($AM$3:$AM$1048576,$AV$3:$AV$1048576,"Regional Spend Addressability")) -> 0.12790698 | AO7: =IF(AN7="","",AN7*AG7) -> 0.007645372 | AP7: =IF(AN7="","",AN7*AH7) -> 0.012180209 | AQ7: =IF(AN7="","",AN7*AB7) -> 358139.53 | AR7: =IF(AN7="","",AN7*AC7) -> 434883.72 | AS7: =COUNTIFS($A$3:$A$1048576,A7,$BG$3:$BG$1048576,"<>") -> 41 | AT7: =10*(COUNTIFS($A$3:$A$1048576,A7,$AZ$3:$AZ$1048576,"Medium",$BG$3:$BG$1048576,"<>")*0.625+COUNTIFS($A$3:$A$1048576,A7,$AZ$3:$AZ$1048576,"Low",$BG$3:$BG$1048576,"<>")*0.25+COUNTIFS($A$3:$A$1048576,A7,$AZ$3:$AZ$1048576,"High",$BG$3:$BG$1048576,"<>")*0.874)/COUNTIFS($A$3:$A$1048576,A7,$AY$3:$AY$1048576,"<>") -> 7.18375 | AU7: =IF(AT7<5,"Low",IF(AT7<7.5,"Medium","High")) -> Medium | AV7: Volume Leverage from Fragmented Category Spend | AW7: If a single commodity or category (e.g., IT Software Licenses, Packaging) has its spend distributed across a high number of unique suppliers (e.g., >10) that do not represent unique functionalities or specialized needs, then significant opportunities for volume consolidation and negotiation exist | AX7: Client data insights | AY7: If top categories and/or SKUs/items have multiple suppliers; and if these suppliers provide similar/identical products and services; then callout these examples of suppliers that can be consolidated | AZ7: =IF(ISERROR(_xlfn.XLOOKUP(CONCATENATE(A7,"_",AV7),'Reference-Proof pt impact flag'!$I$3:$I$1048576,'Reference-Proof pt impact flag'!$G$3:$G$1048576)),"",_xlfn.XLOOKUP(CONCATENATE(A7,"_",AV7),'Reference-Proof pt impact flag'!$I$3:$I$1048576,'Reference-Proof pt impact flag'!$G$3:$G$1048576)) -> High | BA7: Contextualize and enrich the insights to make it 100-120 words summary explaining what you should do, with examples of reasons why. Structure this as bullet points, dont provide specific targets, and also talk about how future trends will impact this | BE7: Exceptional volume leverage opportunity confirmed. Raw ricebran oil (Material 102038) - a single, standardized commodity - is sourced from 50+ suppliers across Malaysian plants, representing significant fragmentation for identical product specifications. Key consolidation targets include: (1) SAKLECHA SOLVENTEX PVT. LTD., M/S ABHAY SOLVENTS PVT LTD., and VIJAY KUMAR AGRO OILS providing similar products to PH06; (2) Multiple Indian suppliers (SAWARIA FOOD & FATS, GOEL INTERNATIONAL, SHAKTI FOOD OIL) serving both plants with identical raw ricebran oil; (3) Smaller suppliers like RAICHUR SOLVENTS LIMITED and PRAKRUTHI SOLVEX delivering same specifications. Recommend consolidating to 15-20 strategic suppliers to capture 80% of volume, leveraging collective $40M+ spend for cost reduction while maintaining supply security through geographic and supplier diversification. | BF7: =_xlfn.XLOOKUP(CONCATENATE(H7,"_",AV7),'Test 2 - Proof points - GPT5'!$T:$T,'Test 2 - Proof points - GPT5'!$S:$S) -> Insights: Supplier base: 87 vendors; Top-1 share 8.6%; HHI ≈ 344 → fragmented. Leverage via bundled bids and two-tiering is feasible. Top leverage candidates by spend: RAW RICEBRAN OIL, REFINED RICEBRAN OIL, REFINED SUNFLOWER OIL EDIBLE. Estimated admin + unit-price benefit from tail collapse (tail 20.6%): 1–3% admin and 2–5% price on rebid. | BG7: =_xlfn.XLOOKUP(CONCATENATE(H7,"_",AV7),'Test 2 -Proof points - Sonnet'!$AB:$AB,'Test 2 -Proof points - Sonnet'!$AA:$AA) -> â€¢ **Consolidate identical ricebran oil sourcing**: Raw ricebran oil (Material 102038) is procured from 10+ suppliers including SHIVAGANGA FOOD OIL EXTRACTIONS, SIDDAGANGA OIL & BIO INDUSTRIES, SAKLECHA SOLVENTEX - all providing identical specifications, creating consolidation opportunities. â€¢ **Leverage cross-oil-type negotiations**: Suppliers like UNIVERSAL AGRO FOOD INDUSTRIES serve both ricebran and sunflower oil categories, enabling bundled negotiations across vegetable oil types for volume discounts. â€¢ **Future supply chain consolidation**: Industry trend toward fewer, strategic supplier partnerships driven by sustainability requirements and supply chain resilience needs will reward early movers who proactively consolidate volumes with capable, multi-category suppliers. | BH7: Why (Strategic Need): Rising price volatility, ESG demands, and digital procurement transformation are driving the need for supplier consolidation, cost efficiency, and risk mitigation. What (Insights Identified): 95% of spend is India/Malaysia-centric; ricebran oil alone is sourced from 10+ suppliers with identical specs. >75% of suppliers contribute to <20% of spend, and average spend per supplier trails industry benchmarks. How (Recommended Actions): Consolidate suppliers like SHIVAGANGA, SIDDAGANGA, and SAKLECHA across ricebran and sunflower oils. Eliminate tail suppliers with sporadic volumes (e.g., RAICHUR SOLVENTS). Leverage cross-category bundling with multi-oil suppliers. Prioritize strategic partnerships with financially stable, ESG-compliant vendors. Align sourcing strategy with market consolidation trends and future digitization shifts. | BJ7: What insights did I find? 95% of spend is concentrated in the India/Malaysia region with ricebran oil sourced from 10+ suppliers despite identical specifications. Over 75% of suppliers contribute to less than 20% of total spend, with average spend per supplier falling below industry benchmarks. This fragmentation limits economies of scale and negotiating power. Why is there a savings opportunity? Rising price volatility, ESG demands, and digital transformation are driving the need for supplier consolidation. The current fragmented supplier base prevents optimal volume leverage and increases administrative overhead. Consolidating volumes across similar SKUs can unlock better pricing through enhanced economies of scale. What should you do next? Consolidate suppliers like SHIVAGANGA, SIDDAGANGA, and SAKLECHA across ricebran and sunflower oils. Eliminate tail suppliers with sporadic volumes such as RAICHUR SOLVENTS. Leverage cross-category bundling opportunities with multi-oil suppliers and prioritize strategic partnerships with financially stable, ESG-compliant vendors. Potential risks involved Geographic concentration risk from consolidating with Indian suppliers could create vulnerability to regional disruptions. Heavy reliance on established suppliers may reduce negotiating leverage over time, while India's medium geopolitical risk rating could impact supply continuity and eliminate projected cost savings. | BM7: Yes | BV7: Yes
A8: 1 | B8: Consumer goods / products | C8: Food & beverages | D8: Plant-based | E8: Vegetable oils | G8: Value | H8: To what extent have you explored bundling of volumes across different types of vegetable oils to maximize economies of scale? | J8: Bundle volumes across SKUs to achieve savings derived from better economies of scale. Focus on high-spend SKUs that are purchased from multiple suppliers. Potentially consolidate SKUs within the tail | L8: Volume bundling | M8: =VLOOKUP(H8,'1_Value & risk levers'!$H$9:$O$1048576,2,FALSE) -> Not practiced / not explored so far | N8: =VLOOKUP(H8,'1_Value & risk levers'!$H$9:$O$1048576,3,FALSE) -> Ad-hoc initiatives to bundle volume across suppliers | O8: =VLOOKUP(H8,'1_Value & risk levers'!$H$9:$O$1048576,4,FALSE) -> Suppliers are evaluated for their product coverage at the time of sourcing | P8: =VLOOKUP(H8,'1_Value & risk levers'!$H$9:$O$1048576,5,FALSE) -> Comprehensive bundling strategy across all vegetable oils - following an optimization approach to identify the right volume mix across suppliers and SKUs | Q8: =IF(VLOOKUP(H8,'1_Value & risk levers'!$H$9:$T$1048576,13,FALSE)=0,"",VLOOKUP(H8,'1_Value & risk levers'!$H$9:$T$1048576,13,FALSE)) -> 3 | R8: =AVERAGEIFS($Q$3:$Q$1048576,$G$3:$G$1048576,"Value") -> 2 | S8: =AVERAGEIFS($Q$3:$Q$1048576,$G$3:$G$1048576,"Risk") -> #DIV/0! | W8: 0.04 | X8: 0.1 | Y8: =VLOOKUP(H8,'1_Value & risk levers'!$H$9:$O$1048576,8,FALSE) -> 0.8 | Z8: =(4-AVERAGEIFS($Q$3:$Q$1048576,$AV$3:$AV$1048576,"Inflation"))*(X8-W8)/4+W8 -> 0.07 | AA8: =Z8+(X8-W8)/4 -> 0.085 | AB8: =Y8*Z8*50000000 -> 2800000 | AC8: =Y8*AA8*50000000 -> 3400000 | AD8: =(COUNTA($Q$3:$Q$1048576)-COUNTIFS($Q$3:$Q$1048576,"",$A$3:$A$1048576,"<>"))/41 -> 7 | AE8: =AVERAGE($AT$3:$AT$1048576)/10 -> 0.48864541 | AF8: =IF(AE8<0.5,"Low",IF(AE8<0.75,"Medium","High")) -> Low | AG8: =Z8-(1-AE8)*2/100 -> 0.059772908 | AH8: =AA8+(1-AE8)*2/100 -> 0.095227092 | AI8: =Y8*AG8*50000000 -> 2390916.3 | AJ8: =Y8*AH8*50000000 -> 3809083.7 | AK8: =VLOOKUP(H8,'1_Value & risk levers'!$H$9:$O$1048576,6,FALSE) -> 0.02 | AL8: =VLOOKUP(H8,'1_Value & risk levers'!$H$9:$O$1048576,7,FALSE) -> 0.05 | AM8: =IF(ISERROR((AK8+((AL8-AK8)*(4-Q8))/4)),"",(AK8+((AL8-AK8)*(4-Q8))/4)) -> 0.0275 | AN8: =IF(AM8="","",AM8/SUMIFS($AM$3:$AM$1048576,$AV$3:$AV$1048576,"Regional Spend Addressability")) -> 0.12790698 | AO8: =IF(AN8="","",AN8*AG8) -> 0.007645372 | AP8: =IF(AN8="","",AN8*AH8) -> 0.012180209 | AQ8: =IF(AN8="","",AN8*AB8) -> 358139.53 | AR8: =IF(AN8="","",AN8*AC8) -> 434883.72 | AS8: =COUNTIFS($A$3:$A$1048576,A8,$BG$3:$BG$1048576,"<>") -> 41 | AT8: =10*(COUNTIFS($A$3:$A$1048576,A8,$AZ$3:$AZ$1048576,"Medium",$BG$3:$BG$1048576,"<>")*0.625+COUNTIFS($A$3:$A$1048576,A8,$AZ$3:$AZ$1048576,"Low",$BG$3:$BG$1048576,"<>")*0.25+COUNTIFS($A$3:$A$1048576,A8,$AZ$3:$AZ$1048576,"High",$BG$3:$BG$1048576,"<>")*0.874)/COUNTIFS($A$3:$A$1048576,A8,$AY$3:$AY$1048576,"<>") -> 7.18375 | AU8: =IF(AT8<5,"Low",IF(AT8<7.5,"Medium","High")) -> Medium | AV8: Geographic Sourcing Optimization for Cost Reduction | AW8: If significant spend for common goods/services occurs with suppliers located in high-cost regions, when similar quality suppliers exist in lower-cost regions (requires external data on regional cost indices), then a sourcing shift could yield savings due to reduced transportation and tarriffs | AX8: Client data insights | AZ8: =IF(ISERROR(_xlfn.XLOOKUP(CONCATENATE(A8,"_",AV8),'Reference-Proof pt impact flag'!$I$3:$I$1048576,'Reference-Proof pt impact flag'!$G$3:$G$1048576)),"",_xlfn.XLOOKUP(CONCATENATE(A8,"_",AV8),'Reference-Proof pt impact flag'!$I$3:$I$1048576,'Reference-Proof pt impact flag'!$G$3:$G$1048576)) | BF8: =_xlfn.XLOOKUP(CONCATENATE(H8,"_",AV8),'Test 2 - Proof points - GPT5'!$T:$T,'Test 2 - Proof points - GPT5'!$S:$S) -> #N/A | BG8: =_xlfn.XLOOKUP(CONCATENATE(H8,"_",AV8),'Test 2 -Proof points - Sonnet'!$AB:$AB,'Test 2 -Proof points - Sonnet'!$AA:$AA) -> #N/A | BJ8: What insights did I find? 95% of spend is concentrated in the India/Malaysia region with ricebran oil sourced from 10+ suppliers despite identical specifications. Over 75% of suppliers contribute to less than 20% of total spend, with average spend per supplier falling below industry benchmarks. This fragmentation limits economies of scale and negotiating power. Why is there a savings opportunity? Rising price volatility, ESG demands, and digital transformation are driving the need for supplier consolidation. The current fragmented supplier base prevents optimal volume leverage and increases administrative overhead. Consolidating volumes across similar SKUs can unlock better pricing through enhanced economies of scale. What should you do next? Consolidate suppliers like SHIVAGANGA, SIDDAGANGA, and SAKLECHA across ricebran and sunflower oils. Eliminate tail suppliers with sporadic volumes such as RAICHUR SOLVENTS. Leverage cross-category bundling opportunities with multi-oil suppliers and prioritize strategic partnerships with financially stable, ESG-compliant vendors. Potential risks involved Geographic concentration risk from consolidating with Indian suppliers could create vulnerability to regional disruptions. Heavy reliance on established suppliers may reduce negotiating leverage over time, while India's medium geopolitical risk rating could impact supply continuity and eliminate projected cost savings.
A9: 1 | B9: Consumer goods / products | C9: Food & beverages | D9: Plant-based | E9: Vegetable oils | G9: Value | H9: To what extent have you explored bundling of volumes across different types of vegetable oils to maximize economies of scale? | J9: Bundle volumes across SKUs to achieve savings derived from better economies of scale. Focus on high-spend SKUs that are purchased from multiple suppliers. Potentially consolidate SKUs within the tail | L9: Volume bundling | M9: =VLOOKUP(H9,'1_Value & risk levers'!$H$9:$O$1048576,2,FALSE) -> Not practiced / not explored so far | N9: =VLOOKUP(H9,'1_Value & risk levers'!$H$9:$O$1048576,3,FALSE) -> Ad-hoc initiatives to bundle volume across suppliers | O9: =VLOOKUP(H9,'1_Value & risk levers'!$H$9:$O$1048576,4,FALSE) -> Suppliers are evaluated for their product coverage at the time of sourcing | P9: =VLOOKUP(H9,'1_Value & risk levers'!$H$9:$O$1048576,5,FALSE) -> Comprehensive bundling strategy across all vegetable oils - following an optimization approach to identify the right volume mix across suppliers and SKUs | Q9: =IF(VLOOKUP(H9,'1_Value & risk levers'!$H$9:$T$1048576,13,FALSE)=0,"",VLOOKUP(H9,'1_Value & risk levers'!$H$9:$T$1048576,13,FALSE)) -> 3 | R9: =AVERAGEIFS($Q$3:$Q$1048576,$G$3:$G$1048576,"Value") -> 2 | S9: =AVERAGEIFS($Q$3:$Q$1048576,$G$3:$G$1048576,"Risk") -> #DIV/0! | W9: 0.04 | X9: 0.1 | Y9: =VLOOKUP(H9,'1_Value & risk levers'!$H$9:$O$1048576,8,FALSE) -> 0.8 | Z9: =(4-AVERAGEIFS($Q$3:$Q$1048576,$AV$3:$AV$1048576,"Inflation"))*(X9-W9)/4+W9 -> 0.07 | AA9: =Z9+(X9-W9)/4 -> 0.085 | AB9: =Y9*Z9*50000000 -> 2800000 | AC9: =Y9*AA9*50000000 -> 3400000 | AD9: =(COUNTA($Q$3:$Q$1048576)-COUNTIFS($Q$3:$Q$1048576,"",$A$3:$A$1048576,"<>"))/41 -> 7 | AE9: =AVERAGE($AT$3:$AT$1048576)/10 -> 0.48864541 | AF9: =IF(AE9<0.5,"Low",IF(AE9<0.75,"Medium","High")) -> Low | AG9: =Z9-(1-AE9)*2/100 -> 0.059772908 | AH9: =AA9+(1-AE9)*2/100 -> 0.095227092 | AI9: =Y9*AG9*50000000 -> 2390916.3 | AJ9: =Y9*AH9*50000000 -> 3809083.7 | AK9: =VLOOKUP(H9,'1_Value & risk levers'!$H$9:$O$1048576,6,FALSE) -> 0.02 | AL9: =VLOOKUP(H9,'1_Value & risk levers'!$H$9:$O$1048576,7,FALSE) -> 0.05 | AM9: =IF(ISERROR((AK9+((AL9-AK9)*(4-Q9))/4)),"",(AK9+((AL9-AK9)*(4-Q9))/4)) -> 0.0275 | AN9: =IF(AM9="","",AM9/SUMIFS($AM$3:$AM$1048576,$AV$3:$AV$1048576,"Regional Spend Addressability")) -> 0.12790698 | AO9: =IF(AN9="","",AN9*AG9) -> 0.007645372 | AP9: =IF(AN9="","",AN9*AH9) -> 0.012180209 | AQ9: =IF(AN9="","",AN9*AB9) -> 358139.53 | AR9: =IF(AN9="","",AN9*AC9) -> 434883.72 | AS9: =COUNTIFS($A$3:$A$1048576,A9,$BG$3:$BG$1048576,"<>") -> 41 | AT9: =10*(COUNTIFS($A$3:$A$1048576,A9,$AZ$3:$AZ$1048576,"Medium",$BG$3:$BG$1048576,"<>")*0.625+COUNTIFS($A$3:$A$1048576,A9,$AZ$3:$AZ$1048576,"Low",$BG$3:$BG$1048576,"<>")*0.25+COUNTIFS($A$3:$A$1048576,A9,$AZ$3:$AZ$1048576,"High",$BG$3:$BG$1048576,"<>")*0.874)/COUNTIFS($A$3:$A$1048576,A9,$AY$3:$AY$1048576,"<>") -> 7.18375 | AU9: =IF(AT9<5,"Low",IF(AT9<7.5,"Medium","High")) -> Medium | AV9: Price Variance for Identical Items/SKUs | AW9: If the same SKU, part number, or highly similar service description is purchased from different suppliers or at different times at widely varying unit prices (e.g., >15% variance) in the time frame, then there's an immediate, quantifiable savings opportunity through price standardization | AX9: Client data insights | AY9: Callout examples of the high spend SKUs that are not only purchased from mutliple suppliers, but also have price variations across suppliers. | AZ9: =IF(ISERROR(_xlfn.XLOOKUP(CONCATENATE(A9,"_",AV9),'Reference-Proof pt impact flag'!$I$3:$I$1048576,'Reference-Proof pt impact flag'!$G$3:$G$1048576)),"",_xlfn.XLOOKUP(CONCATENATE(A9,"_",AV9),'Reference-Proof pt impact flag'!$I$3:$I$1048576,'Reference-Proof pt impact flag'!$G$3:$G$1048576)) -> Medium | BA9: Contextualize and enrich the insights to make it 100-120 words summary explaining what you should do, with examples of reasons why. Structure this as bullet points, dont provide specific targets, and also talk about how future trends will impact this | BE9: Significant price variance opportunity identified for raw ricebran oil (Material 102038). Analysis reveals substantial unit price variations: (1) 2021 prices ranging from $1.38-$1.47/kg across suppliers for identical specifications - 6.5% variance; (2) Historical data shows even wider variations from $0.65-$1.47/kg across time periods, indicating 55%+ price variance; (3) Examples include SAKLECHA SOLVENTEX PVT. LTD. at $1.44/kg vs SIDDAGANGA OIL & BIO INDUSTRIES at $1.44/kg showing supplier pricing inconsistencies. Immediate opportunity to standardize pricing through: (1) Establishing target price bands based on commodity benchmarks plus processing margins; (2) Implementing quarterly price reviews aligned with ricebran oil commodity indices; (3) Challenging premium pricing from suppliers like UNIVERSAL AGRO FOOD INDUSTRIES and ANSUL OVERSEAS to achieve 5-8% cost reduction through price normalization. | BF9: =_xlfn.XLOOKUP(CONCATENATE(H9,"_",AV9),'Test 2 - Proof points - GPT5'!$T:$T,'Test 2 - Proof points - GPT5'!$S:$S) -> Insights: RAW RICEBRAN OIL (suppliers: 37, plants: 1) — price/kg 0.98-1.45 (median 1.27; spread 37%). Potential value ≈ $4,918,366 by aligning 50% volume to P25–P10 pricing. | Refined RBO Hair oil (suppliers: 10, plants: 2) — price/kg 1.24-1.77 (median 1.51; spread 35%). Potential value ≈ $1,019,151 by aligning 50% volume to P25–P10 pricing. | REFINED SUNFLOWER OIL EDIBLE (suppliers: 13, plants: 2) — price/kg 1.65-2.09 (median 1.86; spread 24%). Potential value ≈ $1,565,056 by aligning 50% volume to P25–P10 pricing. Actions: Run competitive re-bids on the cited SKUs, standardize specs, and lock indexed contracts where volatility is high. Prioritize suppliers with proven capability across Malaysia/Australia plants to converge to best-in-class pricing. | BG9: =_xlfn.XLOOKUP(CONCATENATE(H9,"_",AV9),'Test 2 -Proof points - Sonnet'!$AB:$AB,'Test 2 -Proof points - Sonnet'!$AA:$AA) -> #N/A | BH9: Why (Strategic Need): Rising price volatility, ESG demands, and digital procurement transformation are driving the need for supplier consolidation, cost efficiency, and risk mitigation. What (Insights Identified): 95% of spend is India/Malaysia-centric; ricebran oil alone is sourced from 10+ suppliers with identical specs. >75% of suppliers contribute to <20% of spend, and average spend per supplier trails industry benchmarks. How (Recommended Actions): Consolidate suppliers like SHIVAGANGA, SIDDAGANGA, and SAKLECHA across ricebran and sunflower oils. Eliminate tail suppliers with sporadic volumes (e.g., RAICHUR SOLVENTS). Leverage cross-category bundling with multi-oil suppliers. Prioritize strategic partnerships with financially stable, ESG-compliant vendors. Align sourcing strategy with market consolidation trends and future digitization shifts. | BJ9: What insights did I find? 95% of spend is concentrated in the India/Malaysia region with ricebran oil sourced from 10+ suppliers despite identical specifications. Over 75% of suppliers contribute to less than 20% of total spend, with average spend per supplier falling below industry benchmarks. This fragmentation limits economies of scale and negotiating power. Why is there a savings opportunity? Rising price volatility, ESG demands, and digital transformation are driving the need for supplier consolidation. The current fragmented supplier base prevents optimal volume leverage and increases administrative overhead. Consolidating volumes across similar SKUs can unlock better pricing through enhanced economies of scale. What should you do next? Consolidate suppliers like SHIVAGANGA, SIDDAGANGA, and SAKLECHA across ricebran and sunflower oils. Eliminate tail suppliers with sporadic volumes such as RAICHUR SOLVENTS. Leverage cross-category bundling opportunities with multi-oil suppliers and prioritize strategic partnerships with financially stable, ESG-compliant vendors. Potential risks involved Geographic concentration risk from consolidating with Indian suppliers could create vulnerability to regional disruptions. Heavy reliance on established suppliers may reduce negotiating leverage over time, while India's medium geopolitical risk rating could impact supply continuity and eliminate projected cost savings. | BO9: Yes | BV9: Yes
A10: 1 | B10: Consumer goods / products | C10: Food & beverages | D10: Plant-based | E10: Vegetable oils | G10: Value | H10: To what extent have you explored bundling of volumes across different types of vegetable oils to maximize economies of scale? | J10: Bundle volumes across SKUs to achieve savings derived from better economies of scale. Focus on high-spend SKUs that are purchased from multiple suppliers. Potentially consolidate SKUs within the tail | L10: Volume bundling | M10: =VLOOKUP(H10,'1_Value & risk levers'!$H$9:$O$1048576,2,FALSE) -> Not practiced / not explored so far | N10: =VLOOKUP(H10,'1_Value & risk levers'!$H$9:$O$1048576,3,FALSE) -> Ad-hoc initiatives to bundle volume across suppliers | O10: =VLOOKUP(H10,'1_Value & risk levers'!$H$9:$O$1048576,4,FALSE) -> Suppliers are evaluated for their product coverage at the time of sourcing | P10: =VLOOKUP(H10,'1_Value & risk levers'!$H$9:$O$1048576,5,FALSE) -> Comprehensive bundling strategy across all vegetable oils - following an optimization approach to identify the right volume mix across suppliers and SKUs | Q10: =IF(VLOOKUP(H10,'1_Value & risk levers'!$H$9:$T$1048576,13,FALSE)=0,"",VLOOKUP(H10,'1_Value & risk levers'!$H$9:$T$1048576,13,FALSE)) -> 3 | R10: =AVERAGEIFS($Q$3:$Q$1048576,$G$3:$G$1048576,"Value") -> 2 | S10: =AVERAGEIFS($Q$3:$Q$1048576,$G$3:$G$1048576,"Risk") -> #DIV/0! | W10: 0.04 | X10: 0.1 | Y10: =VLOOKUP(H10,'1_Value & risk levers'!$H$9:$O$1048576,8,FALSE) -> 0.8 | Z10: =(4-AVERAGEIFS($Q$3:$Q$1048576,$AV$3:$AV$1048576,"Inflation"))*(X10-W10)/4+W10 -> 0.07 | AA10: =Z10+(X10-W10)/4 -> 0.085 | AB10: =Y10*Z10*50000000 -> 2800000 | AC10: =Y10*AA10*50000000 -> 3400000 | AD10: =(COUNTA($Q$3:$Q$1048576)-COUNTIFS($Q$3:$Q$1048576,"",$A$3:$A$1048576,"<>"))/41 -> 7 | AE10: =AVERAGE($AT$3:$AT$1048576)/10 -> 0.48864541 | AF10: =IF(AE10<0.5,"Low",IF(AE10<0.75,"Medium","High")) -> Low | AG10: =Z10-(1-AE10)*2/100 -> 0.059772908 | AH10: =AA10+(1-AE10)*2/100 -> 0.095227092 | AI10: =Y10*AG10*50000000 -> 2390916.3 | AJ10: =Y10*AH10*50000000 -> 3809083.7 | AK10: =VLOOKUP(H10,'1_Value & risk levers'!$H$9:$O$1048576,6,FALSE) -> 0.02 | AL10: =VLOOKUP(H10,'1_Value & risk levers'!$H$9:$O$1048576,7,FALSE) -> 0.05 | AM10: =IF(ISERROR((AK10+((AL10-AK10)*(4-Q10))/4)),"",(AK10+((AL10-AK10)*(4-Q10))/4)) -> 0.0275 | AN10: =IF(AM10="","",AM10/SUMIFS($AM$3:$AM$1048576,$AV$3:$AV$1048576,"Regional Spend Addressability")) -> 0.12790698 | AO10: =IF(AN10="","",AN10*AG10) -> 0.007645372 | AP10: =IF(AN10="","",AN10*AH10) -> 0.012180209 | AQ10: =IF(AN10="","",AN10*AB10) -> 358139.53 | AR10: =IF(AN10="","",AN10*AC10) -> 434883.72 | AS10: =COUNTIFS($A$3:$A$1048576,A10,$BG$3:$BG$1048576,"<>") -> 41 | AT10: =10*(COUNTIFS($A$3:$A$1048576,A10,$AZ$3:$AZ$1048576,"Medium",$BG$3:$BG$1048576,"<>")*0.625+COUNTIFS($A$3:$A$1048576,A10,$AZ$3:$AZ$1048576,"Low",$BG$3:$BG$1048576,"<>")*0.25+COUNTIFS($A$3:$A$1048576,A10,$AZ$3:$AZ$1048576,"High",$BG$3:$BG$1048576,"<>")*0.874)/COUNTIFS($A$3:$A$1048576,A10,$AY$3:$AY$1048576,"<>") -> 7.18375 | AU10: =IF(AT10<5,"Low",IF(AT10<7.5,"Medium","High")) -> Medium | AV10: Invoice-to-PO Ratio Anomaly - Process Efficiency & Control Issue | AW10: If a high percentage of invoices lack an associated PO in the spend data, or if the average invoice value is significantly lower than the average PO value, then transactional control is weak, leading to potential "no PO, no pay" policy violations and higher processing costs | AX10: Client data insights | AZ10: =IF(ISERROR(_xlfn.XLOOKUP(CONCATENATE(A10,"_",AV10),'Reference-Proof pt impact flag'!$I$3:$I$1048576,'Reference-Proof pt impact flag'!$G$3:$G$1048576)),"",_xlfn.XLOOKUP(CONCATENATE(A10,"_",AV10),'Reference-Proof pt impact flag'!$I$3:$I$1048576,'Reference-Proof pt impact flag'!$G$3:$G$1048576)) | BF10: =_xlfn.XLOOKUP(CONCATENATE(H10,"_",AV10),'Test 2 - Proof points - GPT5'!$T:$T,'Test 2 - Proof points - GPT5'!$S:$S) -> #N/A | BG10: =_xlfn.XLOOKUP(CONCATENATE(H10,"_",AV10),'Test 2 -Proof points - Sonnet'!$AB:$AB,'Test 2 -Proof points - Sonnet'!$AA:$AA) -> #N/A | BJ10: What insights did I find? 95% of spend is concentrated in the India/Malaysia region with ricebran oil sourced from 10+ suppliers despite identical specifications. Over 75% of suppliers contribute to less than 20% of total spend, with average spend per supplier falling below industry benchmarks. This fragmentation limits economies of scale and negotiating power. Why is there a savings opportunity? Rising price volatility, ESG demands, and digital transformation are driving the need for supplier consolidation. The current fragmented supplier base prevents optimal volume leverage and increases administrative overhead. Consolidating volumes across similar SKUs can unlock better pricing through enhanced economies of scale. What should you do next? Consolidate suppliers like SHIVAGANGA, SIDDAGANGA, and SAKLECHA across ricebran and sunflower oils. Eliminate tail suppliers with sporadic volumes such as RAICHUR SOLVENTS. Leverage cross-category bundling opportunities with multi-oil suppliers and prioritize strategic partnerships with financially stable, ESG-compliant vendors. Potential risks involved Geographic concentration risk from consolidating with Indian suppliers could create vulnerability to regional disruptions. Heavy reliance on established suppliers may reduce negotiating leverage over time, while India's medium geopolitical risk rating could impact supply continuity and eliminate projected cost savings.
A11: 1 | B11: Consumer goods / products | C11: Food & beverages | D11: Plant-based | E11: Vegetable oils | G11: Value | H11: To what extent have you explored bundling of volumes across different types of vegetable oils to maximize economies of scale? | J11: Bundle volumes across SKUs to achieve savings derived from better economies of scale. Focus on high-spend SKUs that are purchased from multiple suppliers. Potentially consolidate SKUs within the tail | L11: Volume bundling | M11: =VLOOKUP(H11,'1_Value & risk levers'!$H$9:$O$1048576,2,FALSE) -> Not practiced / not explored so far | N11: =VLOOKUP(H11,'1_Value & risk levers'!$H$9:$O$1048576,3,FALSE) -> Ad-hoc initiatives to bundle volume across suppliers | O11: =VLOOKUP(H11,'1_Value & risk levers'!$H$9:$O$1048576,4,FALSE) -> Suppliers are evaluated for their product coverage at the time of sourcing | P11: =VLOOKUP(H11,'1_Value & risk levers'!$H$9:$O$1048576,5,FALSE) -> Comprehensive bundling strategy across all vegetable oils - following an optimization approach to identify the right volume mix across suppliers and SKUs | Q11: =IF(VLOOKUP(H11,'1_Value & risk levers'!$H$9:$T$1048576,13,FALSE)=0,"",VLOOKUP(H11,'1_Value & risk levers'!$H$9:$T$1048576,13,FALSE)) -> 3 | R11: =AVERAGEIFS($Q$3:$Q$1048576,$G$3:$G$1048576,"Value") -> 2 | S11: =AVERAGEIFS($Q$3:$Q$1048576,$G$3:$G$1048576,"Risk") -> #DIV/0! | W11: 0.04 | X11: 0.1 | Y11: =VLOOKUP(H11,'1_Value & risk levers'!$H$9:$O$1048576,8,FALSE) -> 0.8 | Z11: =(4-AVERAGEIFS($Q$3:$Q$1048576,$AV$3:$AV$1048576,"Inflation"))*(X11-W11)/4+W11 -> 0.07 | AA11: =Z11+(X11-W11)/4 -> 0.085 | AB11: =Y11*Z11*50000000 -> 2800000 | AC11: =Y11*AA11*50000000 -> 3400000 | AD11: =(COUNTA($Q$3:$Q$1048576)-COUNTIFS($Q$3:$Q$1048576,"",$A$3:$A$1048576,"<>"))/41 -> 7 | AE11: =AVERAGE($AT$3:$AT$1048576)/10 -> 0.48864541 | AF11: =IF(AE11<0.5,"Low",IF(AE11<0.75,"Medium","High")) -> Low | AG11: =Z11-(1-AE11)*2/100 -> 0.059772908 | AH11: =AA11+(1-AE11)*2/100 -> 0.095227092 | AI11: =Y11*AG11*50000000 -> 2390916.3 | AJ11: =Y11*AH11*50000000 -> 3809083.7 | AK11: =VLOOKUP(H11,'1_Value & risk levers'!$H$9:$O$1048576,6,FALSE) -> 0.02 | AL11: =VLOOKUP(H11,'1_Value & risk levers'!$H$9:$O$1048576,7,FALSE) -> 0.05 | AM11: =IF(ISERROR((AK11+((AL11-AK11)*(4-Q11))/4)),"",(AK11+((AL11-AK11)*(4-Q11))/4)) -> 0.0275 | AN11: =IF(AM11="","",AM11/SUMIFS($AM$3:$AM$1048576,$AV$3:$AV$1048576,"Regional Spend Addressability")) -> 0.12790698 | AO11: =IF(AN11="","",AN11*AG11) -> 0.007645372 | AP11: =IF(AN11="","",AN11*AH11) -> 0.012180209 | AQ11: =IF(AN11="","",AN11*AB11) -> 358139.53 | AR11: =IF(AN11="","",AN11*AC11) -> 434883.72 | AS11: =COUNTIFS($A$3:$A$1048576,A11,$BG$3:$BG$1048576,"<>") -> 41 | AT11: =10*(COUNTIFS($A$3:$A$1048576,A11,$AZ$3:$AZ$1048576,"Medium",$BG$3:$BG$1048576,"<>")*0.625+COUNTIFS($A$3:$A$1048576,A11,$AZ$3:$AZ$1048576,"Low",$BG$3:$BG$1048576,"<>")*0.25+COUNTIFS($A$3:$A$1048576,A11,$AZ$3:$AZ$1048576,"High",$BG$3:$BG$1048576,"<>")*0.874)/COUNTIFS($A$3:$A$1048576,A11,$AY$3:$AY$1048576,"<>") -> 7.18375 | AU11: =IF(AT11<5,"Low",IF(AT11<7.5,"Medium","High")) -> Medium | AV11: Average Spend per Supplier vs. Industry Benchmarks/Internal Targets | AW11: If the average spend per active supplier (total spend / total unique suppliers) is significantly lower than industry benchmarks or internal targets, especially when revenue is stagnant or declining, it could indicate excessive supplier fragmentation for the current business scale, driving administrative inefficiency | AX11: Client data insights | AY11: If avg spend/supplier > benchmark, call this out and mention how the vlaue compares against the Quartile1/Quartile3/median value of the benchmark | AZ11: =IF(ISERROR(_xlfn.XLOOKUP(CONCATENATE(A11,"_",AV11),'Reference-Proof pt impact flag'!$I$3:$I$1048576,'Reference-Proof pt impact flag'!$G$3:$G$1048576)),"",_xlfn.XLOOKUP(CONCATENATE(A11,"_",AV11),'Reference-Proof pt impact flag'!$I$3:$I$1048576,'Reference-Proof pt impact flag'!$G$3:$G$1048576)) -> Medium | BA11: Contextualize and enrich the insights to make it 100-120 words summary explaining what you should do, with examples of reasons why. Structure this as bullet points, dont provide specific targets, and also talk about how future trends will impact this | BF11: =_xlfn.XLOOKUP(CONCATENATE(H11,"_",AV11),'Test 2 - Proof points - GPT5'!$T:$T,'Test 2 - Proof points - GPT5'!$S:$S) -> Insights: Avg spend/supplier benchmarks (client distribution): Q1 $255,687, Median $723,229, Q3 $1,830,514. 22 suppliers sit above Q3, owning 74.6% of spend; tail (<1%) is 20.6% across 61 suppliers. Supplier base: 87 vendors; Top-1 share 8.6%; HHI ≈ 344 → fragmented. Leverage via bundled bids and two-tiering is feasible. Actions: Set target portfolio — strategic (top decile), preferred (Q2–Q3), and transactional (tail). Rebalance volumes to cap any single-supplier share at ≤35% and collapse long tail via cataloging/frameworks. | BG11: =_xlfn.XLOOKUP(CONCATENATE(H11,"_",AV11),'Test 2 -Proof points - Sonnet'!$AB:$AB,'Test 2 -Proof points - Sonnet'!$AA:$AA) -> â€¢ **Optimize supplier portfolio efficiency**: Current average spend per supplier appears below industry median for food ingredient procurement, indicating potential over-fragmentation in supplier base management. â€¢ **Focus on strategic supplier relationships**: Top suppliers like SHIVAGANGA and SIDDAGANGA represent higher-value partnerships that align with industry best practices for concentrated strategic sourcing relationships. â€¢ **Future procurement digitization demands**: Industry evolution toward integrated supplier ecosystems and automated procurement platforms will favor organizations with optimized supplier portfolios, making current consolidation efforts essential for maintaining competitive procurement operations and reducing administrative overhead costs. | BH11: Why (Strategic Need): Rising price volatility, ESG demands, and digital procurement transformation are driving the need for supplier consolidation, cost efficiency, and risk mitigation. What (Insights Identified): 95% of spend is India/Malaysia-centric; ricebran oil alone is sourced from 10+ suppliers with identical specs. >75% of suppliers contribute to <20% of spend, and average spend per supplier trails industry benchmarks. How (Recommended Actions): Consolidate suppliers like SHIVAGANGA, SIDDAGANGA, and SAKLECHA across ricebran and sunflower oils. Eliminate tail suppliers with sporadic volumes (e.g., RAICHUR SOLVENTS). Leverage cross-category bundling with multi-oil suppliers. Prioritize strategic partnerships with financially stable, ESG-compliant vendors. Align sourcing strategy with market consolidation trends and future digitization shifts. | BJ11: What insights did I find? 95% of spend is concentrated in the India/Malaysia region with ricebran oil sourced from 10+ suppliers despite identical specifications. Over 75% of suppliers contribute to less than 20% of total spend, with average spend per supplier falling below industry benchmarks. This fragmentation limits economies of scale and negotiating power. Why is there a savings opportunity? Rising price volatility, ESG demands, and digital transformation are driving the need for supplier consolidation. The current fragmented supplier base prevents optimal volume leverage and increases administrative overhead. Consolidating volumes across similar SKUs can unlock better pricing through enhanced economies of scale. What should you do next? Consolidate suppliers like SHIVAGANGA, SIDDAGANGA, and SAKLECHA across ricebran and sunflower oils. Eliminate tail suppliers with sporadic volumes such as RAICHUR SOLVENTS. Leverage cross-category bundling opportunities with multi-oil suppliers and prioritize strategic partnerships with financially stable, ESG-compliant vendors. Potential risks involved Geographic concentration risk from consolidating with Indian suppliers could create vulnerability to regional disruptions. Heavy reliance on established suppliers may reduce negotiating leverage over time, while India's medium geopolitical risk rating could impact supply continuity and eliminate projected cost savings. | BV11: Yes
A12: 1 | B12: Consumer goods / products | C12: Food & beverages | D12: Plant-based | E12: Vegetable oils | G12: Value | H12: To what extent have you explored bundling of volumes across different types of vegetable oils to maximize economies of scale? | J12: Bundle volumes across SKUs to achieve savings derived from better economies of scale. Focus on high-spend SKUs that are purchased from multiple suppliers. Potentially consolidate SKUs within the tail | L12: Volume bundling | M12: =VLOOKUP(H12,'1_Value & risk levers'!$H$9:$O$1048576,2,FALSE) -> Not practiced / not explored so far | N12: =VLOOKUP(H12,'1_Value & risk levers'!$H$9:$O$1048576,3,FALSE) -> Ad-hoc initiatives to bundle volume across suppliers | O12: =VLOOKUP(H12,'1_Value & risk levers'!$H$9:$O$1048576,4,FALSE) -> Suppliers are evaluated for their product coverage at the time of sourcing | P12: =VLOOKUP(H12,'1_Value & risk levers'!$H$9:$O$1048576,5,FALSE) -> Comprehensive bundling strategy across all vegetable oils - following an optimization approach to identify the right volume mix across suppliers and SKUs | Q12: =IF(VLOOKUP(H12,'1_Value & risk levers'!$H$9:$T$1048576,13,FALSE)=0,"",VLOOKUP(H12,'1_Value & risk levers'!$H$9:$T$1048576,13,FALSE)) -> 3 | R12: =AVERAGEIFS($Q$3:$Q$1048576,$G$3:$G$1048576,"Value") -> 2 | S12: =AVERAGEIFS($Q$3:$Q$1048576,$G$3:$G$1048576,"Risk") -> #DIV/0! | W12: 0.04 | X12: 0.1 | Y12: =VLOOKUP(H12,'1_Value & risk levers'!$H$9:$O$1048576,8,FALSE) -> 0.8 | Z12: =(4-AVERAGEIFS($Q$3:$Q$1048576,$AV$3:$AV$1048576,"Inflation"))*(X12-W12)/4+W12 -> 0.07 | AA12: =Z12+(X12-W12)/4 -> 0.085 | AB12: =Y12*Z12*50000000 -> 2800000 | AC12: =Y12*AA12*50000000 -> 3400000 | AD12: =(COUNTA($Q$3:$Q$1048576)-COUNTIFS($Q$3:$Q$1048576,"",$A$3:$A$1048576,"<>"))/41 -> 7 | AE12: =AVERAGE($AT$3:$AT$1048576)/10 -> 0.48864541 | AF12: =IF(AE12<0.5,"Low",IF(AE12<0.75,"Medium","High")) -> Low | AG12: =Z12-(1-AE12)*2/100 -> 0.059772908 | AH12: =AA12+(1-AE12)*2/100 -> 0.095227092 | AI12: =Y12*AG12*50000000 -> 2390916.3 | AJ12: =Y12*AH12*50000000 -> 3809083.7 | AK12: =VLOOKUP(H12,'1_Value & risk levers'!$H$9:$O$1048576,6,FALSE) -> 0.02 | AL12: =VLOOKUP(H12,'1_Value & risk levers'!$H$9:$O$1048576,7,FALSE) -> 0.05 | AM12: =IF(ISERROR((AK12+((AL12-AK12)*(4-Q12))/4)),"",(AK12+((AL12-AK12)*(4-Q12))/4)) -> 0.0275 | AN12: =IF(AM12="","",AM12/SUMIFS($AM$3:$AM$1048576,$AV$3:$AV$1048576,"Regional Spend Addressability")) -> 0.12790698 | AO12: =IF(AN12="","",AN12*AG12) -> 0.007645372 | AP12: =IF(AN12="","",AN12*AH12) -> 0.012180209 | AQ12: =IF(AN12="","",AN12*AB12) -> 358139.53 | AR12: =IF(AN12="","",AN12*AC12) -> 434883.72 | AS12: =COUNTIFS($A$3:$A$1048576,A12,$BG$3:$BG$1048576,"<>") -> 41 | AT12: =10*(COUNTIFS($A$3:$A$1048576,A12,$AZ$3:$AZ$1048576,"Medium",$BG$3:$BG$1048576,"<>")*0.625+COUNTIFS($A$3:$A$1048576,A12,$AZ$3:$AZ$1048576,"Low",$BG$3:$BG$1048576,"<>")*0.25+COUNTIFS($A$3:$A$1048576,A12,$AZ$3:$AZ$1048576,"High",$BG$3:$BG$1048576,"<>")*0.874)/COUNTIFS($A$3:$A$1048576,A12,$AY$3:$AY$1048576,"<>") -> 7.18375 | AU12: =IF(AT12<5,"Low",IF(AT12<7.5,"Medium","High")) -> Medium | AV12: Spend Impact on Product Profitability (Direct Material Focus) | AW12: If the cost of direct materials for a high-volume, low-margin product category shows significant volatility or consistent increases in spend data, while its revenue remains stable or declines, then it's directly eroding product profitability, requiring urgent procurement intervention | AX12: Client data insights | AZ12: =IF(ISERROR(_xlfn.XLOOKUP(CONCATENATE(A12,"_",AV12),'Reference-Proof pt impact flag'!$I$3:$I$1048576,'Reference-Proof pt impact flag'!$G$3:$G$1048576)),"",_xlfn.XLOOKUP(CONCATENATE(A12,"_",AV12),'Reference-Proof pt impact flag'!$I$3:$I$1048576,'Reference-Proof pt impact flag'!$G$3:$G$1048576)) | BF12: =_xlfn.XLOOKUP(CONCATENATE(H12,"_",AV12),'Test 2 - Proof points - GPT5'!$T:$T,'Test 2 - Proof points - GPT5'!$S:$S) -> #N/A | BG12: =_xlfn.XLOOKUP(CONCATENATE(H12,"_",AV12),'Test 2 -Proof points - Sonnet'!$AB:$AB,'Test 2 -Proof points - Sonnet'!$AA:$AA) -> #N/A | BJ12: What insights did I find? 95% of spend is concentrated in the India/Malaysia region with ricebran oil sourced from 10+ suppliers despite identical specifications. Over 75% of suppliers contribute to less than 20% of total spend, with average spend per supplier falling below industry benchmarks. This fragmentation limits economies of scale and negotiating power. Why is there a savings opportunity? Rising price volatility, ESG demands, and digital transformation are driving the need for supplier consolidation. The current fragmented supplier base prevents optimal volume leverage and increases administrative overhead. Consolidating volumes across similar SKUs can unlock better pricing through enhanced economies of scale. What should you do next? Consolidate suppliers like SHIVAGANGA, SIDDAGANGA, and SAKLECHA across ricebran and sunflower oils. Eliminate tail suppliers with sporadic volumes such as RAICHUR SOLVENTS. Leverage cross-category bundling opportunities with multi-oil suppliers and prioritize strategic partnerships with financially stable, ESG-compliant vendors. Potential risks involved Geographic concentration risk from consolidating with Indian suppliers could create vulnerability to regional disruptions. Heavy reliance on established suppliers may reduce negotiating leverage over time, while India's medium geopolitical risk rating could impact supply continuity and eliminate projected cost savings.
A13: 1 | B13: Consumer goods / products | C13: Food & beverages | D13: Plant-based | E13: Vegetable oils | G13: Value | H13: To what extent have you explored bundling of volumes across different types of vegetable oils to maximize economies of scale? | J13: Bundle volumes across SKUs to achieve savings derived from better economies of scale. Focus on high-spend SKUs that are purchased from multiple suppliers. Potentially consolidate SKUs within the tail | L13: Volume bundling | M13: =VLOOKUP(H13,'1_Value & risk levers'!$H$9:$O$1048576,2,FALSE) -> Not practiced / not explored so far | N13: =VLOOKUP(H13,'1_Value & risk levers'!$H$9:$O$1048576,3,FALSE) -> Ad-hoc initiatives to bundle volume across suppliers | O13: =VLOOKUP(H13,'1_Value & risk levers'!$H$9:$O$1048576,4,FALSE) -> Suppliers are evaluated for their product coverage at the time of sourcing | P13: =VLOOKUP(H13,'1_Value & risk levers'!$H$9:$O$1048576,5,FALSE) -> Comprehensive bundling strategy across all vegetable oils - following an optimization approach to identify the right volume mix across suppliers and SKUs | Q13: =IF(VLOOKUP(H13,'1_Value & risk levers'!$H$9:$T$1048576,13,FALSE)=0,"",VLOOKUP(H13,'1_Value & risk levers'!$H$9:$T$1048576,13,FALSE)) -> 3 | R13: =AVERAGEIFS($Q$3:$Q$1048576,$G$3:$G$1048576,"Value") -> 2 | S13: =AVERAGEIFS($Q$3:$Q$1048576,$G$3:$G$1048576,"Risk") -> #DIV/0! | W13: 0.04 | X13: 0.1 | Y13: =VLOOKUP(H13,'1_Value & risk levers'!$H$9:$O$1048576,8,FALSE) -> 0.8 | Z13: =(4-AVERAGEIFS($Q$3:$Q$1048576,$AV$3:$AV$1048576,"Inflation"))*(X13-W13)/4+W13 -> 0.07 | AA13: =Z13+(X13-W13)/4 -> 0.085 | AB13: =Y13*Z13*50000000 -> 2800000 | AC13: =Y13*AA13*50000000 -> 3400000 | AD13: =(COUNTA($Q$3:$Q$1048576)-COUNTIFS($Q$3:$Q$1048576,"",$A$3:$A$1048576,"<>"))/41 -> 7 | AE13: =AVERAGE($AT$3:$AT$1048576)/10 -> 0.48864541 | AF13: =IF(AE13<0.5,"Low",IF(AE13<0.75,"Medium","High")) -> Low | AG13: =Z13-(1-AE13)*2/100 -> 0.059772908 | AH13: =AA13+(1-AE13)*2/100 -> 0.095227092 | AI13: =Y13*AG13*50000000 -> 2390916.3 | AJ13: =Y13*AH13*50000000 -> 3809083.7 | AK13: =VLOOKUP(H13,'1_Value & risk levers'!$H$9:$O$1048576,6,FALSE) -> 0.02 | AL13: =VLOOKUP(H13,'1_Value & risk levers'!$H$9:$O$1048576,7,FALSE) -> 0.05 | AM13: =IF(ISERROR((AK13+((AL13-AK13)*(4-Q13))/4)),"",(AK13+((AL13-AK13)*(4-Q13))/4)) -> 0.0275 | AN13: =IF(AM13="","",AM13/SUMIFS($AM$3:$AM$1048576,$AV$3:$AV$1048576,"Regional Spend Addressability")) -> 0.12790698 | AO13: =IF(AN13="","",AN13*AG13) -> 0.007645372 | AP13: =IF(AN13="","",AN13*AH13) -> 0.012180209 | AQ13: =IF(AN13="","",AN13*AB13) -> 358139.53 | AR13: =IF(AN13="","",AN13*AC13) -> 434883.72 | AS13: =COUNTIFS($A$3:$A$1048576,A13,$BG$3:$BG$1048576,"<>") -> 41 | AT13: =10*(COUNTIFS($A$3:$A$1048576,A13,$AZ$3:$AZ$1048576,"Medium",$BG$3:$BG$1048576,"<>")*0.625+COUNTIFS($A$3:$A$1048576,A13,$AZ$3:$AZ$1048576,"Low",$BG$3:$BG$1048576,"<>")*0.25+COUNTIFS($A$3:$A$1048576,A13,$AZ$3:$AZ$1048576,"High",$BG$3:$BG$1048576,"<>")*0.874)/COUNTIFS($A$3:$A$1048576,A13,$AY$3:$AY$1048576,"<>") -> 7.18375 | AU13: =IF(AT13<5,"Low",IF(AT13<7.5,"Medium","High")) -> Medium | AV13: Category not optimized | AW13: Category spend/revenue vs benchmakrs | AX13: Client data insights | AZ13: =IF(ISERROR(_xlfn.XLOOKUP(CONCATENATE(A13,"_",AV13),'Reference-Proof pt impact flag'!$I$3:$I$1048576,'Reference-Proof pt impact flag'!$G$3:$G$1048576)),"",_xlfn.XLOOKUP(CONCATENATE(A13,"_",AV13),'Reference-Proof pt impact flag'!$I$3:$I$1048576,'Reference-Proof pt impact flag'!$G$3:$G$1048576)) | BF13: =_xlfn.XLOOKUP(CONCATENATE(H13,"_",AV13),'Test 2 - Proof points - GPT5'!$T:$T,'Test 2 - Proof points - GPT5'!$S:$S) -> #N/A | BG13: =_xlfn.XLOOKUP(CONCATENATE(H13,"_",AV13),'Test 2 -Proof points - Sonnet'!$AB:$AB,'Test 2 -Proof points - Sonnet'!$AA:$AA) -> #N/A | BJ13: What insights did I find? 95% of spend is concentrated in the India/Malaysia region with ricebran oil sourced from 10+ suppliers despite identical specifications. Over 75% of suppliers contribute to less than 20% of total spend, with average spend per supplier falling below industry benchmarks. This fragmentation limits economies of scale and negotiating power. Why is there a savings opportunity? Rising price volatility, ESG demands, and digital transformation are driving the need for supplier consolidation. The current fragmented supplier base prevents optimal volume leverage and increases administrative overhead. Consolidating volumes across similar SKUs can unlock better pricing through enhanced economies of scale. What should you do next? Consolidate suppliers like SHIVAGANGA, SIDDAGANGA, and SAKLECHA across ricebran and sunflower oils. Eliminate tail suppliers with sporadic volumes such as RAICHUR SOLVENTS. Leverage cross-category bundling opportunities with multi-oil suppliers and prioritize strategic partnerships with financially stable, ESG-compliant vendors. Potential risks involved Geographic concentration risk from consolidating with Indian suppliers could create vulnerability to regional disruptions. Heavy reliance on established suppliers may reduce negotiating leverage over time, while India's medium geopolitical risk rating could impact supply continuity and eliminate projected cost savings.
A14: 1 | B14: Consumer goods / products | C14: Food & beverages | D14: Plant-based | E14: Vegetable oils | G14: Value | H14: To what extent have you explored bundling of volumes across different types of vegetable oils to maximize economies of scale? | J14: Bundle volumes across SKUs to achieve savings derived from better economies of scale. Focus on high-spend SKUs that are purchased from multiple suppliers. Potentially consolidate SKUs within the tail | L14: Volume bundling | M14: =VLOOKUP(H14,'1_Value & risk levers'!$H$9:$O$1048576,2,FALSE) -> Not practiced / not explored so far | N14: =VLOOKUP(H14,'1_Value & risk levers'!$H$9:$O$1048576,3,FALSE) -> Ad-hoc initiatives to bundle volume across suppliers | O14: =VLOOKUP(H14,'1_Value & risk levers'!$H$9:$O$1048576,4,FALSE) -> Suppliers are evaluated for their product coverage at the time of sourcing | P14: =VLOOKUP(H14,'1_Value & risk levers'!$H$9:$O$1048576,5,FALSE) -> Comprehensive bundling strategy across all vegetable oils - following an optimization approach to identify the right volume mix across suppliers and SKUs | Q14: =IF(VLOOKUP(H14,'1_Value & risk levers'!$H$9:$T$1048576,13,FALSE)=0,"",VLOOKUP(H14,'1_Value & risk levers'!$H$9:$T$1048576,13,FALSE)) -> 3 | R14: =AVERAGEIFS($Q$3:$Q$1048576,$G$3:$G$1048576,"Value") -> 2 | S14: =AVERAGEIFS($Q$3:$Q$1048576,$G$3:$G$1048576,"Risk") -> #DIV/0! | W14: 0.04 | X14: 0.1 | Y14: =VLOOKUP(H14,'1_Value & risk levers'!$H$9:$O$1048576,8,FALSE) -> 0.8 | Z14: =(4-AVERAGEIFS($Q$3:$Q$1048576,$AV$3:$AV$1048576,"Inflation"))*(X14-W14)/4+W14 -> 0.07 | AA14: =Z14+(X14-W14)/4 -> 0.085 | AB14: =Y14*Z14*50000000 -> 2800000 | AC14: =Y14*AA14*50000000 -> 3400000 | AD14: =(COUNTA($Q$3:$Q$1048576)-COUNTIFS($Q$3:$Q$1048576,"",$A$3:$A$1048576,"<>"))/41 -> 7 | AE14: =AVERAGE($AT$3:$AT$1048576)/10 -> 0.48864541 | AF14: =IF(AE14<0.5,"Low",IF(AE14<0.75,"Medium","High")) -> Low | AG14: =Z14-(1-AE14)*2/100 -> 0.059772908 | AH14: =AA14+(1-AE14)*2/100 -> 0.095227092 | AI14: =Y14*AG14*50000000 -> 2390916.3 | AJ14: =Y14*AH14*50000000 -> 3809083.7 | AK14: =VLOOKUP(H14,'1_Value & risk levers'!$H$9:$O$1048576,6,FALSE) -> 0.02 | AL14: =VLOOKUP(H14,'1_Value & risk levers'!$H$9:$O$1048576,7,FALSE) -> 0.05 | AM14: =IF(ISERROR((AK14+((AL14-AK14)*(4-Q14))/4)),"",(AK14+((AL14-AK14)*(4-Q14))/4)) -> 0.0275 | AN14: =IF(AM14="","",AM14/SUMIFS($AM$3:$AM$1048576,$AV$3:$AV$1048576,"Regional Spend Addressability")) -> 0.12790698 | AO14: =IF(AN14="","",AN14*AG14) -> 0.007645372 | AP14: =IF(AN14="","",AN14*AH14) -> 0.012180209 | AQ14: =IF(AN14="","",AN14*AB14) -> 358139.53 | AR14: =IF(AN14="","",AN14*AC14) -> 434883.72 | AS14: =COUNTIFS($A$3:$A$1048576,A14,$BG$3:$BG$1048576,"<>") -> 41 | AT14: =10*(COUNTIFS($A$3:$A$1048576,A14,$AZ$3:$AZ$1048576,"Medium",$BG$3:$BG$1048576,"<>")*0.625+COUNTIFS($A$3:$A$1048576,A14,$AZ$3:$AZ$1048576,"Low",$BG$3:$BG$1048576,"<>")*0.25+COUNTIFS($A$3:$A$1048576,A14,$AZ$3:$AZ$1048576,"High",$BG$3:$BG$1048576,"<>")*0.874)/COUNTIFS($A$3:$A$1048576,A14,$AY$3:$AY$1048576,"<>") -> 7.18375 | AU14: =IF(AT14<5,"Low",IF(AT14<7.5,"Medium","High")) -> Medium | AV14: Opportunity to reshuffle supply base | AW14: Check client's top suppliers with the industry top suppliers (from benchmark database) | AX14: Client data insights | AZ14: =IF(ISERROR(_xlfn.XLOOKUP(CONCATENATE(A14,"_",AV14),'Reference-Proof pt impact flag'!$I$3:$I$1048576,'Reference-Proof pt impact flag'!$G$3:$G$1048576)),"",_xlfn.XLOOKUP(CONCATENATE(A14,"_",AV14),'Reference-Proof pt impact flag'!$I$3:$I$1048576,'Reference-Proof pt impact flag'!$G$3:$G$1048576)) | BF14: =_xlfn.XLOOKUP(CONCATENATE(H14,"_",AV14),'Test 2 - Proof points - GPT5'!$T:$T,'Test 2 - Proof points - GPT5'!$S:$S) -> #N/A | BG14: =_xlfn.XLOOKUP(CONCATENATE(H14,"_",AV14),'Test 2 -Proof points - Sonnet'!$AB:$AB,'Test 2 -Proof points - Sonnet'!$AA:$AA) -> #N/A | BJ14: What insights did I find? 95% of spend is concentrated in the India/Malaysia region with ricebran oil sourced from 10+ suppliers despite identical specifications. Over 75% of suppliers contribute to less than 20% of total spend, with average spend per supplier falling below industry benchmarks. This fragmentation limits economies of scale and negotiating power. Why is there a savings opportunity? Rising price volatility, ESG demands, and digital transformation are driving the need for supplier consolidation. The current fragmented supplier base prevents optimal volume leverage and increases administrative overhead. Consolidating volumes across similar SKUs can unlock better pricing through enhanced economies of scale. What should you do next? Consolidate suppliers like SHIVAGANGA, SIDDAGANGA, and SAKLECHA across ricebran and sunflower oils. Eliminate tail suppliers with sporadic volumes such as RAICHUR SOLVENTS. Leverage cross-category bundling opportunities with multi-oil suppliers and prioritize strategic partnerships with financially stable, ESG-compliant vendors. Potential risks involved Geographic concentration risk from consolidating with Indian suppliers could create vulnerability to regional disruptions. Heavy reliance on established suppliers may reduce negotiating leverage over time, while India's medium geopolitical risk rating could impact supply continuity and eliminate projected cost savings.
A15: 1 | B15: Consumer goods / products | C15: Food & beverages | D15: Plant-based | E15: Vegetable oils | G15: Value | H15: To what extent have you explored bundling of volumes across different types of vegetable oils to maximize economies of scale? | J15: Bundle volumes across SKUs to achieve savings derived from better economies of scale. Focus on high-spend SKUs that are purchased from multiple suppliers. Potentially consolidate SKUs within the tail | L15: Volume bundling | M15: =VLOOKUP(H15,'1_Value & risk levers'!$H$9:$O$1048576,2,FALSE) -> Not practiced / not explored so far | N15: =VLOOKUP(H15,'1_Value & risk levers'!$H$9:$O$1048576,3,FALSE) -> Ad-hoc initiatives to bundle volume across suppliers | O15: =VLOOKUP(H15,'1_Value & risk levers'!$H$9:$O$1048576,4,FALSE) -> Suppliers are evaluated for their product coverage at the time of sourcing | P15: =VLOOKUP(H15,'1_Value & risk levers'!$H$9:$O$1048576,5,FALSE) -> Comprehensive bundling strategy across all vegetable oils - following an optimization approach to identify the right volume mix across suppliers and SKUs | Q15: =IF(VLOOKUP(H15,'1_Value & risk levers'!$H$9:$T$1048576,13,FALSE)=0,"",VLOOKUP(H15,'1_Value & risk levers'!$H$9:$T$1048576,13,FALSE)) -> 3 | R15: =AVERAGEIFS($Q$3:$Q$1048576,$G$3:$G$1048576,"Value") -> 2 | S15: =AVERAGEIFS($Q$3:$Q$1048576,$G$3:$G$1048576,"Risk") -> #DIV/0! | W15: 0.04 | X15: 0.1 | Y15: =VLOOKUP(H15,'1_Value & risk levers'!$H$9:$O$1048576,8,FALSE) -> 0.8 | Z15: =(4-AVERAGEIFS($Q$3:$Q$1048576,$AV$3:$AV$1048576,"Inflation"))*(X15-W15)/4+W15 -> 0.07 | AA15: =Z15+(X15-W15)/4 -> 0.085 | AB15: =Y15*Z15*50000000 -> 2800000 | AC15: =Y15*AA15*50000000 -> 3400000 | AD15: =(COUNTA($Q$3:$Q$1048576)-COUNTIFS($Q$3:$Q$1048576,"",$A$3:$A$1048576,"<>"))/41 -> 7 | AE15: =AVERAGE($AT$3:$AT$1048576)/10 -> 0.48864541 | AF15: =IF(AE15<0.5,"Low",IF(AE15<0.75,"Medium","High")) -> Low | AG15: =Z15-(1-AE15)*2/100 -> 0.059772908 | AH15: =AA15+(1-AE15)*2/100 -> 0.095227092 | AI15: =Y15*AG15*50000000 -> 2390916.3 | AJ15: =Y15*AH15*50000000 -> 3809083.7 | AK15: =VLOOKUP(H15,'1_Value & risk levers'!$H$9:$O$1048576,6,FALSE) -> 0.02 | AL15: =VLOOKUP(H15,'1_Value & risk levers'!$H$9:$O$1048576,7,FALSE) -> 0.05 | AM15: =IF(ISERROR((AK15+((AL15-AK15)*(4-Q15))/4)),"",(AK15+((AL15-AK15)*(4-Q15))/4)) -> 0.0275 | AN15: =IF(AM15="","",AM15/SUMIFS($AM$3:$AM$1048576,$AV$3:$AV$1048576,"Regional Spend Addressability")) -> 0.12790698 | AO15: =IF(AN15="","",AN15*AG15) -> 0.007645372 | AP15: =IF(AN15="","",AN15*AH15) -> 0.012180209 | AQ15: =IF(AN15="","",AN15*AB15) -> 358139.53 | AR15: =IF(AN15="","",AN15*AC15) -> 434883.72 | AS15: =COUNTIFS($A$3:$A$1048576,A15,$BG$3:$BG$1048576,"<>") -> 41 | AT15: =10*(COUNTIFS($A$3:$A$1048576,A15,$AZ$3:$AZ$1048576,"Medium",$BG$3:$BG$1048576,"<>")*0.625+COUNTIFS($A$3:$A$1048576,A15,$AZ$3:$AZ$1048576,"Low",$BG$3:$BG$1048576,"<>")*0.25+COUNTIFS($A$3:$A$1048576,A15,$AZ$3:$AZ$1048576,"High",$BG$3:$BG$1048576,"<>")*0.874)/COUNTIFS($A$3:$A$1048576,A15,$AY$3:$AY$1048576,"<>") -> 7.18375 | AU15: =IF(AT15<5,"Low",IF(AT15<7.5,"Medium","High")) -> Medium | AV15: Market Size | AX15: Market driver | AZ15: =IF(ISERROR(_xlfn.XLOOKUP(CONCATENATE(A15,"_",AV15),'Reference-Proof pt impact flag'!$I$3:$I$1048576,'Reference-Proof pt impact flag'!$G$3:$G$1048576)),"",_xlfn.XLOOKUP(CONCATENATE(A15,"_",AV15),'Reference-Proof pt impact flag'!$I$3:$I$1048576,'Reference-Proof pt impact flag'!$G$3:$G$1048576)) | BF15: =_xlfn.XLOOKUP(CONCATENATE(H15,"_",AV15),'Test 2 - Proof points - GPT5'!$T:$T,'Test 2 - Proof points - GPT5'!$S:$S) -> #N/A | BG15: =_xlfn.XLOOKUP(CONCATENATE(H15,"_",AV15),'Test 2 -Proof points - Sonnet'!$AB:$AB,'Test 2 -Proof points - Sonnet'!$AA:$AA) -> #N/A | BJ15: What insights did I find? 95% of spend is concentrated in the India/Malaysia region with ricebran oil sourced from 10+ suppliers despite identical specifications. Over 75% of suppliers contribute to less than 20% of total spend, with average spend per supplier falling below industry benchmarks. This fragmentation limits economies of scale and negotiating power. Why is there a savings opportunity? Rising price volatility, ESG demands, and digital transformation are driving the need for supplier consolidation. The current fragmented supplier base prevents optimal volume leverage and increases administrative overhead. Consolidating volumes across similar SKUs can unlock better pricing through enhanced economies of scale. What should you do next? Consolidate suppliers like SHIVAGANGA, SIDDAGANGA, and SAKLECHA across ricebran and sunflower oils. Eliminate tail suppliers with sporadic volumes such as RAICHUR SOLVENTS. Leverage cross-category bundling opportunities with multi-oil suppliers and prioritize strategic partnerships with financially stable, ESG-compliant vendors. Potential risks involved Geographic concentration risk from consolidating with Indian suppliers could create vulnerability to regional disruptions. Heavy reliance on established suppliers may reduce negotiating leverage over time, while India's medium geopolitical risk rating could impact supply continuity and eliminate projected cost savings.
A16: 1 | B16: Consumer goods / products | C16: Food & beverages | D16: Plant-based | E16: Vegetable oils | G16: Value | H16: To what extent have you explored bundling of volumes across different types of vegetable oils to maximize economies of scale? | J16: Bundle volumes across SKUs to achieve savings derived from better economies of scale. Focus on high-spend SKUs that are purchased from multiple suppliers. Potentially consolidate SKUs within the tail | L16: Volume bundling | M16: =VLOOKUP(H16,'1_Value & risk levers'!$H$9:$O$1048576,2,FALSE) -> Not practiced / not explored so far | N16: =VLOOKUP(H16,'1_Value & risk levers'!$H$9:$O$1048576,3,FALSE) -> Ad-hoc initiatives to bundle volume across suppliers | O16: =VLOOKUP(H16,'1_Value & risk levers'!$H$9:$O$1048576,4,FALSE) -> Suppliers are evaluated for their product coverage at the time of sourcing | P16: =VLOOKUP(H16,'1_Value & risk levers'!$H$9:$O$1048576,5,FALSE) -> Comprehensive bundling strategy across all vegetable oils - following an optimization approach to identify the right volume mix across suppliers and SKUs | Q16: =IF(VLOOKUP(H16,'1_Value & risk levers'!$H$9:$T$1048576,13,FALSE)=0,"",VLOOKUP(H16,'1_Value & risk levers'!$H$9:$T$1048576,13,FALSE)) -> 3 | R16: =AVERAGEIFS($Q$3:$Q$1048576,$G$3:$G$1048576,"Value") -> 2 | S16: =AVERAGEIFS($Q$3:$Q$1048576,$G$3:$G$1048576,"Risk") -> #DIV/0! | W16: 0.04 | X16: 0.1 | Y16: =VLOOKUP(H16,'1_Value & risk levers'!$H$9:$O$1048576,8,FALSE) -> 0.8 | Z16: =(4-AVERAGEIFS($Q$3:$Q$1048576,$AV$3:$AV$1048576,"Inflation"))*(X16-W16)/4+W16 -> 0.07 | AA16: =Z16+(X16-W16)/4 -> 0.085 | AB16: =Y16*Z16*50000000 -> 2800000 | AC16: =Y16*AA16*50000000 -> 3400000 | AD16: =(COUNTA($Q$3:$Q$1048576)-COUNTIFS($Q$3:$Q$1048576,"",$A$3:$A$1048576,"<>"))/41 -> 7 | AE16: =AVERAGE($AT$3:$AT$1048576)/10 -> 0.48864541 | AF16: =IF(AE16<0.5,"Low",IF(AE16<0.75,"Medium","High")) -> Low | AG16: =Z16-(1-AE16)*2/100 -> 0.059772908 | AH16: =AA16+(1-AE16)*2/100 -> 0.095227092 | AI16: =Y16*AG16*50000000 -> 2390916.3 | AJ16: =Y16*AH16*50000000 -> 3809083.7 | AK16: =VLOOKUP(H16,'1_Value & risk levers'!$H$9:$O$1048576,6,FALSE) -> 0.02 | AL16: =VLOOKUP(H16,'1_Value & risk levers'!$H$9:$O$1048576,7,FALSE) -> 0.05 | AM16: =IF(ISERROR((AK16+((AL16-AK16)*(4-Q16))/4)),"",(AK16+((AL16-AK16)*(4-Q16))/4)) -> 0.0275 | AN16: =IF(AM16="","",AM16/SUMIFS($AM$3:$AM$1048576,$AV$3:$AV$1048576,"Regional Spend Addressability")) -> 0.12790698 | AO16: =IF(AN16="","",AN16*AG16) -> 0.007645372 | AP16: =IF(AN16="","",AN16*AH16) -> 0.012180209 | AQ16: =IF(AN16="","",AN16*AB16) -> 358139.53 | AR16: =IF(AN16="","",AN16*AC16) -> 434883.72 | AS16: =COUNTIFS($A$3:$A$1048576,A16,$BG$3:$BG$1048576,"<>") -> 41 | AT16: =10*(COUNTIFS($A$3:$A$1048576,A16,$AZ$3:$AZ$1048576,"Medium",$BG$3:$BG$1048576,"<>")*0.625+COUNTIFS($A$3:$A$1048576,A16,$AZ$3:$AZ$1048576,"Low",$BG$3:$BG$1048576,"<>")*0.25+COUNTIFS($A$3:$A$1048576,A16,$AZ$3:$AZ$1048576,"High",$BG$3:$BG$1048576,"<>")*0.874)/COUNTIFS($A$3:$A$1048576,A16,$AY$3:$AY$1048576,"<>") -> 7.18375 | AU16: =IF(AT16<5,"Low",IF(AT16<7.5,"Medium","High")) -> Medium | AV16: Market Growth Rate | AX16: Market driver | AZ16: =IF(ISERROR(_xlfn.XLOOKUP(CONCATENATE(A16,"_",AV16),'Reference-Proof pt impact flag'!$I$3:$I$1048576,'Reference-Proof pt impact flag'!$G$3:$G$1048576)),"",_xlfn.XLOOKUP(CONCATENATE(A16,"_",AV16),'Reference-Proof pt impact flag'!$I$3:$I$1048576,'Reference-Proof pt impact flag'!$G$3:$G$1048576)) | BF16: =_xlfn.XLOOKUP(CONCATENATE(H16,"_",AV16),'Test 2 - Proof points - GPT5'!$T:$T,'Test 2 - Proof points - GPT5'!$S:$S) -> #N/A | BG16: =_xlfn.XLOOKUP(CONCATENATE(H16,"_",AV16),'Test 2 -Proof points - Sonnet'!$AB:$AB,'Test 2 -Proof points - Sonnet'!$AA:$AA) -> #N/A | BJ16: What insights did I find? 95% of spend is concentrated in the India/Malaysia region with ricebran oil sourced from 10+ suppliers despite identical specifications. Over 75% of suppliers contribute to less than 20% of total spend, with average spend per supplier falling below industry benchmarks. This fragmentation limits economies of scale and negotiating power. Why is there a savings opportunity? Rising price volatility, ESG demands, and digital transformation are driving the need for supplier consolidation. The current fragmented supplier base prevents optimal volume leverage and increases administrative overhead. Consolidating volumes across similar SKUs can unlock better pricing through enhanced economies of scale. What should you do next? Consolidate suppliers like SHIVAGANGA, SIDDAGANGA, and SAKLECHA across ricebran and sunflower oils. Eliminate tail suppliers with sporadic volumes such as RAICHUR SOLVENTS. Leverage cross-category bundling opportunities with multi-oil suppliers and prioritize strategic partnerships with financially stable, ESG-compliant vendors. Potential risks involved Geographic concentration risk from consolidating with Indian suppliers could create vulnerability to regional disruptions. Heavy reliance on established suppliers may reduce negotiating leverage over time, while India's medium geopolitical risk rating could impact supply continuity and eliminate projected cost savings.
A17: 1 | B17: Consumer goods / products | C17: Food & beverages | D17: Plant-based | E17: Vegetable oils | G17: Value | H17: To what extent have you explored bundling of volumes across different types of vegetable oils to maximize economies of scale? | J17: Bundle volumes across SKUs to achieve savings derived from better economies of scale. Focus on high-spend SKUs that are purchased from multiple suppliers. Potentially consolidate SKUs within the tail | L17: Volume bundling | M17: =VLOOKUP(H17,'1_Value & risk levers'!$H$9:$O$1048576,2,FALSE) -> Not practiced / not explored so far | N17: =VLOOKUP(H17,'1_Value & risk levers'!$H$9:$O$1048576,3,FALSE) -> Ad-hoc initiatives to bundle volume across suppliers | O17: =VLOOKUP(H17,'1_Value & risk levers'!$H$9:$O$1048576,4,FALSE) -> Suppliers are evaluated for their product coverage at the time of sourcing | P17: =VLOOKUP(H17,'1_Value & risk levers'!$H$9:$O$1048576,5,FALSE) -> Comprehensive bundling strategy across all vegetable oils - following an optimization approach to identify the right volume mix across suppliers and SKUs | Q17: =IF(VLOOKUP(H17,'1_Value & risk levers'!$H$9:$T$1048576,13,FALSE)=0,"",VLOOKUP(H17,'1_Value & risk levers'!$H$9:$T$1048576,13,FALSE)) -> 3 | R17: =AVERAGEIFS($Q$3:$Q$1048576,$G$3:$G$1048576,"Value") -> 2 | S17: =AVERAGEIFS($Q$3:$Q$1048576,$G$3:$G$1048576,"Risk") -> #DIV/0! | W17: 0.04 | X17: 0.1 | Y17: =VLOOKUP(H17,'1_Value & risk levers'!$H$9:$O$1048576,8,FALSE) -> 0.8 | Z17: =(4-AVERAGEIFS($Q$3:$Q$1048576,$AV$3:$AV$1048576,"Inflation"))*(X17-W17)/4+W17 -> 0.07 | AA17: =Z17+(X17-W17)/4 -> 0.085 | AB17: =Y17*Z17*50000000 -> 2800000 | AC17: =Y17*AA17*50000000 -> 3400000 | AD17: =(COUNTA($Q$3:$Q$1048576)-COUNTIFS($Q$3:$Q$1048576,"",$A$3:$A$1048576,"<>"))/41 -> 7 | AE17: =AVERAGE($AT$3:$AT$1048576)/10 -> 0.48864541 | AF17: =IF(AE17<0.5,"Low",IF(AE17<0.75,"Medium","High")) -> Low | AG17: =Z17-(1-AE17)*2/100 -> 0.059772908 | AH17: =AA17+(1-AE17)*2/100 -> 0.095227092 | AI17: =Y17*AG17*50000000 -> 2390916.3 | AJ17: =Y17*AH17*50000000 -> 3809083.7 | AK17: =VLOOKUP(H17,'1_Value & risk levers'!$H$9:$O$1048576,6,FALSE) -> 0.02 | AL17: =VLOOKUP(H17,'1_Value & risk levers'!$H$9:$O$1048576,7,FALSE) -> 0.05 | AM17: =IF(ISERROR((AK17+((AL17-AK17)*(4-Q17))/4)),"",(AK17+((AL17-AK17)*(4-Q17))/4)) -> 0.0275 | AN17: =IF(AM17="","",AM17/SUMIFS($AM$3:$AM$1048576,$AV$3:$AV$1048576,"Regional Spend Addressability")) -> 0.12790698 | AO17: =IF(AN17="","",AN17*AG17) -> 0.007645372 | AP17: =IF(AN17="","",AN17*AH17) -> 0.012180209 | AQ17: =IF(AN17="","",AN17*AB17) -> 358139.53 | AR17: =IF(AN17="","",AN17*AC17) -> 434883.72 | AS17: =COUNTIFS($A$3:$A$1048576,A17,$BG$3:$BG$1048576,"<>") -> 41 | AT17: =10*(COUNTIFS($A$3:$A$1048576,A17,$AZ$3:$AZ$1048576,"Medium",$BG$3:$BG$1048576,"<>")*0.625+COUNTIFS($A$3:$A$1048576,A17,$AZ$3:$AZ$1048576,"Low",$BG$3:$BG$1048576,"<>")*0.25+COUNTIFS($A$3:$A$1048576,A17,$AZ$3:$AZ$1048576,"High",$BG$3:$BG$1048576,"<>")*0.874)/COUNTIFS($A$3:$A$1048576,A17,$AY$3:$AY$1048576,"<>") -> 7.18375 | AU17: =IF(AT17<5,"Low",IF(AT17<7.5,"Medium","High")) -> Medium | AV17: Market Maturity | AX17: Market driver | AZ17: =IF(ISERROR(_xlfn.XLOOKUP(CONCATENATE(A17,"_",AV17),'Reference-Proof pt impact flag'!$I$3:$I$1048576,'Reference-Proof pt impact flag'!$G$3:$G$1048576)),"",_xlfn.XLOOKUP(CONCATENATE(A17,"_",AV17),'Reference-Proof pt impact flag'!$I$3:$I$1048576,'Reference-Proof pt impact flag'!$G$3:$G$1048576)) | BF17: =_xlfn.XLOOKUP(CONCATENATE(H17,"_",AV17),'Test 2 - Proof points - GPT5'!$T:$T,'Test 2 - Proof points - GPT5'!$S:$S) -> #N/A | BG17: =_xlfn.XLOOKUP(CONCATENATE(H17,"_",AV17),'Test 2 -Proof points - Sonnet'!$AB:$AB,'Test 2 -Proof points - Sonnet'!$AA:$AA) -> #N/A | BJ17: What insights did I find? 95% of spend is concentrated in the India/Malaysia region with ricebran oil sourced from 10+ suppliers despite identical specifications. Over 75% of suppliers contribute to less than 20% of total spend, with average spend per supplier falling below industry benchmarks. This fragmentation limits economies of scale and negotiating power. Why is there a savings opportunity? Rising price volatility, ESG demands, and digital transformation are driving the need for supplier consolidation. The current fragmented supplier base prevents optimal volume leverage and increases administrative overhead. Consolidating volumes across similar SKUs can unlock better pricing through enhanced economies of scale. What should you do next? Consolidate suppliers like SHIVAGANGA, SIDDAGANGA, and SAKLECHA across ricebran and sunflower oils. Eliminate tail suppliers with sporadic volumes such as RAICHUR SOLVENTS. Leverage cross-category bundling opportunities with multi-oil suppliers and prioritize strategic partnerships with financially stable, ESG-compliant vendors. Potential risks involved Geographic concentration risk from consolidating with Indian suppliers could create vulnerability to regional disruptions. Heavy reliance on established suppliers may reduce negotiating leverage over time, while India's medium geopolitical risk rating could impact supply continuity and eliminate projected cost savings.
